Workbook
Name functions: Lists!$B$11:$I$11
Name verticals: Lists!$B$1:$F$1
Name research_status: Lists!$B$4:$E$4
Name tiers: Lists!$B$3:$D$3
Name relationship_source: Lists!$B$13:$H$13
Name persona_status: Lists!$B$7:$G$7
Name signal_types: Lists!$B$2:$G$2
Name yes_no: Lists!$B$10:$C$10
Name account_names: Accounts!$B$2:$B$41
Name owners: Lists!$B$9:$F$9
Name seniority: Lists!$B$12:$G$12
Name outreach_status: Lists!$B$5:$F$5
Name meeting_status: Lists!$B$6:$G$6
Name activity_types: Lists!$B$8:$I$8

Sheet Form Responses 1
A1: Timestamp | B1: Show Day | C1: Time Block | D1: Account | E1: Persona Name | F1: Title | G1: Channel | H1: Meeting Type | I1: Location | J1: Interest (1-5) | K1: Urgency (1-5) | L1: Influence (1-5) | M1: Use-Case Fit (1-5) | N1: Requested Asset | O1: Need Primo? | P1: Next Step | Q1: Owner | R1: Due Date | S1: Follow-Up Template | T1: Outcome | U1: Notes
A2: 46106.495 | B2: Day 1 | C2: 10:00-12:00 | D2: Danone | E2: Test Contact | F2: VP Supply Chain | G2: Booth | H2: Discovery | I2: MODEX Floor | J2: 5 | K2: 4 | L2: 5 | M2: 5 | N2: Infographic | O2: Yes | P2: Send Danone Infographic | Q2: Jake | R2: 46107 | T2: Qualified | U2: Test submission from setup validation

Sheet README
A1: MODEX Campaign RevOps Engine
A2: Purpose
A3: Run the MODEX meeting campaign for Jake / FreightRoll in one place: rank accounts, research personas, track intros and outreach, and manage booked meetings.
A5: How to use
A6: 1. Start in Accounts: update scores, statuses, current motion, next actions, and due dates.
A7: 2. Add named targets in Personas as you identify them. The sheet pulls the account score automatically.
A8: 3. Log every touch in Activities. If it happened, log it. CRM discipline beats optimism theater.
A9: 4. Move real conversations into Meetings and tag whether Primo will join for social proof.
A10: 5. Use Dashboard in standups to see pipeline, coverage gaps, and which accounts need executive air cover.
A13: Scoring logic
A14: Priority Score is a weighted 0-100 score built from ICP fit, MODEX signal, Primo story fit, warm intro strength, strategic value, and meeting ease.
A15: Weights and tier cutoffs live on the hidden Lists sheet so you can tune the machine without rebuilding formulas.
A17: Color guide
A18: Blue text / pale blue fill | B18: Inputs you should update
A19: Green text / pale green fill | B19: Linked or imported reference fields
A20: Black text / white fill | B20: Formulas and outputs
A21: Gray text / gray fill | B21: Static labels and constants
A22: Purple fill | B22: Control logic
A25: Source note
A26: Seed account signals came from official MODEX 2026 pages and the official past-attendee PDF. URLs are stored in the Accounts sheet for easy fact checking.
A28: New in Phase 3+
A29: Hunt Plan | B29: Account-by-account hunting order, title lanes, proof assets, and timing.
A30: Search Strings | B30: Repeatable LinkedIn / Sales Nav / Google queries for persona discovery.
A31: Outreach Waves | B31: Wave-based operating cadence to sequence warm intros, must-book targets, and opportunistic accounts.
A32: Meeting Briefs | B32: Fast pre-meeting prep with why-now angle, likely pains, and asset checklist.
A34: UI/UX update | B34: Accounts and Personas were refactored into compact operating views: filters on, panes frozen, detail columns hidden, and key intelligence pulled forward so the main tabs can be run without horizontal-scroll hell.
A35: Patch Notes | B35: Use the new Actionable Intel tab to collect facility footprint, trigger events, tech-stack clues, site leaders, and carrier pain evidence before outreach.
A36: Phase 16 patch: Live Capture now pulls directly from Form Responses 1, Mobile Capture Lite mirrors Live Capture cleanly, and Follow-Up Engine uses non-circular formulas.
A37: This version is designed so intake still works even if Apps Script append behavior is imperfect in Google Sheets.
A38: Added embedded custom infographics for the Top 20 accounts plus a compact asset register and gallery. Accounts and Personas tabs were reworked to reduce horizontal scrolling.
A40: Phase 9 additions
A41: • Jake Battlecards: account-specific meeting theses, discovery questions, objections, counters, and asks.
A42: • Jake Talk Tracks: booth-safe scripts for opening, diagnosing, bridging to Primo, and closing.
A43: • Objection Map: reusable counters by objection type.
A44: • MODEX Close Plan: what a good meeting outcome looks like account by account.
A46: Phase 11 | B46: MODEX Command Sheet
A47: Phase 12 | B47: Follow-Up Engine + Follow-Up Templates
A48: New in phase 13
A49: - Live Capture tab for in-the-moment meeting notes, scoring, follow-up assignment, and due dates.
A50: - Field View tab for a no-scroll top-20 operating view with live captures, hot signals, overdue follow-ups, and last-activity dates.
A51: - Account Radar tab for heat-based triage across meetings, live captures, and intro availability.
A53: Phase 14 additions
A54: • Jake Queue: compact daily triage board for hot captures, due follow-ups, intros, and backup targets.
A55: • Apps Script Install: step-by-step setup for the companion Google Apps Script project.
A56: • Automation Map: function-by-function summary of the menu/button workflow.
A57: • Mobile Capture Lite: phone-friendly scratchpad for fast entry on the floor.
A58: • Jake Daily Brief: smallest possible daily command view.
A60: Phase 16 | QR journey enhancement
A61: Use QR Journey for the master scan display and QR Assets for account-specific prefilled scans. After uploading to Google Sheets, run setupMobileForm() and then buildQrAssets().

Sheet MODEX Command Sheet
A1: MODEX Command Sheet
A2: Run-of-show for April 13–16, 2026 in Atlanta. Hall A is open 9:00 AM–5:00 PM Monday–Wednesday and 9:00 AM–1:00 PM Thursday; Halls B & C open 10:00 AM–5:00 PM Monday–Wednesday and 9:00 AM–1:00 PM Thursday. Monday keynote at 9:00 AM: Richard McPhail, The Home Depot.
A3: Sources: https://www.modexshow.com/about | https://www.modexshow.com/education
A4: Show Days | D4: Top Accounts in Rotation | G4: Leave-Behinds Ready | I4: Follow-Up Templates
A5: 4 | D5: =COUNTA('Top 20 Board'!$B$2:$B$21) -> 20 | G5: =COUNTA('Leave-Behind Index'!$A:$A)-1 -> 12 | I5: =COUNTA('Follow-Up Templates'!$A:$A)-4 -> 5
A7: Day | B7: Time Block | C7: Focus | D7: Primary Accounts | E7: Backup Accounts | F7: Hall / Anchor | G7: Primary Asset | H7: Success Criteria | I7: Status | J7: Notes
A8: Mon 4/13 | B8: 8:15–8:50 | C8: Pre-floor prep + account triage | D8: Danone; General Mills; The Home Depot | E8: Hormel Foods; JM Smucker | F8: Lobby / coffee near Hall A | G8: Top 3 leave-behinds + battlecards | H8: Jake aligned on top 6 targets before keynote | I8: Planned
A9: Mon 4/13 | B9: 9:00–10:00 | C9: Home Depot keynote intercept window | D9: The Home Depot | E9: Barnes & Noble; Kenco Logistics Services | F9: Hall A keynote area | G9: Home Depot leave-behind + battlecard | H9: Secure post-keynote intro or referral path | I9: Planned
A10: Mon 4/13 | B10: 10:00–11:30 | C10: Food & Bev wave 1 | D10: Danone; General Mills; Frito-Lay | E10: Hormel Foods; JM Smucker | F10: Hall B/C high-traffic software zones | G10: Danone / GM / Frito infographics | H10: Book 2 meetings or 3 strong follow-up paths | I10: Planned
A11: Mon 4/13 | B11: 11:30–1:00 | C11: Lunch meetings / corridor catches | D11: Danone; The Home Depot | E11: Diageo; Georgia Pacific | F11: Any seated lunch area | G11: 2 printed leave-behinds + digital gallery | H11: One sit-down meeting or scheduled follow-up | I11: Planned
A12: Mon 4/13 | B12: 1:00–3:00 | C12: Food & Bev wave 2 | D12: Diageo; Hormel Foods; JM Smucker | E12: Dawn Foods; Del Monte Foods | F12: Hall B/C | G12: Diageo / Hormel / Smucker infographics | H12: Advance 3 accounts to next step | I12: Planned
A13: Mon 4/13 | B13: 3:00–5:00 | C13: Retail / industrial wave | D13: Georgia Pacific; H-E-B; Hyundai Motor America | E13: Honda; John Deere | F13: Hall A / crossover aisles | G13: GP / H-E-B / Hyundai battlecards | H13: Log 6 quality conversations | I13: Planned
A14: Tue 4/14 | B14: 9:00–10:00 | C14: Keynote networking / AI wedge | D14: FedEx; Kenco Logistics Services | E14: IKEA; Dollar General | F14: Keynote area / foyer | G14: Kenco + FedEx one-pagers | H14: Find 2 warm referrals from ecosystem players | I14: Planned
A15: Tue 4/14 | B15: 10:00–12:00 | C15: Top-10 must-book sweep | D15: Danone; General Mills; Frito-Lay; The Home Depot | E15: Diageo; Hormel Foods | F15: Hall B/C then Hall A | G15: Top 10 leave-behinds | H15: Book 3 meetings and identify 3 alternates | I15: Planned
A16: Tue 4/14 | B16: 1:00–3:00 | C16: Manufacturing / automotive sweep | D16: Hyundai Motor America; Honda; John Deere | E16: Georgia Pacific; Del Monte Foods | F16: Hall A/B | G16: Hyundai / Honda / Deere infographics | H16: Open 2 meetings and 3 real follow-ups | I16: Planned
A17: Tue 4/14 | B17: 3:00–5:00 | C17: Retail / grocery / value channel | D17: H-E-B; Dollar General; Dollar Tree; IKEA | E17: Barnes & Noble | F17: Hall A | G17: Retail leave-behinds | H17: Find operator-level buyers and transportation leads | I17: Planned
A18: Wed 4/15 | B18: 9:00–10:00 | C18: Keynote + partner intelligence | D18: Kenco Logistics Services; Barnes & Noble | E18: FedEx | F18: Keynote area | G18: Kenco / B&N battlecards | H18: Secure ecosystem insight or referral | I18: Planned
A19: Wed 4/15 | B19: 10:00–12:00 | C19: Close-plan day: convert interest to meetings | D19: All open P1 accounts | E19: Any top-20 backup | F19: Hall B/C software zones | G19: Battlecards + calendar booking links | H19: Turn floor interest into calendar holds | I19: Planned
... A23: Thu 4/16 | B23: 11:00–1:00 | C23: Last-call triage + follow-up staging | D23: All active accounts | E23: Any missed account | F23: Exit paths / coffee / lobby | G23: Follow-up templates + notes | H23: Every quality conversation assigned a next step | I23: Planned

Sheet Live Capture
A1: Timestamp
A2: Fast capture sheet for live conversations. Log the interaction, score the signal, set the next step, and keep the floor moving.
A3: Scoring: Heat Score = Interest + Urgency + Influence + Use-Case Fit + 2 bonus if Primo proof requested. Filter for HOT / WARM when triaging post-meeting work.
A5: Capture ID | B5: Logged At | C5: Show Day | D5: Time Block | E5: Account | F5: Persona Name | G5: Title | H5: Channel | I5: Meeting Type | J5: Location | K5: Interest (1-5) | L5: Urgency (1-5) | M5: Influence (1-5) | N5: Use-Case Fit (1-5) | O5: Requested Asset | P5: Need Primo? | Q5: Next Step | R5: Owner | S5: Due Date | T5: Follow-Up Template | U5: Outcome | V5: Heat Score | W5: Band | X5: Status | Y5: Notes
A6: =IF(E6="","","LC-"&TEXT(ROW()-5,"000")) -> LC-001 | B6: {=IFERROR(IF(INDEX('Form Responses 1'!$D:$D,ROW()-4)="","",INDEX('Form Responses 1'!$A:$A,ROW()-4)),"")} -> 46106.495 | C6: {=IFERROR(IF(INDEX('Form Responses 1'!$D:$D,ROW()-4)="","",INDEX('Form Responses 1'!$B:$B,ROW()-4)),"")} -> Day 1 | D6: {=IFERROR(IF(INDEX('Form Responses 1'!$D:$D,ROW()-4)="","",INDEX('Form Responses 1'!$C:$C,ROW()-4)),"")} -> 10:00-12:00 | E6: {=IFERROR(IF(INDEX('Form Responses 1'!$D:$D,ROW()-4)="","",INDEX('Form Responses 1'!$D:$D,ROW()-4)),"")} -> Danone | F6: {=IFERROR(IF(INDEX('Form Responses 1'!$D:$D,ROW()-4)="","",INDEX('Form Responses 1'!$E:$E,ROW()-4)),"")} -> Test Contact | G6: {=IFERROR(IF(INDEX('Form Responses 1'!$D:$D,ROW()-4)="","",INDEX('Form Responses 1'!$F:$F,ROW()-4)),"")} -> VP Supply Chain | H6: {=IFERROR(IF(INDEX('Form Responses 1'!$D:$D,ROW()-4)="","",INDEX('Form Responses 1'!$G:$G,ROW()-4)),"")} -> Booth | I6: {=IFERROR(IF(INDEX('Form Responses 1'!$D:$D,ROW()-4)="","",INDEX('Form Responses 1'!$H:$H,ROW()-4)),"")} -> Discovery | J6: {=IFERROR(IF(INDEX('Form Responses 1'!$D:$D,ROW()-4)="","",INDEX('Form Responses 1'!$I:$I,ROW()-4)),"")} -> MODEX Floor | K6: {=IFERROR(IF(INDEX('Form Responses 1'!$D:$D,ROW()-4)="","",INDEX('Form Responses 1'!$J:$J,ROW()-4)),"")} -> 5 | L6: {=IFERROR(IF(INDEX('Form Responses 1'!$D:$D,ROW()-4)="","",INDEX('Form Responses 1'!$K:$K,ROW()-4)),"")} -> 4 | M6: {=IFERROR(IF(INDEX('Form Responses 1'!$D:$D,ROW()-4)="","",INDEX('Form Responses 1'!$L:$L,ROW()-4)),"")} -> 5 | N6: {=IFERROR(IF(INDEX('Form Responses 1'!$D:$D,ROW()-4)="","",INDEX('Form Responses 1'!$M:$M,ROW()-4)),"")} -> 5 | O6: {=IFERROR(IF(INDEX('Form Responses 1'!$D:$D,ROW()-4)="","",INDEX('Form Responses 1'!$N:$N,ROW()-4)),"")} -> Infographic | P6: {=IFERROR(IF(INDEX('Form Responses 1'!$D:$D,ROW()-4)="","",INDEX('Form Responses 1'!$O:$O,ROW()-4)),"")} -> Yes | Q6: {=IFERROR(IF(INDEX('Form Responses 1'!$D:$D,ROW()-4)="","",INDEX('Form Responses 1'!$P:$P,ROW()-4)),"")} -> Send Danone Infographic | R6: {=IFERROR(IF(INDEX('Form Responses 1'!$D:$D,ROW()-4)="","",INDEX('Form Responses 1'!$Q:$Q,ROW()-4)),"")} -> Jake | S6: {=IFERROR(IF(INDEX('Form Responses 1'!$D:$D,ROW()-4)="","",INDEX('Form Responses 1'!$R:$R,ROW()-4)),"")} -> 46107 | T6: {=IFERROR(IF(INDEX('Form Responses 1'!$D:$D,ROW()-4)="","",INDEX('Form Responses 1'!$S:$S,ROW()-4)),"")} | U6: {=IFERROR(IF(INDEX('Form Responses 1'!$D:$D,ROW()-4)="","",INDEX('Form Responses 1'!$T:$T,ROW()-4)),"")} -> Qualified | V6: =IF(B6="","",SUM(K6:N6)+IF(P6="Yes",2,0)) -> 21 | W6: =IF(V6="","",IF(V6>=18,"HOT",IF(V6>=14,"WARM",IF(V6>=10,"WORK","NURTURE")))) -> HOT | X6: =IF(B6="","",IF(OR(U6="Not a fit",U6="Follow later"),"Closed","Open")) -> Open | Y6: {=IFERROR(IF(INDEX('Form Responses 1'!$D:$D,ROW()-4)="","",INDEX('Form Responses 1'!$U:$U,ROW()-4)),"")} -> Test submission from setup validation
A7: =IF(E7="","","LC-"&TEXT(ROW()-5,"000")) | B7: {=IFERROR(IF(INDEX('Form Responses 1'!$D:$D,ROW()-4)="","",INDEX('Form Responses 1'!$A:$A,ROW()-4)),"")} | C7: {=IFERROR(IF(INDEX('Form Responses 1'!$D:$D,ROW()-4)="","",INDEX('Form Responses 1'!$B:$B,ROW()-4)),"")} | D7: {=IFERROR(IF(INDEX('Form Responses 1'!$D:$D,ROW()-4)="","",INDEX('Form Responses 1'!$C:$C,ROW()-4)),"")} | E7: {=IFERROR(IF(INDEX('Form Responses 1'!$D:$D,ROW()-4)="","",INDEX('Form Responses 1'!$D:$D,ROW()-4)),"")} | F7: {=IFERROR(IF(INDEX('Form Responses 1'!$D:$D,ROW()-4)="","",INDEX('Form Responses 1'!$E:$E,ROW()-4)),"")} | G7: {=IFERROR(IF(INDEX('Form Responses 1'!$D:$D,ROW()-4)="","",INDEX('Form Responses 1'!$F:$F,ROW()-4)),"")} | H7: {=IFERROR(IF(INDEX('Form Responses 1'!$D:$D,ROW()-4)="","",INDEX('Form Responses 1'!$G:$G,ROW()-4)),"")} | I7: {=IFERROR(IF(INDEX('Form Responses 1'!$D:$D,ROW()-4)="","",INDEX('Form Responses 1'!$H:$H,ROW()-4)),"")} | J7: {=IFERROR(IF(INDEX('Form Responses 1'!$D:$D,ROW()-4)="","",INDEX('Form Responses 1'!$I:$I,ROW()-4)),"")} | K7: {=IFERROR(IF(INDEX('Form Responses 1'!$D:$D,ROW()-4)="","",INDEX('Form Responses 1'!$J:$J,ROW()-4)),"")} | L7: {=IFERROR(IF(INDEX('Form Responses 1'!$D:$D,ROW()-4)="","",INDEX('Form Responses 1'!$K:$K,ROW()-4)),"")} | M7: {=IFERROR(IF(INDEX('Form Responses 1'!$D:$D,ROW()-4)="","",INDEX('Form Responses 1'!$L:$L,ROW()-4)),"")} | N7: {=IFERROR(IF(INDEX('Form Responses 1'!$D:$D,ROW()-4)="","",INDEX('Form Responses 1'!$M:$M,ROW()-4)),"")} | O7: {=IFERROR(IF(INDEX('Form Responses 1'!$D:$D,ROW()-4)="","",INDEX('Form Responses 1'!$N:$N,ROW()-4)),"")} | P7: {=IFERROR(IF(INDEX('Form Responses 1'!$D:$D,ROW()-4)="","",INDEX('Form Responses 1'!$O:$O,ROW()-4)),"")} | Q7: {=IFERROR(IF(INDEX('Form Responses 1'!$D:$D,ROW()-4)="","",INDEX('Form Responses 1'!$P:$P,ROW()-4)),"")} | R7: {=IFERROR(IF(INDEX('Form Responses 1'!$D:$D,ROW()-4)="","",INDEX('Form Responses 1'!$Q:$Q,ROW()-4)),"")} | S7: {=IFERROR(IF(INDEX('Form Responses 1'!$D:$D,ROW()-4)="","",INDEX('Form Responses 1'!$R:$R,ROW()-4)),"")} | T7: {=IFERROR(IF(INDEX('Form Responses 1'!$D:$D,ROW()-4)="","",INDEX('Form Responses 1'!$S:$S,ROW()-4)),"")} | U7: {=IFERROR(IF(INDEX('Form Responses 1'!$D:$D,ROW()-4)="","",INDEX('Form Responses 1'!$T:$T,ROW()-4)),"")} | V7: =IF(B7="","",SUM(K7:N7)+IF(P7="Yes",2,0)) | W7: =IF(V7="","",IF(V7>=18,"HOT",IF(V7>=14,"WARM",IF(V7>=10,"WORK","NURTURE")))) | X7: =IF(B7="","",IF(OR(U7="Not a fit",U7="Follow later"),"Closed","Open")) | Y7: {=IFERROR(IF(INDEX('Form Responses 1'!$D:$D,ROW()-4)="","",INDEX('Form Responses 1'!$U:$U,ROW()-4)),"")}
A8: =IF(E8="","","LC-"&TEXT(ROW()-5,"000")) | B8: {=IFERROR(IF(INDEX('Form Responses 1'!$D:$D,ROW()-4)="","",INDEX('Form Responses 1'!$A:$A,ROW()-4)),"")} | C8: {=IFERROR(IF(INDEX('Form Responses 1'!$D:$D,ROW()-4)="","",INDEX('Form Responses 1'!$B:$B,ROW()-4)),"")} | D8: {=IFERROR(IF(INDEX('Form Responses 1'!$D:$D,ROW()-4)="","",INDEX('Form Responses 1'!$C:$C,ROW()-4)),"")} | E8: {=IFERROR(IF(INDEX('Form Responses 1'!$D:$D,ROW()-4)="","",INDEX('Form Responses 1'!$D:$D,ROW()-4)),"")} | F8: {=IFERROR(IF(INDEX('Form Responses 1'!$D:$D,ROW()-4)="","",INDEX('Form Responses 1'!$E:$E,ROW()-4)),"")} | G8: {=IFERROR(IF(INDEX('Form Responses 1'!$D:$D,ROW()-4)="","",INDEX('Form Responses 1'!$F:$F,ROW()-4)),"")} | H8: {=IFERROR(IF(INDEX('Form Responses 1'!$D:$D,ROW()-4)="","",INDEX('Form Responses 1'!$G:$G,ROW()-4)),"")} | I8: {=IFERROR(IF(INDEX('Form Responses 1'!$D:$D,ROW()-4)="","",INDEX('Form Responses 1'!$H:$H,ROW()-4)),"")} | J8: {=IFERROR(IF(INDEX('Form Responses 1'!$D:$D,ROW()-4)="","",INDEX('Form Responses 1'!$I:$I,ROW()-4)),"")} | K8: {=IFERROR(IF(INDEX('Form Responses 1'!$D:$D,ROW()-4)="","",INDEX('Form Responses 1'!$J:$J,ROW()-4)),"")} | L8: {=IFERROR(IF(INDEX('Form Responses 1'!$D:$D,ROW()-4)="","",INDEX('Form Responses 1'!$K:$K,ROW()-4)),"")} | M8: {=IFERROR(IF(INDEX('Form Responses 1'!$D:$D,ROW()-4)="","",INDEX('Form Responses 1'!$L:$L,ROW()-4)),"")} | N8: {=IFERROR(IF(INDEX('Form Responses 1'!$D:$D,ROW()-4)="","",INDEX('Form Responses 1'!$M:$M,ROW()-4)),"")} | O8: {=IFERROR(IF(INDEX('Form Responses 1'!$D:$D,ROW()-4)="","",INDEX('Form Responses 1'!$N:$N,ROW()-4)),"")} | P8: {=IFERROR(IF(INDEX('Form Responses 1'!$D:$D,ROW()-4)="","",INDEX('Form Responses 1'!$O:$O,ROW()-4)),"")} | Q8: {=IFERROR(IF(INDEX('Form Responses 1'!$D:$D,ROW()-4)="","",INDEX('Form Responses 1'!$P:$P,ROW()-4)),"")} | R8: {=IFERROR(IF(INDEX('Form Responses 1'!$D:$D,ROW()-4)="","",INDEX('Form Responses 1'!$Q:$Q,ROW()-4)),"")} | S8: {=IFERROR(IF(INDEX('Form Responses 1'!$D:$D,ROW()-4)="","",INDEX('Form Responses 1'!$R:$R,ROW()-4)),"")} | T8: {=IFERROR(IF(INDEX('Form Responses 1'!$D:$D,ROW()-4)="","",INDEX('Form Responses 1'!$S:$S,ROW()-4)),"")} | U8: {=IFERROR(IF(INDEX('Form Responses 1'!$D:$D,ROW()-4)="","",INDEX('Form Responses 1'!$T:$T,ROW()-4)),"")} | V8: =IF(B8="","",SUM(K8:N8)+IF(P8="Yes",2,0)) | W8: =IF(V8="","",IF(V8>=18,"HOT",IF(V8>=14,"WARM",IF(V8>=10,"WORK","NURTURE")))) | X8: =IF(B8="","",IF(OR(U8="Not a fit",U8="Follow later"),"Closed","Open")) | Y8: {=IFERROR(IF(INDEX('Form Responses 1'!$D:$D,ROW()-4)="","",INDEX('Form Responses 1'!$U:$U,ROW()-4)),"")}
A9: =IF(E9="","","LC-"&TEXT(ROW()-5,"000")) | B9: {=IFERROR(IF(INDEX('Form Responses 1'!$D:$D,ROW()-4)="","",INDEX('Form Responses 1'!$A:$A,ROW()-4)),"")} | C9: {=IFERROR(IF(INDEX('Form Responses 1'!$D:$D,ROW()-4)="","",INDEX('Form Responses 1'!$B:$B,ROW()-4)),"")} | D9: {=IFERROR(IF(INDEX('Form Responses 1'!$D:$D,ROW()-4)="","",INDEX('Form Responses 1'!$C:$C,ROW()-4)),"")} | E9: {=IFERROR(IF(INDEX('Form Responses 1'!$D:$D,ROW()-4)="","",INDEX('Form Responses 1'!$D:$D,ROW()-4)),"")} | F9: {=IFERROR(IF(INDEX('Form Responses 1'!$D:$D,ROW()-4)="","",INDEX('Form Responses 1'!$E:$E,ROW()-4)),"")} | G9: {=IFERROR(IF(INDEX('Form Responses 1'!$D:$D,ROW()-4)="","",INDEX('Form Responses 1'!$F:$F,ROW()-4)),"")} | H9: {=IFERROR(IF(INDEX('Form Responses 1'!$D:$D,ROW()-4)="","",INDEX('Form Responses 1'!$G:$G,ROW()-4)),"")} | I9: {=IFERROR(IF(INDEX('Form Responses 1'!$D:$D,ROW()-4)="","",INDEX('Form Responses 1'!$H:$H,ROW()-4)),"")} | J9: {=IFERROR(IF(INDEX('Form Responses 1'!$D:$D,ROW()-4)="","",INDEX('Form Responses 1'!$I:$I,ROW()-4)),"")} | K9: {=IFERROR(IF(INDEX('Form Responses 1'!$D:$D,ROW()-4)="","",INDEX('Form Responses 1'!$J:$J,ROW()-4)),"")} | L9: {=IFERROR(IF(INDEX('Form Responses 1'!$D:$D,ROW()-4)="","",INDEX('Form Responses 1'!$K:$K,ROW()-4)),"")} | M9: {=IFERROR(IF(INDEX('Form Responses 1'!$D:$D,ROW()-4)="","",INDEX('Form Responses 1'!$L:$L,ROW()-4)),"")} | N9: {=IFERROR(IF(INDEX('Form Responses 1'!$D:$D,ROW()-4)="","",INDEX('Form Responses 1'!$M:$M,ROW()-4)),"")} | O9: {=IFERROR(IF(INDEX('Form Responses 1'!$D:$D,ROW()-4)="","",INDEX('Form Responses 1'!$N:$N,ROW()-4)),"")} | P9: {=IFERROR(IF(INDEX('Form Responses 1'!$D:$D,ROW()-4)="","",INDEX('Form Responses 1'!$O:$O,ROW()-4)),"")} | Q9: {=IFERROR(IF(INDEX('Form Responses 1'!$D:$D,ROW()-4)="","",INDEX('Form Responses 1'!$P:$P,ROW()-4)),"")} | R9: {=IFERROR(IF(INDEX('Form Responses 1'!$D:$D,ROW()-4)="","",INDEX('Form Responses 1'!$Q:$Q,ROW()-4)),"")} | S9: {=IFERROR(IF(INDEX('Form Responses 1'!$D:$D,ROW()-4)="","",INDEX('Form Responses 1'!$R:$R,ROW()-4)),"")} | T9: {=IFERROR(IF(INDEX('Form Responses 1'!$D:$D,ROW()-4)="","",INDEX('Form Responses 1'!$S:$S,ROW()-4)),"")} | U9: {=IFERROR(IF(INDEX('Form Responses 1'!$D:$D,ROW()-4)="","",INDEX('Form Responses 1'!$T:$T,ROW()-4)),"")} | V9: =IF(B9="","",SUM(K9:N9)+IF(P9="Yes",2,0)) | W9: =IF(V9="","",IF(V9>=18,"HOT",IF(V9>=14,"WARM",IF(V9>=10,"WORK","NURTURE")))) | X9: =IF(B9="","",IF(OR(U9="Not a fit",U9="Follow later"),"Closed","Open")) | Y9: {=IFERROR(IF(INDEX('Form Responses 1'!$D:$D,ROW()-4)="","",INDEX('Form Responses 1'!$U:$U,ROW()-4)),"")}
A10: =IF(E10="","","LC-"&TEXT(ROW()-5,"000")) | B10: {=IFERROR(IF(INDEX('Form Responses 1'!$D:$D,ROW()-4)="","",INDEX('Form Responses 1'!$A:$A,ROW()-4)),"")} | C10: {=IFERROR(IF(INDEX('Form Responses 1'!$D:$D,ROW()-4)="","",INDEX('Form Responses 1'!$B:$B,ROW()-4)),"")} | D10: {=IFERROR(IF(INDEX('Form Responses 1'!$D:$D,ROW()-4)="","",INDEX('Form Responses 1'!$C:$C,ROW()-4)),"")} | E10: {=IFERROR(IF(INDEX('Form Responses 1'!$D:$D,ROW()-4)="","",INDEX('Form Responses 1'!$D:$D,ROW()-4)),"")} | F10: {=IFERROR(IF(INDEX('Form Responses 1'!$D:$D,ROW()-4)="","",INDEX('Form Responses 1'!$E:$E,ROW()-4)),"")} | G10: {=IFERROR(IF(INDEX('Form Responses 1'!$D:$D,ROW()-4)="","",INDEX('Form Responses 1'!$F:$F,ROW()-4)),"")} | H10: {=IFERROR(IF(INDEX('Form Responses 1'!$D:$D,ROW()-4)="","",INDEX('Form Responses 1'!$G:$G,ROW()-4)),"")} | I10: {=IFERROR(IF(INDEX('Form Responses 1'!$D:$D,ROW()-4)="","",INDEX('Form Responses 1'!$H:$H,ROW()-4)),"")} | J10: {=IFERROR(IF(INDEX('Form Responses 1'!$D:$D,ROW()-4)="","",INDEX('Form Responses 1'!$I:$I,ROW()-4)),"")} | K10: {=IFERROR(IF(INDEX('Form Responses 1'!$D:$D,ROW()-4)="","",INDEX('Form Responses 1'!$J:$J,ROW()-4)),"")} | L10: {=IFERROR(IF(INDEX('Form Responses 1'!$D:$D,ROW()-4)="","",INDEX('Form Responses 1'!$K:$K,ROW()-4)),"")} | M10: {=IFERROR(IF(INDEX('Form Responses 1'!$D:$D,ROW()-4)="","",INDEX('Form Responses 1'!$L:$L,ROW()-4)),"")} | N10: {=IFERROR(IF(INDEX('Form Responses 1'!$D:$D,ROW()-4)="","",INDEX('Form Responses 1'!$M:$M,ROW()-4)),"")} | O10: {=IFERROR(IF(INDEX('Form Responses 1'!$D:$D,ROW()-4)="","",INDEX('Form Responses 1'!$N:$N,ROW()-4)),"")} | P10: {=IFERROR(IF(INDEX('Form Responses 1'!$D:$D,ROW()-4)="","",INDEX('Form Responses 1'!$O:$O,ROW()-4)),"")} | Q10: {=IFERROR(IF(INDEX('Form Responses 1'!$D:$D,ROW()-4)="","",INDEX('Form Responses 1'!$P:$P,ROW()-4)),"")} | R10: {=IFERROR(IF(INDEX('Form Responses 1'!$D:$D,ROW()-4)="","",INDEX('Form Responses 1'!$Q:$Q,ROW()-4)),"")} | S10: {=IFERROR(IF(INDEX('Form Responses 1'!$D:$D,ROW()-4)="","",INDEX('Form Responses 1'!$R:$R,ROW()-4)),"")} | T10: {=IFERROR(IF(INDEX('Form Responses 1'!$D:$D,ROW()-4)="","",INDEX('Form Responses 1'!$S:$S,ROW()-4)),"")} | U10: {=IFERROR(IF(INDEX('Form Responses 1'!$D:$D,ROW()-4)="","",INDEX('Form Responses 1'!$T:$T,ROW()-4)),"")} | V10: =IF(B10="","",SUM(K10:N10)+IF(P10="Yes",2,0)) | W10: =IF(V10="","",IF(V10>=18,"HOT",IF(V10>=14,"WARM",IF(V10>=10,"WORK","NURTURE")))) | X10: =IF(B10="","",IF(OR(U10="Not a fit",U10="Follow later"),"Closed","Open")) | Y10: {=IFERROR(IF(INDEX('Form Responses 1'!$D:$D,ROW()-4)="","",INDEX('Form Responses 1'!$U:$U,ROW()-4)),"")}
A11: =IF(E11="","","LC-"&TEXT(ROW()-5,"000")) | B11: {=IFERROR(IF(INDEX('Form Responses 1'!$D:$D,ROW()-4)="","",INDEX('Form Responses 1'!$A:$A,ROW()-4)),"")} | C11: {=IFERROR(IF(INDEX('Form Responses 1'!$D:$D,ROW()-4)="","",INDEX('Form Responses 1'!$B:$B,ROW()-4)),"")} | D11: {=IFERROR(IF(INDEX('Form Responses 1'!$D:$D,ROW()-4)="","",INDEX('Form Responses 1'!$C:$C,ROW()-4)),"")} | E11: {=IFERROR(IF(INDEX('Form Responses 1'!$D:$D,ROW()-4)="","",INDEX('Form Responses 1'!$D:$D,ROW()-4)),"")} | F11: {=IFERROR(IF(INDEX('Form Responses 1'!$D:$D,ROW()-4)="","",INDEX('Form Responses 1'!$E:$E,ROW()-4)),"")} | G11: {=IFERROR(IF(INDEX('Form Responses 1'!$D:$D,ROW()-4)="","",INDEX('Form Responses 1'!$F:$F,ROW()-4)),"")} | H11: {=IFERROR(IF(INDEX('Form Responses 1'!$D:$D,ROW()-4)="","",INDEX('Form Responses 1'!$G:$G,ROW()-4)),"")} | I11: {=IFERROR(IF(INDEX('Form Responses 1'!$D:$D,ROW()-4)="","",INDEX('Form Responses 1'!$H:$H,ROW()-4)),"")} | J11: {=IFERROR(IF(INDEX('Form Responses 1'!$D:$D,ROW()-4)="","",INDEX('Form Responses 1'!$I:$I,ROW()-4)),"")} | K11: {=IFERROR(IF(INDEX('Form Responses 1'!$D:$D,ROW()-4)="","",INDEX('Form Responses 1'!$J:$J,ROW()-4)),"")} | L11: {=IFERROR(IF(INDEX('Form Responses 1'!$D:$D,ROW()-4)="","",INDEX('Form Responses 1'!$K:$K,ROW()-4)),"")} | M11: {=IFERROR(IF(INDEX('Form Responses 1'!$D:$D,ROW()-4)="","",INDEX('Form Responses 1'!$L:$L,ROW()-4)),"")} | N11: {=IFERROR(IF(INDEX('Form Responses 1'!$D:$D,ROW()-4)="","",INDEX('Form Responses 1'!$M:$M,ROW()-4)),"")} | O11: {=IFERROR(IF(INDEX('Form Responses 1'!$D:$D,ROW()-4)="","",INDEX('Form Responses 1'!$N:$N,ROW()-4)),"")} | P11: {=IFERROR(IF(INDEX('Form Responses 1'!$D:$D,ROW()-4)="","",INDEX('Form Responses 1'!$O:$O,ROW()-4)),"")} | Q11: {=IFERROR(IF(INDEX('Form Responses 1'!$D:$D,ROW()-4)="","",INDEX('Form Responses 1'!$P:$P,ROW()-4)),"")} | R11: {=IFERROR(IF(INDEX('Form Responses 1'!$D:$D,ROW()-4)="","",INDEX('Form Responses 1'!$Q:$Q,ROW()-4)),"")} | S11: {=IFERROR(IF(INDEX('Form Responses 1'!$D:$D,ROW()-4)="","",INDEX('Form Responses 1'!$R:$R,ROW()-4)),"")} | T11: {=IFERROR(IF(INDEX('Form Responses 1'!$D:$D,ROW()-4)="","",INDEX('Form Responses 1'!$S:$S,ROW()-4)),"")} | U11: {=IFERROR(IF(INDEX('Form Responses 1'!$D:$D,ROW()-4)="","",INDEX('Form Responses 1'!$T:$T,ROW()-4)),"")} | V11: =IF(B11="","",SUM(K11:N11)+IF(P11="Yes",2,0)) | W11: =IF(V11="","",IF(V11>=18,"HOT",IF(V11>=14,"WARM",IF(V11>=10,"WORK","NURTURE")))) | X11: =IF(B11="","",IF(OR(U11="Not a fit",U11="Follow later"),"Closed","Open")) | Y11: {=IFERROR(IF(INDEX('Form Responses 1'!$D:$D,ROW()-4)="","",INDEX('Form Responses 1'!$U:$U,ROW()-4)),"")}
A12: =IF(E12="","","LC-"&TEXT(ROW()-5,"000")) | B12: {=IFERROR(IF(INDEX('Form Responses 1'!$D:$D,ROW()-4)="","",INDEX('Form Responses 1'!$A:$A,ROW()-4)),"")} | C12: {=IFERROR(IF(INDEX('Form Responses 1'!$D:$D,ROW()-4)="","",INDEX('Form Responses 1'!$B:$B,ROW()-4)),"")} | D12: {=IFERROR(IF(INDEX('Form Responses 1'!$D:$D,ROW()-4)="","",INDEX('Form Responses 1'!$C:$C,ROW()-4)),"")} | E12: {=IFERROR(IF(INDEX('Form Responses 1'!$D:$D,ROW()-4)="","",INDEX('Form Responses 1'!$D:$D,ROW()-4)),"")} | F12: {=IFERROR(IF(INDEX('Form Responses 1'!$D:$D,ROW()-4)="","",INDEX('Form Responses 1'!$E:$E,ROW()-4)),"")} | G12: {=IFERROR(IF(INDEX('Form Responses 1'!$D:$D,ROW()-4)="","",INDEX('Form Responses 1'!$F:$F,ROW()-4)),"")} | H12: {=IFERROR(IF(INDEX('Form Responses 1'!$D:$D,ROW()-4)="","",INDEX('Form Responses 1'!$G:$G,ROW()-4)),"")} | I12: {=IFERROR(IF(INDEX('Form Responses 1'!$D:$D,ROW()-4)="","",INDEX('Form Responses 1'!$H:$H,ROW()-4)),"")} | J12: {=IFERROR(IF(INDEX('Form Responses 1'!$D:$D,ROW()-4)="","",INDEX('Form Responses 1'!$I:$I,ROW()-4)),"")} | K12: {=IFERROR(IF(INDEX('Form Responses 1'!$D:$D,ROW()-4)="","",INDEX('Form Responses 1'!$J:$J,ROW()-4)),"")} | L12: {=IFERROR(IF(INDEX('Form Responses 1'!$D:$D,ROW()-4)="","",INDEX('Form Responses 1'!$K:$K,ROW()-4)),"")} | M12: {=IFERROR(IF(INDEX('Form Responses 1'!$D:$D,ROW()-4)="","",INDEX('Form Responses 1'!$L:$L,ROW()-4)),"")} | N12: {=IFERROR(IF(INDEX('Form Responses 1'!$D:$D,ROW()-4)="","",INDEX('Form Responses 1'!$M:$M,ROW()-4)),"")} | O12: {=IFERROR(IF(INDEX('Form Responses 1'!$D:$D,ROW()-4)="","",INDEX('Form Responses 1'!$N:$N,ROW()-4)),"")} | P12: {=IFERROR(IF(INDEX('Form Responses 1'!$D:$D,ROW()-4)="","",INDEX('Form Responses 1'!$O:$O,ROW()-4)),"")} | Q12: {=IFERROR(IF(INDEX('Form Responses 1'!$D:$D,ROW()-4)="","",INDEX('Form Responses 1'!$P:$P,ROW()-4)),"")} | R12: {=IFERROR(IF(INDEX('Form Responses 1'!$D:$D,ROW()-4)="","",INDEX('Form Responses 1'!$Q:$Q,ROW()-4)),"")} | S12: {=IFERROR(IF(INDEX('Form Responses 1'!$D:$D,ROW()-4)="","",INDEX('Form Responses 1'!$R:$R,ROW()-4)),"")} | T12: {=IFERROR(IF(INDEX('Form Responses 1'!$D:$D,ROW()-4)="","",INDEX('Form Responses 1'!$S:$S,ROW()-4)),"")} | U12: {=IFERROR(IF(INDEX('Form Responses 1'!$D:$D,ROW()-4)="","",INDEX('Form Responses 1'!$T:$T,ROW()-4)),"")} | V12: =IF(B12="","",SUM(K12:N12)+IF(P12="Yes",2,0)) | W12: =IF(V12="","",IF(V12>=18,"HOT",IF(V12>=14,"WARM",IF(V12>=10,"WORK","NURTURE")))) | X12: =IF(B12="","",IF(OR(U12="Not a fit",U12="Follow later"),"Closed","Open")) | Y12: {=IFERROR(IF(INDEX('Form Responses 1'!$D:$D,ROW()-4)="","",INDEX('Form Responses 1'!$U:$U,ROW()-4)),"")}
A13: =IF(E13="","","LC-"&TEXT(ROW()-5,"000")) | B13: {=IFERROR(IF(INDEX('Form Responses 1'!$D:$D,ROW()-4)="","",INDEX('Form Responses 1'!$A:$A,ROW()-4)),"")} | C13: {=IFERROR(IF(INDEX('Form Responses 1'!$D:$D,ROW()-4)="","",INDEX('Form Responses 1'!$B:$B,ROW()-4)),"")} | D13: {=IFERROR(IF(INDEX('Form Responses 1'!$D:$D,ROW()-4)="","",INDEX('Form Responses 1'!$C:$C,ROW()-4)),"")} | E13: {=IFERROR(IF(INDEX('Form Responses 1'!$D:$D,ROW()-4)="","",INDEX('Form Responses 1'!$D:$D,ROW()-4)),"")} | F13: {=IFERROR(IF(INDEX('Form Responses 1'!$D:$D,ROW()-4)="","",INDEX('Form Responses 1'!$E:$E,ROW()-4)),"")} | G13: {=IFERROR(IF(INDEX('Form Responses 1'!$D:$D,ROW()-4)="","",INDEX('Form Responses 1'!$F:$F,ROW()-4)),"")} | H13: {=IFERROR(IF(INDEX('Form Responses 1'!$D:$D,ROW()-4)="","",INDEX('Form Responses 1'!$G:$G,ROW()-4)),"")} | I13: {=IFERROR(IF(INDEX('Form Responses 1'!$D:$D,ROW()-4)="","",INDEX('Form Responses 1'!$H:$H,ROW()-4)),"")} | J13: {=IFERROR(IF(INDEX('Form Responses 1'!$D:$D,ROW()-4)="","",INDEX('Form Responses 1'!$I:$I,ROW()-4)),"")} | K13: {=IFERROR(IF(INDEX('Form Responses 1'!$D:$D,ROW()-4)="","",INDEX('Form Responses 1'!$J:$J,ROW()-4)),"")} | L13: {=IFERROR(IF(INDEX('Form Responses 1'!$D:$D,ROW()-4)="","",INDEX('Form Responses 1'!$K:$K,ROW()-4)),"")} | M13: {=IFERROR(IF(INDEX('Form Responses 1'!$D:$D,ROW()-4)="","",INDEX('Form Responses 1'!$L:$L,ROW()-4)),"")} | N13: {=IFERROR(IF(INDEX('Form Responses 1'!$D:$D,ROW()-4)="","",INDEX('Form Responses 1'!$M:$M,ROW()-4)),"")} | O13: {=IFERROR(IF(INDEX('Form Responses 1'!$D:$D,ROW()-4)="","",INDEX('Form Responses 1'!$N:$N,ROW()-4)),"")} | P13: {=IFERROR(IF(INDEX('Form Responses 1'!$D:$D,ROW()-4)="","",INDEX('Form Responses 1'!$O:$O,ROW()-4)),"")} | Q13: {=IFERROR(IF(INDEX('Form Responses 1'!$D:$D,ROW()-4)="","",INDEX('Form Responses 1'!$P:$P,ROW()-4)),"")} | R13: {=IFERROR(IF(INDEX('Form Responses 1'!$D:$D,ROW()-4)="","",INDEX('Form Responses 1'!$Q:$Q,ROW()-4)),"")} | S13: {=IFERROR(IF(INDEX('Form Responses 1'!$D:$D,ROW()-4)="","",INDEX('Form Responses 1'!$R:$R,ROW()-4)),"")} | T13: {=IFERROR(IF(INDEX('Form Responses 1'!$D:$D,ROW()-4)="","",INDEX('Form Responses 1'!$S:$S,ROW()-4)),"")} | U13: {=IFERROR(IF(INDEX('Form Responses 1'!$D:$D,ROW()-4)="","",INDEX('Form Responses 1'!$T:$T,ROW()-4)),"")} | V13: =IF(B13="","",SUM(K13:N13)+IF(P13="Yes",2,0)) | W13: =IF(V13="","",IF(V13>=18,"HOT",IF(V13>=14,"WARM",IF(V13>=10,"WORK","NURTURE")))) | X13: =IF(B13="","",IF(OR(U13="Not a fit",U13="Follow later"),"Closed","Open")) | Y13: {=IFERROR(IF(INDEX('Form Responses 1'!$D:$D,ROW()-4)="","",INDEX('Form Responses 1'!$U:$U,ROW()-4)),"")}
A14: =IF(E14="","","LC-"&TEXT(ROW()-5,"000")) | B14: {=IFERROR(IF(INDEX('Form Responses 1'!$D:$D,ROW()-4)="","",INDEX('Form Responses 1'!$A:$A,ROW()-4)),"")} | C14: {=IFERROR(IF(INDEX('Form Responses 1'!$D:$D,ROW()-4)="","",INDEX('Form Responses 1'!$B:$B,ROW()-4)),"")} | D14: {=IFERROR(IF(INDEX('Form Responses 1'!$D:$D,ROW()-4)="","",INDEX('Form Responses 1'!$C:$C,ROW()-4)),"")} | E14: {=IFERROR(IF(INDEX('Form Responses 1'!$D:$D,ROW()-4)="","",INDEX('Form Responses 1'!$D:$D,ROW()-4)),"")} | F14: {=IFERROR(IF(INDEX('Form Responses 1'!$D:$D,ROW()-4)="","",INDEX('Form Responses 1'!$E:$E,ROW()-4)),"")} | G14: {=IFERROR(IF(INDEX('Form Responses 1'!$D:$D,ROW()-4)="","",INDEX('Form Responses 1'!$F:$F,ROW()-4)),"")} | H14: {=IFERROR(IF(INDEX('Form Responses 1'!$D:$D,ROW()-4)="","",INDEX('Form Responses 1'!$G:$G,ROW()-4)),"")} | I14: {=IFERROR(IF(INDEX('Form Responses 1'!$D:$D,ROW()-4)="","",INDEX('Form Responses 1'!$H:$H,ROW()-4)),"")} | J14: {=IFERROR(IF(INDEX('Form Responses 1'!$D:$D,ROW()-4)="","",INDEX('Form Responses 1'!$I:$I,ROW()-4)),"")} | K14: {=IFERROR(IF(INDEX('Form Responses 1'!$D:$D,ROW()-4)="","",INDEX('Form Responses 1'!$J:$J,ROW()-4)),"")} | L14: {=IFERROR(IF(INDEX('Form Responses 1'!$D:$D,ROW()-4)="","",INDEX('Form Responses 1'!$K:$K,ROW()-4)),"")} | M14: {=IFERROR(IF(INDEX('Form Responses 1'!$D:$D,ROW()-4)="","",INDEX('Form Responses 1'!$L:$L,ROW()-4)),"")} | N14: {=IFERROR(IF(INDEX('Form Responses 1'!$D:$D,ROW()-4)="","",INDEX('Form Responses 1'!$M:$M,ROW()-4)),"")} | O14: {=IFERROR(IF(INDEX('Form Responses 1'!$D:$D,ROW()-4)="","",INDEX('Form Responses 1'!$N:$N,ROW()-4)),"")} | P14: {=IFERROR(IF(INDEX('Form Responses 1'!$D:$D,ROW()-4)="","",INDEX('Form Responses 1'!$O:$O,ROW()-4)),"")} | Q14: {=IFERROR(IF(INDEX('Form Responses 1'!$D:$D,ROW()-4)="","",INDEX('Form Responses 1'!$P:$P,ROW()-4)),"")} | R14: {=IFERROR(IF(INDEX('Form Responses 1'!$D:$D,ROW()-4)="","",INDEX('Form Responses 1'!$Q:$Q,ROW()-4)),"")} | S14: {=IFERROR(IF(INDEX('Form Responses 1'!$D:$D,ROW()-4)="","",INDEX('Form Responses 1'!$R:$R,ROW()-4)),"")} | T14: {=IFERROR(IF(INDEX('Form Responses 1'!$D:$D,ROW()-4)="","",INDEX('Form Responses 1'!$S:$S,ROW()-4)),"")} | U14: {=IFERROR(IF(INDEX('Form Responses 1'!$D:$D,ROW()-4)="","",INDEX('Form Responses 1'!$T:$T,ROW()-4)),"")} | V14: =IF(B14="","",SUM(K14:N14)+IF(P14="Yes",2,0)) | W14: =IF(V14="","",IF(V14>=18,"HOT",IF(V14>=14,"WARM",IF(V14>=10,"WORK","NURTURE")))) | X14: =IF(B14="","",IF(OR(U14="Not a fit",U14="Follow later"),"Closed","Open")) | Y14: {=IFERROR(IF(INDEX('Form Responses 1'!$D:$D,ROW()-4)="","",INDEX('Form Responses 1'!$U:$U,ROW()-4)),"")}
A15: =IF(E15="","","LC-"&TEXT(ROW()-5,"000")) | B15: {=IFERROR(IF(INDEX('Form Responses 1'!$D:$D,ROW()-4)="","",INDEX('Form Responses 1'!$A:$A,ROW()-4)),"")} | C15: {=IFERROR(IF(INDEX('Form Responses 1'!$D:$D,ROW()-4)="","",INDEX('Form Responses 1'!$B:$B,ROW()-4)),"")} | D15: {=IFERROR(IF(INDEX('Form Responses 1'!$D:$D,ROW()-4)="","",INDEX('Form Responses 1'!$C:$C,ROW()-4)),"")} | E15: {=IFERROR(IF(INDEX('Form Responses 1'!$D:$D,ROW()-4)="","",INDEX('Form Responses 1'!$D:$D,ROW()-4)),"")} | F15: {=IFERROR(IF(INDEX('Form Responses 1'!$D:$D,ROW()-4)="","",INDEX('Form Responses 1'!$E:$E,ROW()-4)),"")} | G15: {=IFERROR(IF(INDEX('Form Responses 1'!$D:$D,ROW()-4)="","",INDEX('Form Responses 1'!$F:$F,ROW()-4)),"")} | H15: {=IFERROR(IF(INDEX('Form Responses 1'!$D:$D,ROW()-4)="","",INDEX('Form Responses 1'!$G:$G,ROW()-4)),"")} | I15: {=IFERROR(IF(INDEX('Form Responses 1'!$D:$D,ROW()-4)="","",INDEX('Form Responses 1'!$H:$H,ROW()-4)),"")} | J15: {=IFERROR(IF(INDEX('Form Responses 1'!$D:$D,ROW()-4)="","",INDEX('Form Responses 1'!$I:$I,ROW()-4)),"")} | K15: {=IFERROR(IF(INDEX('Form Responses 1'!$D:$D,ROW()-4)="","",INDEX('Form Responses 1'!$J:$J,ROW()-4)),"")} | L15: {=IFERROR(IF(INDEX('Form Responses 1'!$D:$D,ROW()-4)="","",INDEX('Form Responses 1'!$K:$K,ROW()-4)),"")} | M15: {=IFERROR(IF(INDEX('Form Responses 1'!$D:$D,ROW()-4)="","",INDEX('Form Responses 1'!$L:$L,ROW()-4)),"")} | N15: {=IFERROR(IF(INDEX('Form Responses 1'!$D:$D,ROW()-4)="","",INDEX('Form Responses 1'!$M:$M,ROW()-4)),"")} | O15: {=IFERROR(IF(INDEX('Form Responses 1'!$D:$D,ROW()-4)="","",INDEX('Form Responses 1'!$N:$N,ROW()-4)),"")} | P15: {=IFERROR(IF(INDEX('Form Responses 1'!$D:$D,ROW()-4)="","",INDEX('Form Responses 1'!$O:$O,ROW()-4)),"")} | Q15: {=IFERROR(IF(INDEX('Form Responses 1'!$D:$D,ROW()-4)="","",INDEX('Form Responses 1'!$P:$P,ROW()-4)),"")} | R15: {=IFERROR(IF(INDEX('Form Responses 1'!$D:$D,ROW()-4)="","",INDEX('Form Responses 1'!$Q:$Q,ROW()-4)),"")} | S15: {=IFERROR(IF(INDEX('Form Responses 1'!$D:$D,ROW()-4)="","",INDEX('Form Responses 1'!$R:$R,ROW()-4)),"")} | T15: {=IFERROR(IF(INDEX('Form Responses 1'!$D:$D,ROW()-4)="","",INDEX('Form Responses 1'!$S:$S,ROW()-4)),"")} | U15: {=IFERROR(IF(INDEX('Form Responses 1'!$D:$D,ROW()-4)="","",INDEX('Form Responses 1'!$T:$T,ROW()-4)),"")} | V15: =IF(B15="","",SUM(K15:N15)+IF(P15="Yes",2,0)) | W15: =IF(V15="","",IF(V15>=18,"HOT",IF(V15>=14,"WARM",IF(V15>=10,"WORK","NURTURE")))) | X15: =IF(B15="","",IF(OR(U15="Not a fit",U15="Follow later"),"Closed","Open")) | Y15: {=IFERROR(IF(INDEX('Form Responses 1'!$D:$D,ROW()-4)="","",INDEX('Form Responses 1'!$U:$U,ROW()-4)),"")}
A16: =IF(E16="","","LC-"&TEXT(ROW()-5,"000")) | B16: {=IFERROR(IF(INDEX('Form Responses 1'!$D:$D,ROW()-4)="","",INDEX('Form Responses 1'!$A:$A,ROW()-4)),"")} | C16: {=IFERROR(IF(INDEX('Form Responses 1'!$D:$D,ROW()-4)="","",INDEX('Form Responses 1'!$B:$B,ROW()-4)),"")} | D16: {=IFERROR(IF(INDEX('Form Responses 1'!$D:$D,ROW()-4)="","",INDEX('Form Responses 1'!$C:$C,ROW()-4)),"")} | E16: {=IFERROR(IF(INDEX('Form Responses 1'!$D:$D,ROW()-4)="","",INDEX('Form Responses 1'!$D:$D,ROW()-4)),"")} | F16: {=IFERROR(IF(INDEX('Form Responses 1'!$D:$D,ROW()-4)="","",INDEX('Form Responses 1'!$E:$E,ROW()-4)),"")} | G16: {=IFERROR(IF(INDEX('Form Responses 1'!$D:$D,ROW()-4)="","",INDEX('Form Responses 1'!$F:$F,ROW()-4)),"")} | H16: {=IFERROR(IF(INDEX('Form Responses 1'!$D:$D,ROW()-4)="","",INDEX('Form Responses 1'!$G:$G,ROW()-4)),"")} | I16: {=IFERROR(IF(INDEX('Form Responses 1'!$D:$D,ROW()-4)="","",INDEX('Form Responses 1'!$H:$H,ROW()-4)),"")} | J16: {=IFERROR(IF(INDEX('Form Responses 1'!$D:$D,ROW()-4)="","",INDEX('Form Responses 1'!$I:$I,ROW()-4)),"")} | K16: {=IFERROR(IF(INDEX('Form Responses 1'!$D:$D,ROW()-4)="","",INDEX('Form Responses 1'!$J:$J,ROW()-4)),"")} | L16: {=IFERROR(IF(INDEX('Form Responses 1'!$D:$D,ROW()-4)="","",INDEX('Form Responses 1'!$K:$K,ROW()-4)),"")} | M16: {=IFERROR(IF(INDEX('Form Responses 1'!$D:$D,ROW()-4)="","",INDEX('Form Responses 1'!$L:$L,ROW()-4)),"")} | N16: {=IFERROR(IF(INDEX('Form Responses 1'!$D:$D,ROW()-4)="","",INDEX('Form Responses 1'!$M:$M,ROW()-4)),"")} | O16: {=IFERROR(IF(INDEX('Form Responses 1'!$D:$D,ROW()-4)="","",INDEX('Form Responses 1'!$N:$N,ROW()-4)),"")} | P16: {=IFERROR(IF(INDEX('Form Responses 1'!$D:$D,ROW()-4)="","",INDEX('Form Responses 1'!$O:$O,ROW()-4)),"")} | Q16: {=IFERROR(IF(INDEX('Form Responses 1'!$D:$D,ROW()-4)="","",INDEX('Form Responses 1'!$P:$P,ROW()-4)),"")} | R16: {=IFERROR(IF(INDEX('Form Responses 1'!$D:$D,ROW()-4)="","",INDEX('Form Responses 1'!$Q:$Q,ROW()-4)),"")} | S16: {=IFERROR(IF(INDEX('Form Responses 1'!$D:$D,ROW()-4)="","",INDEX('Form Responses 1'!$R:$R,ROW()-4)),"")} | T16: {=IFERROR(IF(INDEX('Form Responses 1'!$D:$D,ROW()-4)="","",INDEX('Form Responses 1'!$S:$S,ROW()-4)),"")} | U16: {=IFERROR(IF(INDEX('Form Responses 1'!$D:$D,ROW()-4)="","",INDEX('Form Responses 1'!$T:$T,ROW()-4)),"")} | V16: =IF(B16="","",SUM(K16:N16)+IF(P16="Yes",2,0)) | W16: =IF(V16="","",IF(V16>=18,"HOT",IF(V16>=14,"WARM",IF(V16>=10,"WORK","NURTURE")))) | X16: =IF(B16="","",IF(OR(U16="Not a fit",U16="Follow later"),"Closed","Open")) | Y16: {=IFERROR(IF(INDEX('Form Responses 1'!$D:$D,ROW()-4)="","",INDEX('Form Responses 1'!$U:$U,ROW()-4)),"")}
A17: =IF(E17="","","LC-"&TEXT(ROW()-5,"000")) | B17: {=IFERROR(IF(INDEX('Form Responses 1'!$D:$D,ROW()-4)="","",INDEX('Form Responses 1'!$A:$A,ROW()-4)),"")} | C17: {=IFERROR(IF(INDEX('Form Responses 1'!$D:$D,ROW()-4)="","",INDEX('Form Responses 1'!$B:$B,ROW()-4)),"")} | D17: {=IFERROR(IF(INDEX('Form Responses 1'!$D:$D,ROW()-4)="","",INDEX('Form Responses 1'!$C:$C,ROW()-4)),"")} | E17: {=IFERROR(IF(INDEX('Form Responses 1'!$D:$D,ROW()-4)="","",INDEX('Form Responses 1'!$D:$D,ROW()-4)),"")} | F17: {=IFERROR(IF(INDEX('Form Responses 1'!$D:$D,ROW()-4)="","",INDEX('Form Responses 1'!$E:$E,ROW()-4)),"")} | G17: {=IFERROR(IF(INDEX('Form Responses 1'!$D:$D,ROW()-4)="","",INDEX('Form Responses 1'!$F:$F,ROW()-4)),"")} | H17: {=IFERROR(IF(INDEX('Form Responses 1'!$D:$D,ROW()-4)="","",INDEX('Form Responses 1'!$G:$G,ROW()-4)),"")} | I17: {=IFERROR(IF(INDEX('Form Responses 1'!$D:$D,ROW()-4)="","",INDEX('Form Responses 1'!$H:$H,ROW()-4)),"")} | J17: {=IFERROR(IF(INDEX('Form Responses 1'!$D:$D,ROW()-4)="","",INDEX('Form Responses 1'!$I:$I,ROW()-4)),"")} | K17: {=IFERROR(IF(INDEX('Form Responses 1'!$D:$D,ROW()-4)="","",INDEX('Form Responses 1'!$J:$J,ROW()-4)),"")} | L17: {=IFERROR(IF(INDEX('Form Responses 1'!$D:$D,ROW()-4)="","",INDEX('Form Responses 1'!$K:$K,ROW()-4)),"")} | M17: {=IFERROR(IF(INDEX('Form Responses 1'!$D:$D,ROW()-4)="","",INDEX('Form Responses 1'!$L:$L,ROW()-4)),"")} | N17: {=IFERROR(IF(INDEX('Form Responses 1'!$D:$D,ROW()-4)="","",INDEX('Form Responses 1'!$M:$M,ROW()-4)),"")} | O17: {=IFERROR(IF(INDEX('Form Responses 1'!$D:$D,ROW()-4)="","",INDEX('Form Responses 1'!$N:$N,ROW()-4)),"")} | P17: {=IFERROR(IF(INDEX('Form Responses 1'!$D:$D,ROW()-4)="","",INDEX('Form Responses 1'!$O:$O,ROW()-4)),"")} | Q17: {=IFERROR(IF(INDEX('Form Responses 1'!$D:$D,ROW()-4)="","",INDEX('Form Responses 1'!$P:$P,ROW()-4)),"")} | R17: {=IFERROR(IF(INDEX('Form Responses 1'!$D:$D,ROW()-4)="","",INDEX('Form Responses 1'!$Q:$Q,ROW()-4)),"")} | S17: {=IFERROR(IF(INDEX('Form Responses 1'!$D:$D,ROW()-4)="","",INDEX('Form Responses 1'!$R:$R,ROW()-4)),"")} | T17: {=IFERROR(IF(INDEX('Form Responses 1'!$D:$D,ROW()-4)="","",INDEX('Form Responses 1'!$S:$S,ROW()-4)),"")} | U17: {=IFERROR(IF(INDEX('Form Responses 1'!$D:$D,ROW()-4)="","",INDEX('Form Responses 1'!$T:$T,ROW()-4)),"")} | V17: =IF(B17="","",SUM(K17:N17)+IF(P17="Yes",2,0)) | W17: =IF(V17="","",IF(V17>=18,"HOT",IF(V17>=14,"WARM",IF(V17>=10,"WORK","NURTURE")))) | X17: =IF(B17="","",IF(OR(U17="Not a fit",U17="Follow later"),"Closed","Open")) | Y17: {=IFERROR(IF(INDEX('Form Responses 1'!$D:$D,ROW()-4)="","",INDEX('Form Responses 1'!$U:$U,ROW()-4)),"")}
... A505: =IF(E505="","","LC-"&TEXT(ROW()-5,"000")) | B505: {=IFERROR(IF(INDEX('Form Responses 1'!$D:$D,ROW()-4)="","",INDEX('Form Responses 1'!$A:$A,ROW()-4)),"")} | C505: {=IFERROR(IF(INDEX('Form Responses 1'!$D:$D,ROW()-4)="","",INDEX('Form Responses 1'!$B:$B,ROW()-4)),"")} | D505: {=IFERROR(IF(INDEX('Form Responses 1'!$D:$D,ROW()-4)="","",INDEX('Form Responses 1'!$C:$C,ROW()-4)),"")} | E505: {=IFERROR(IF(INDEX('Form Responses 1'!$D:$D,ROW()-4)="","",INDEX('Form Responses 1'!$D:$D,ROW()-4)),"")} | F505: {=IFERROR(IF(INDEX('Form Responses 1'!$D:$D,ROW()-4)="","",INDEX('Form Responses 1'!$E:$E,ROW()-4)),"")} | G505: {=IFERROR(IF(INDEX('Form Responses 1'!$D:$D,ROW()-4)="","",INDEX('Form Responses 1'!$F:$F,ROW()-4)),"")} | H505: {=IFERROR(IF(INDEX('Form Responses 1'!$D:$D,ROW()-4)="","",INDEX('Form Responses 1'!$G:$G,ROW()-4)),"")} | I505: {=IFERROR(IF(INDEX('Form Responses 1'!$D:$D,ROW()-4)="","",INDEX('Form Responses 1'!$H:$H,ROW()-4)),"")} | J505: {=IFERROR(IF(INDEX('Form Responses 1'!$D:$D,ROW()-4)="","",INDEX('Form Responses 1'!$I:$I,ROW()-4)),"")} | K505: {=IFERROR(IF(INDEX('Form Responses 1'!$D:$D,ROW()-4)="","",INDEX('Form Responses 1'!$J:$J,ROW()-4)),"")} | L505: {=IFERROR(IF(INDEX('Form Responses 1'!$D:$D,ROW()-4)="","",INDEX('Form Responses 1'!$K:$K,ROW()-4)),"")} | M505: {=IFERROR(IF(INDEX('Form Responses 1'!$D:$D,ROW()-4)="","",INDEX('Form Responses 1'!$L:$L,ROW()-4)),"")} | N505: {=IFERROR(IF(INDEX('Form Responses 1'!$D:$D,ROW()-4)="","",INDEX('Form Responses 1'!$M:$M,ROW()-4)),"")} | O505: {=IFERROR(IF(INDEX('Form Responses 1'!$D:$D,ROW()-4)="","",INDEX('Form Responses 1'!$N:$N,ROW()-4)),"")} | P505: {=IFERROR(IF(INDEX('Form Responses 1'!$D:$D,ROW()-4)="","",INDEX('Form Responses 1'!$O:$O,ROW()-4)),"")} | Q505: {=IFERROR(IF(INDEX('Form Responses 1'!$D:$D,ROW()-4)="","",INDEX('Form Responses 1'!$P:$P,ROW()-4)),"")} | R505: {=IFERROR(IF(INDEX('Form Responses 1'!$D:$D,ROW()-4)="","",INDEX('Form Responses 1'!$Q:$Q,ROW()-4)),"")} | S505: {=IFERROR(IF(INDEX('Form Responses 1'!$D:$D,ROW()-4)="","",INDEX('Form Responses 1'!$R:$R,ROW()-4)),"")} | T505: {=IFERROR(IF(INDEX('Form Responses 1'!$D:$D,ROW()-4)="","",INDEX('Form Responses 1'!$S:$S,ROW()-4)),"")} | U505: {=IFERROR(IF(INDEX('Form Responses 1'!$D:$D,ROW()-4)="","",INDEX('Form Responses 1'!$T:$T,ROW()-4)),"")} | V505: =IF(B505="","",SUM(K505:N505)+IF(P505="Yes",2,0)) | W505: =IF(V505="","",IF(V505>=18,"HOT",IF(V505>=14,"WARM",IF(V505>=10,"WORK","NURTURE")))) | X505: =IF(B505="","",IF(OR(U505="Not a fit",U505="Follow later"),"Closed","Open")) | Y505: {=IFERROR(IF(INDEX('Form Responses 1'!$D:$D,ROW()-4)="","",INDEX('Form Responses 1'!$U:$U,ROW()-4)),"")}

Sheet Mobile Capture Lite
A1: Timestamp | B1: Account | C1: Persona Name | D1: Meeting Type | E1: Requested Asset | F1: Need Primo | G1: Owner | H1: Due Date | I1: Notes
A2: Phone-friendly scratchpad for the show floor. Enter quick notes here if opening the full Live Capture tab feels like trying to parallel park a boat.
A4: Timestamp | B4: Account | C4: Persona | D4: Meeting Type | E4: Requested Asset | F4: Need Primo? | G4: Owner | H4: Due Date | I4: Band | J4: Notes
A5: =IF('Live Capture'!B6="","",'Live Capture'!B6) -> 46106.495 | B5: =IF('Live Capture'!B6="","",'Live Capture'!E6) -> Danone | C5: =IF('Live Capture'!B6="","",'Live Capture'!F6) -> Test Contact | D5: =IF('Live Capture'!B6="","",'Live Capture'!I6) -> Discovery | E5: =IF('Live Capture'!B6="","",'Live Capture'!O6) -> Infographic | F5: =IF('Live Capture'!B6="","",'Live Capture'!P6) -> Yes | G5: =IF('Live Capture'!B6="","",'Live Capture'!R6) -> Jake | H5: =IF('Live Capture'!B6="","",'Live Capture'!S6) -> 46107 | I5: =IF('Live Capture'!B6="","",'Live Capture'!W6) -> HOT | J5: =IF('Live Capture'!B6="","",'Live Capture'!Y6) -> Test submission from setup validation
A6: =IF('Live Capture'!B7="","",'Live Capture'!B7) | B6: =IF('Live Capture'!B7="","",'Live Capture'!E7) | C6: =IF('Live Capture'!B7="","",'Live Capture'!F7) | D6: =IF('Live Capture'!B7="","",'Live Capture'!I7) | E6: =IF('Live Capture'!B7="","",'Live Capture'!O7) | F6: =IF('Live Capture'!B7="","",'Live Capture'!P7) | G6: =IF('Live Capture'!B7="","",'Live Capture'!R7) | H6: =IF('Live Capture'!B7="","",'Live Capture'!S7) | I6: =IF('Live Capture'!B7="","",'Live Capture'!W7) | J6: =IF('Live Capture'!B7="","",'Live Capture'!Y7)
A7: =IF('Live Capture'!B8="","",'Live Capture'!B8) | B7: =IF('Live Capture'!B8="","",'Live Capture'!E8) | C7: =IF('Live Capture'!B8="","",'Live Capture'!F8) | D7: =IF('Live Capture'!B8="","",'Live Capture'!I8) | E7: =IF('Live Capture'!B8="","",'Live Capture'!O8) | F7: =IF('Live Capture'!B8="","",'Live Capture'!P8) | G7: =IF('Live Capture'!B8="","",'Live Capture'!R8) | H7: =IF('Live Capture'!B8="","",'Live Capture'!S8) | I7: =IF('Live Capture'!B8="","",'Live Capture'!W8) | J7: =IF('Live Capture'!B8="","",'Live Capture'!Y8)
A8: =IF('Live Capture'!B9="","",'Live Capture'!B9) | B8: =IF('Live Capture'!B9="","",'Live Capture'!E9) | C8: =IF('Live Capture'!B9="","",'Live Capture'!F9) | D8: =IF('Live Capture'!B9="","",'Live Capture'!I9) | E8: =IF('Live Capture'!B9="","",'Live Capture'!O9) | F8: =IF('Live Capture'!B9="","",'Live Capture'!P9) | G8: =IF('Live Capture'!B9="","",'Live Capture'!R9) | H8: =IF('Live Capture'!B9="","",'Live Capture'!S9) | I8: =IF('Live Capture'!B9="","",'Live Capture'!W9) | J8: =IF('Live Capture'!B9="","",'Live Capture'!Y9)
A9: =IF('Live Capture'!B10="","",'Live Capture'!B10) | B9: =IF('Live Capture'!B10="","",'Live Capture'!E10) | C9: =IF('Live Capture'!B10="","",'Live Capture'!F10) | D9: =IF('Live Capture'!B10="","",'Live Capture'!I10) | E9: =IF('Live Capture'!B10="","",'Live Capture'!O10) | F9: =IF('Live Capture'!B10="","",'Live Capture'!P10) | G9: =IF('Live Capture'!B10="","",'Live Capture'!R10) | H9: =IF('Live Capture'!B10="","",'Live Capture'!S10) | I9: =IF('Live Capture'!B10="","",'Live Capture'!W10) | J9: =IF('Live Capture'!B10="","",'Live Capture'!Y10)
A10: =IF('Live Capture'!B11="","",'Live Capture'!B11) | B10: =IF('Live Capture'!B11="","",'Live Capture'!E11) | C10: =IF('Live Capture'!B11="","",'Live Capture'!F11) | D10: =IF('Live Capture'!B11="","",'Live Capture'!I11) | E10: =IF('Live Capture'!B11="","",'Live Capture'!O11) | F10: =IF('Live Capture'!B11="","",'Live Capture'!P11) | G10: =IF('Live Capture'!B11="","",'Live Capture'!R11) | H10: =IF('Live Capture'!B11="","",'Live Capture'!S11) | I10: =IF('Live Capture'!B11="","",'Live Capture'!W11) | J10: =IF('Live Capture'!B11="","",'Live Capture'!Y11)
A11: =IF('Live Capture'!B12="","",'Live Capture'!B12) | B11: =IF('Live Capture'!B12="","",'Live Capture'!E12) | C11: =IF('Live Capture'!B12="","",'Live Capture'!F12) | D11: =IF('Live Capture'!B12="","",'Live Capture'!I12) | E11: =IF('Live Capture'!B12="","",'Live Capture'!O12) | F11: =IF('Live Capture'!B12="","",'Live Capture'!P12) | G11: =IF('Live Capture'!B12="","",'Live Capture'!R12) | H11: =IF('Live Capture'!B12="","",'Live Capture'!S12) | I11: =IF('Live Capture'!B12="","",'Live Capture'!W12) | J11: =IF('Live Capture'!B12="","",'Live Capture'!Y12)
A12: =IF('Live Capture'!B13="","",'Live Capture'!B13) | B12: =IF('Live Capture'!B13="","",'Live Capture'!E13) | C12: =IF('Live Capture'!B13="","",'Live Capture'!F13) | D12: =IF('Live Capture'!B13="","",'Live Capture'!I13) | E12: =IF('Live Capture'!B13="","",'Live Capture'!O13) | F12: =IF('Live Capture'!B13="","",'Live Capture'!P13) | G12: =IF('Live Capture'!B13="","",'Live Capture'!R13) | H12: =IF('Live Capture'!B13="","",'Live Capture'!S13) | I12: =IF('Live Capture'!B13="","",'Live Capture'!W13) | J12: =IF('Live Capture'!B13="","",'Live Capture'!Y13)
A13: =IF('Live Capture'!B14="","",'Live Capture'!B14) | B13: =IF('Live Capture'!B14="","",'Live Capture'!E14) | C13: =IF('Live Capture'!B14="","",'Live Capture'!F14) | D13: =IF('Live Capture'!B14="","",'Live Capture'!I14) | E13: =IF('Live Capture'!B14="","",'Live Capture'!O14) | F13: =IF('Live Capture'!B14="","",'Live Capture'!P14) | G13: =IF('Live Capture'!B14="","",'Live Capture'!R14) | H13: =IF('Live Capture'!B14="","",'Live Capture'!S14) | I13: =IF('Live Capture'!B14="","",'Live Capture'!W14) | J13: =IF('Live Capture'!B14="","",'Live Capture'!Y14)
A14: =IF('Live Capture'!B15="","",'Live Capture'!B15) | B14: =IF('Live Capture'!B15="","",'Live Capture'!E15) | C14: =IF('Live Capture'!B15="","",'Live Capture'!F15) | D14: =IF('Live Capture'!B15="","",'Live Capture'!I15) | E14: =IF('Live Capture'!B15="","",'Live Capture'!O15) | F14: =IF('Live Capture'!B15="","",'Live Capture'!P15) | G14: =IF('Live Capture'!B15="","",'Live Capture'!R15) | H14: =IF('Live Capture'!B15="","",'Live Capture'!S15) | I14: =IF('Live Capture'!B15="","",'Live Capture'!W15) | J14: =IF('Live Capture'!B15="","",'Live Capture'!Y15)
A15: =IF('Live Capture'!B16="","",'Live Capture'!B16) | B15: =IF('Live Capture'!B16="","",'Live Capture'!E16) | C15: =IF('Live Capture'!B16="","",'Live Capture'!F16) | D15: =IF('Live Capture'!B16="","",'Live Capture'!I16) | E15: =IF('Live Capture'!B16="","",'Live Capture'!O16) | F15: =IF('Live Capture'!B16="","",'Live Capture'!P16) | G15: =IF('Live Capture'!B16="","",'Live Capture'!R16) | H15: =IF('Live Capture'!B16="","",'Live Capture'!S16) | I15: =IF('Live Capture'!B16="","",'Live Capture'!W16) | J15: =IF('Live Capture'!B16="","",'Live Capture'!Y16)
A16: =IF('Live Capture'!B17="","",'Live Capture'!B17) | B16: =IF('Live Capture'!B17="","",'Live Capture'!E17) | C16: =IF('Live Capture'!B17="","",'Live Capture'!F17) | D16: =IF('Live Capture'!B17="","",'Live Capture'!I17) | E16: =IF('Live Capture'!B17="","",'Live Capture'!O17) | F16: =IF('Live Capture'!B17="","",'Live Capture'!P17) | G16: =IF('Live Capture'!B17="","",'Live Capture'!R17) | H16: =IF('Live Capture'!B17="","",'Live Capture'!S17) | I16: =IF('Live Capture'!B17="","",'Live Capture'!W17) | J16: =IF('Live Capture'!B17="","",'Live Capture'!Y17)
... A504: =IF('Live Capture'!B505="","",'Live Capture'!B505) | B504: =IF('Live Capture'!B505="","",'Live Capture'!E505) | C504: =IF('Live Capture'!B505="","",'Live Capture'!F505) | D504: =IF('Live Capture'!B505="","",'Live Capture'!I505) | E504: =IF('Live Capture'!B505="","",'Live Capture'!O505) | F504: =IF('Live Capture'!B505="","",'Live Capture'!P505) | G504: =IF('Live Capture'!B505="","",'Live Capture'!R505) | H504: =IF('Live Capture'!B505="","",'Live Capture'!S505) | I504: =IF('Live Capture'!B505="","",'Live Capture'!W505) | J504: =IF('Live Capture'!B505="","",'Live Capture'!Y505)

Sheet Follow-Up Engine
A1: Follow-Up Engine
A2: Use this after each conversation. Same-day recap goes out the day of the meeting, next-step ask within 24 hours, and Primo / proof follow-up within 48 hours unless the prospect asks for something else.
A3: Template library: Follow-Up Templates tab | Meeting source: Meetings tab
A5: Capture ID | B5: Account | C5: Persona | D5: Logged At | E5: Band | F5: Due Date | G5: Follow-Up Due | H5: Asset to Send | I5: Template | J5: Owner | K5: Status | L5: Next Step | M5: Notes
A6: =IF('Live Capture'!A6="","",'Live Capture'!A6) -> LC-001 | B6: =IF(A6="","",'Live Capture'!E6) -> Danone | C6: =IF(A6="","",'Live Capture'!F6) -> Test Contact | D6: =IF(A6="","",'Live Capture'!B6) -> 46106.495 | E6: =IF(A6="","",'Live Capture'!W6) -> HOT | F6: =IF(A6="","",'Live Capture'!S6) -> 46107 | G6: =IF(A6="","",IF(F6<>"",F6,INT(D6)+IF(E6="HOT",0,IF(E6="WARM",1,IF(E6="WORK",2,5))))) -> 46107 | H6: =IF(A6="","",IF('Live Capture'!O6<>"",'Live Capture'!O6,"Leave-behind + infographic")) -> Infographic | I6: =IF(A6="","",IF('Live Capture'!T6<>"",'Live Capture'!T6,IF(E6="HOT","Post-meeting strong interest",IF(E6="WARM","Post-meeting standard","Post-meeting light")))) -> Post-meeting strong interest | J6: =IF(A6="","",'Live Capture'!R6) -> Jake | K6: =IF(A6="","",IF('Live Capture'!X6<>"",'Live Capture'!X6,"Open")) -> Open | L6: =IF(A6="","",'Live Capture'!Q6) -> Send Danone Infographic | M6: =IF(A6="","",'Live Capture'!Y6) -> Test submission from setup validation
A7: =IF('Live Capture'!A7="","",'Live Capture'!A7) | B7: =IF(A7="","",'Live Capture'!E7) | C7: =IF(A7="","",'Live Capture'!F7) | D7: =IF(A7="","",'Live Capture'!B7) | E7: =IF(A7="","",'Live Capture'!W7) | F7: =IF(A7="","",'Live Capture'!S7) | G7: =IF(A7="","",IF(F7<>"",F7,INT(D7)+IF(E7="HOT",0,IF(E7="WARM",1,IF(E7="WORK",2,5))))) | H7: =IF(A7="","",IF('Live Capture'!O7<>"",'Live Capture'!O7,"Leave-behind + infographic")) | I7: =IF(A7="","",IF('Live Capture'!T7<>"",'Live Capture'!T7,IF(E7="HOT","Post-meeting strong interest",IF(E7="WARM","Post-meeting standard","Post-meeting light")))) | J7: =IF(A7="","",'Live Capture'!R7) | K7: =IF(A7="","",IF('Live Capture'!X7<>"",'Live Capture'!X7,"Open")) | L7: =IF(A7="","",'Live Capture'!Q7) | M7: =IF(A7="","",'Live Capture'!Y7)
A8: =IF('Live Capture'!A8="","",'Live Capture'!A8) | B8: =IF(A8="","",'Live Capture'!E8) | C8: =IF(A8="","",'Live Capture'!F8) | D8: =IF(A8="","",'Live Capture'!B8) | E8: =IF(A8="","",'Live Capture'!W8) | F8: =IF(A8="","",'Live Capture'!S8) | G8: =IF(A8="","",IF(F8<>"",F8,INT(D8)+IF(E8="HOT",0,IF(E8="WARM",1,IF(E8="WORK",2,5))))) | H8: =IF(A8="","",IF('Live Capture'!O8<>"",'Live Capture'!O8,"Leave-behind + infographic")) | I8: =IF(A8="","",IF('Live Capture'!T8<>"",'Live Capture'!T8,IF(E8="HOT","Post-meeting strong interest",IF(E8="WARM","Post-meeting standard","Post-meeting light")))) | J8: =IF(A8="","",'Live Capture'!R8) | K8: =IF(A8="","",IF('Live Capture'!X8<>"",'Live Capture'!X8,"Open")) | L8: =IF(A8="","",'Live Capture'!Q8) | M8: =IF(A8="","",'Live Capture'!Y8)
A9: =IF('Live Capture'!A9="","",'Live Capture'!A9) | B9: =IF(A9="","",'Live Capture'!E9) | C9: =IF(A9="","",'Live Capture'!F9) | D9: =IF(A9="","",'Live Capture'!B9) | E9: =IF(A9="","",'Live Capture'!W9) | F9: =IF(A9="","",'Live Capture'!S9) | G9: =IF(A9="","",IF(F9<>"",F9,INT(D9)+IF(E9="HOT",0,IF(E9="WARM",1,IF(E9="WORK",2,5))))) | H9: =IF(A9="","",IF('Live Capture'!O9<>"",'Live Capture'!O9,"Leave-behind + infographic")) | I9: =IF(A9="","",IF('Live Capture'!T9<>"",'Live Capture'!T9,IF(E9="HOT","Post-meeting strong interest",IF(E9="WARM","Post-meeting standard","Post-meeting light")))) | J9: =IF(A9="","",'Live Capture'!R9) | K9: =IF(A9="","",IF('Live Capture'!X9<>"",'Live Capture'!X9,"Open")) | L9: =IF(A9="","",'Live Capture'!Q9) | M9: =IF(A9="","",'Live Capture'!Y9)
A10: =IF('Live Capture'!A10="","",'Live Capture'!A10) | B10: =IF(A10="","",'Live Capture'!E10) | C10: =IF(A10="","",'Live Capture'!F10) | D10: =IF(A10="","",'Live Capture'!B10) | E10: =IF(A10="","",'Live Capture'!W10) | F10: =IF(A10="","",'Live Capture'!S10) | G10: =IF(A10="","",IF(F10<>"",F10,INT(D10)+IF(E10="HOT",0,IF(E10="WARM",1,IF(E10="WORK",2,5))))) | H10: =IF(A10="","",IF('Live Capture'!O10<>"",'Live Capture'!O10,"Leave-behind + infographic")) | I10: =IF(A10="","",IF('Live Capture'!T10<>"",'Live Capture'!T10,IF(E10="HOT","Post-meeting strong interest",IF(E10="WARM","Post-meeting standard","Post-meeting light")))) | J10: =IF(A10="","",'Live Capture'!R10) | K10: =IF(A10="","",IF('Live Capture'!X10<>"",'Live Capture'!X10,"Open")) | L10: =IF(A10="","",'Live Capture'!Q10) | M10: =IF(A10="","",'Live Capture'!Y10)
A11: =IF('Live Capture'!A11="","",'Live Capture'!A11) | B11: =IF(A11="","",'Live Capture'!E11) | C11: =IF(A11="","",'Live Capture'!F11) | D11: =IF(A11="","",'Live Capture'!B11) | E11: =IF(A11="","",'Live Capture'!W11) | F11: =IF(A11="","",'Live Capture'!S11) | G11: =IF(A11="","",IF(F11<>"",F11,INT(D11)+IF(E11="HOT",0,IF(E11="WARM",1,IF(E11="WORK",2,5))))) | H11: =IF(A11="","",IF('Live Capture'!O11<>"",'Live Capture'!O11,"Leave-behind + infographic")) | I11: =IF(A11="","",IF('Live Capture'!T11<>"",'Live Capture'!T11,IF(E11="HOT","Post-meeting strong interest",IF(E11="WARM","Post-meeting standard","Post-meeting light")))) | J11: =IF(A11="","",'Live Capture'!R11) | K11: =IF(A11="","",IF('Live Capture'!X11<>"",'Live Capture'!X11,"Open")) | L11: =IF(A11="","",'Live Capture'!Q11) | M11: =IF(A11="","",'Live Capture'!Y11)
A12: =IF('Live Capture'!A12="","",'Live Capture'!A12) | B12: =IF(A12="","",'Live Capture'!E12) | C12: =IF(A12="","",'Live Capture'!F12) | D12: =IF(A12="","",'Live Capture'!B12) | E12: =IF(A12="","",'Live Capture'!W12) | F12: =IF(A12="","",'Live Capture'!S12) | G12: =IF(A12="","",IF(F12<>"",F12,INT(D12)+IF(E12="HOT",0,IF(E12="WARM",1,IF(E12="WORK",2,5))))) | H12: =IF(A12="","",IF('Live Capture'!O12<>"",'Live Capture'!O12,"Leave-behind + infographic")) | I12: =IF(A12="","",IF('Live Capture'!T12<>"",'Live Capture'!T12,IF(E12="HOT","Post-meeting strong interest",IF(E12="WARM","Post-meeting standard","Post-meeting light")))) | J12: =IF(A12="","",'Live Capture'!R12) | K12: =IF(A12="","",IF('Live Capture'!X12<>"",'Live Capture'!X12,"Open")) | L12: =IF(A12="","",'Live Capture'!Q12) | M12: =IF(A12="","",'Live Capture'!Y12)
A13: =IF('Live Capture'!A13="","",'Live Capture'!A13) | B13: =IF(A13="","",'Live Capture'!E13) | C13: =IF(A13="","",'Live Capture'!F13) | D13: =IF(A13="","",'Live Capture'!B13) | E13: =IF(A13="","",'Live Capture'!W13) | F13: =IF(A13="","",'Live Capture'!S13) | G13: =IF(A13="","",IF(F13<>"",F13,INT(D13)+IF(E13="HOT",0,IF(E13="WARM",1,IF(E13="WORK",2,5))))) | H13: =IF(A13="","",IF('Live Capture'!O13<>"",'Live Capture'!O13,"Leave-behind + infographic")) | I13: =IF(A13="","",IF('Live Capture'!T13<>"",'Live Capture'!T13,IF(E13="HOT","Post-meeting strong interest",IF(E13="WARM","Post-meeting standard","Post-meeting light")))) | J13: =IF(A13="","",'Live Capture'!R13) | K13: =IF(A13="","",IF('Live Capture'!X13<>"",'Live Capture'!X13,"Open")) | L13: =IF(A13="","",'Live Capture'!Q13) | M13: =IF(A13="","",'Live Capture'!Y13)
A14: =IF('Live Capture'!A14="","",'Live Capture'!A14) | B14: =IF(A14="","",'Live Capture'!E14) | C14: =IF(A14="","",'Live Capture'!F14) | D14: =IF(A14="","",'Live Capture'!B14) | E14: =IF(A14="","",'Live Capture'!W14) | F14: =IF(A14="","",'Live Capture'!S14) | G14: =IF(A14="","",IF(F14<>"",F14,INT(D14)+IF(E14="HOT",0,IF(E14="WARM",1,IF(E14="WORK",2,5))))) | H14: =IF(A14="","",IF('Live Capture'!O14<>"",'Live Capture'!O14,"Leave-behind + infographic")) | I14: =IF(A14="","",IF('Live Capture'!T14<>"",'Live Capture'!T14,IF(E14="HOT","Post-meeting strong interest",IF(E14="WARM","Post-meeting standard","Post-meeting light")))) | J14: =IF(A14="","",'Live Capture'!R14) | K14: =IF(A14="","",IF('Live Capture'!X14<>"",'Live Capture'!X14,"Open")) | L14: =IF(A14="","",'Live Capture'!Q14) | M14: =IF(A14="","",'Live Capture'!Y14)
A15: =IF('Live Capture'!A15="","",'Live Capture'!A15) | B15: =IF(A15="","",'Live Capture'!E15) | C15: =IF(A15="","",'Live Capture'!F15) | D15: =IF(A15="","",'Live Capture'!B15) | E15: =IF(A15="","",'Live Capture'!W15) | F15: =IF(A15="","",'Live Capture'!S15) | G15: =IF(A15="","",IF(F15<>"",F15,INT(D15)+IF(E15="HOT",0,IF(E15="WARM",1,IF(E15="WORK",2,5))))) | H15: =IF(A15="","",IF('Live Capture'!O15<>"",'Live Capture'!O15,"Leave-behind + infographic")) | I15: =IF(A15="","",IF('Live Capture'!T15<>"",'Live Capture'!T15,IF(E15="HOT","Post-meeting strong interest",IF(E15="WARM","Post-meeting standard","Post-meeting light")))) | J15: =IF(A15="","",'Live Capture'!R15) | K15: =IF(A15="","",IF('Live Capture'!X15<>"",'Live Capture'!X15,"Open")) | L15: =IF(A15="","",'Live Capture'!Q15) | M15: =IF(A15="","",'Live Capture'!Y15)
A16: =IF('Live Capture'!A16="","",'Live Capture'!A16) | B16: =IF(A16="","",'Live Capture'!E16) | C16: =IF(A16="","",'Live Capture'!F16) | D16: =IF(A16="","",'Live Capture'!B16) | E16: =IF(A16="","",'Live Capture'!W16) | F16: =IF(A16="","",'Live Capture'!S16) | G16: =IF(A16="","",IF(F16<>"",F16,INT(D16)+IF(E16="HOT",0,IF(E16="WARM",1,IF(E16="WORK",2,5))))) | H16: =IF(A16="","",IF('Live Capture'!O16<>"",'Live Capture'!O16,"Leave-behind + infographic")) | I16: =IF(A16="","",IF('Live Capture'!T16<>"",'Live Capture'!T16,IF(E16="HOT","Post-meeting strong interest",IF(E16="WARM","Post-meeting standard","Post-meeting light")))) | J16: =IF(A16="","",'Live Capture'!R16) | K16: =IF(A16="","",IF('Live Capture'!X16<>"",'Live Capture'!X16,"Open")) | L16: =IF(A16="","",'Live Capture'!Q16) | M16: =IF(A16="","",'Live Capture'!Y16)
A17: =IF('Live Capture'!A17="","",'Live Capture'!A17) | B17: =IF(A17="","",'Live Capture'!E17) | C17: =IF(A17="","",'Live Capture'!F17) | D17: =IF(A17="","",'Live Capture'!B17) | E17: =IF(A17="","",'Live Capture'!W17) | F17: =IF(A17="","",'Live Capture'!S17) | G17: =IF(A17="","",IF(F17<>"",F17,INT(D17)+IF(E17="HOT",0,IF(E17="WARM",1,IF(E17="WORK",2,5))))) | H17: =IF(A17="","",IF('Live Capture'!O17<>"",'Live Capture'!O17,"Leave-behind + infographic")) | I17: =IF(A17="","",IF('Live Capture'!T17<>"",'Live Capture'!T17,IF(E17="HOT","Post-meeting strong interest",IF(E17="WARM","Post-meeting standard","Post-meeting light")))) | J17: =IF(A17="","",'Live Capture'!R17) | K17: =IF(A17="","",IF('Live Capture'!X17<>"",'Live Capture'!X17,"Open")) | L17: =IF(A17="","",'Live Capture'!Q17) | M17: =IF(A17="","",'Live Capture'!Y17)
... A505: =IF('Live Capture'!A505="","",'Live Capture'!A505) | B505: =IF(A505="","",'Live Capture'!E505) | C505: =IF(A505="","",'Live Capture'!F505) | D505: =IF(A505="","",'Live Capture'!B505) | E505: =IF(A505="","",'Live Capture'!W505) | F505: =IF(A505="","",'Live Capture'!S505) | G505: =IF(A505="","",IF(F505<>"",F505,INT(D505)+IF(E505="HOT",0,IF(E505="WARM",1,IF(E505="WORK",2,5))))) | H505: =IF(A505="","",IF('Live Capture'!O505<>"",'Live Capture'!O505,"Leave-behind + infographic")) | I505: =IF(A505="","",IF('Live Capture'!T505<>"",'Live Capture'!T505,IF(E505="HOT","Post-meeting strong interest",IF(E505="WARM","Post-meeting standard","Post-meeting light")))) | J505: =IF(A505="","",'Live Capture'!R505) | K505: =IF(A505="","",IF('Live Capture'!X505<>"",'Live Capture'!X505,"Open")) | L505: =IF(A505="","",'Live Capture'!Q505) | M505: =IF(A505="","",'Live Capture'!Y505)

Sheet Follow-Up Templates
A1: Follow-Up Templates
A2: Fast templates Jake can use same day from MODEX. Edit the bracketed fields and send.
A4: Template | B4: Use Case | C4: Subject Line | D4: Body
A5: Post-meeting strong interest | B5: Met live, good conversation, clear pain | C5: Great meeting you at MODEX, [Account] | D5: Good meeting you at MODEX. Based on our conversation, it sounds like [Account] is focused on [pain / objective]. Jake would love to keep the momentum going with a short follow-up next week to show how YardFlow standardizes the gate-to-dock sequence and helps sites move more volume without adding headcount. Attaching the account-specific one-pager we discussed. Would [day/time option 1] or [day/time option 2] work?
A6: Post-meeting standard | B6: Solid conversation, not fully qualified yet | C6: Following up from MODEX, [Account] | D6: Thanks again for the conversation at MODEX. Sharing the one-pager we referenced so you have the operating hypothesis in writing. If it would be helpful, Jake can do a 20-minute follow-up to pressure-test whether this is relevant for your sites and whether a customer proof conversation with Primo would be useful.
A7: Warm intro ask | B7: Use with connector / mutual contact | C7: Quick intro request for [Account] at MODEX follow-up | D7: Wanted to see if you would be comfortable connecting Jake with [Name / Team] at [Account]. We had a relevant MODEX conversation around standardizing gate-to-dock flow, reducing dock-office friction, and increasing throughput without adding headcount. Happy to send a short blurb you can forward.
A8: Primo proof ask | B8: Prospect wants social proof or customer voice | C8: Possible customer-proof follow-up for [Account] | D8: One reason I thought the conversation was worth continuing is that Primo has already deployed YardFlow across live facilities and is willing to help validate the operational value in the right conversations. If helpful, we can set up a short follow-up call with Jake first and then decide whether a customer-proof step makes sense.
A9: No-show / missed connect | B9: Meeting slipped or booth pass-by did not land | C9: Missed each other at MODEX | D9: Looks like we just missed each other at MODEX. Rather than let the opportunity die on the show floor, I’m attaching the one-page account hypothesis Jake prepared for [Account]. If the problem statement is directionally right, we should grab 20 minutes next week.
A10: Internal recap | B10: Send to Jake / internal team after live convo | C10: MODEX recap: [Account] | D10: Account: [Account] Who we met: [Names] Signals: [pain, urgency, current process, event relevance] Best angle: [Primo / throughput / standardization / chain of custody] Next step needed: [intro, follow-up call, asset send, customer proof] Owner: [Name] Due: [Date]

Sheet Leave-Behind Index
A1: Top 10 Leave-Behind Pack
A2: One-page printable meeting briefs for Jake. Each sheet pairs the custom infographic with the meeting thesis, talk track, discovery path, objection handling, and close.
A4: Rank | B4: Account | C4: Sheet | D4: Exec Anchor | E4: Operator Anchor | F4: Meeting Wedge | G4: Primary Ask | H4: Infographic File
A5: 1 | B5: Danone | C5: LB - Danone | D5: Heiko Gerling | Chief Operations Officer, North America | E5: Whitney Klemm | Supply Chain Leader | F5: Show how Primo used yard/process standardization to lift throughput without adding yard labor. | G5: Use the Mark Shaughnessy route to secure a 20-minute meeting with Heiko Gerling or his delegate, and tee up a follow-on review with the Jacksonville / network ops team plus a Primo reference. | H5: Danone.png
A6: 2 | B6: General Mills | C6: LB - General Mills | D6: Jonathan Ness | Chief Supply Chain Officer | E6: Nisar Ahsanullah | General Mills supply chain leader | F6: Anchor on multi-site consistency and how standardized yard execution supports sourcing, planning, manufacturing, logistics, and customer operations. | G6: Book a 15-20 minute MODEX meeting with the exec anchor or a direct report, then lock a follow-up working session with the operator owner inside 7 days. | H6: General_Mills.png
A7: 3 | B7: Frito-Lay | C7: LB - Frito-Lay | D7: Beth Mars | Transportation Director | E7: Brian Watson | Vice President of Supply Chain | F7: Position YardFlow as the layer that reduces execution variance when network design is shifting under the business. | G7: Book a 15-20 minute MODEX meeting with the exec anchor or a direct report, then lock a follow-up working session with the operator owner inside 7 days. | H7: Frito_Lay.png
A8: 4 | B8: Diageo | C8: LB - Diageo | D8: Raymond Reddrick | SVP North America Supply - Manufacturing and Distillation | E8: Marsha McIntosh-Hamilton | President of North America Supply | F8: Use Primo to prove YardFlow is not theory; it is a way to make new network capacity behave better, faster. | G8: Book a 15-20 minute MODEX meeting with the exec anchor or a direct report, then lock a follow-up working session with the operator owner inside 7 days. | H8: Diageo.png
A9: 5 | B9: Hormel Foods | C9: LB - Hormel Foods | D9: Will Bonifant | Group Vice President and Chief Supply Chain Officer | E9: Nicholas Schwartz | Supply Chain Planning COE & Strategy Lead | F9: Use Primo to show that standard work in the yard can compound with broader supply-chain transformation. | G9: Book a 15-20 minute MODEX meeting with the exec anchor or a direct report, then lock a follow-up working session with the operator owner inside 7 days. | H9: Hormel_Foods.png
A10: 6 | B10: JM Smucker | C10: LB - JM Smucker | D10: Rob Ferguson | Chief Product Supply Officer | Executive Vice President, Coffee, Pet, and Away From Home | E10: Anbu Kuppusamy | Transportation Function Leader | F10: Frame YardFlow as a way to reduce site-by-site operational variance across distribution and manufacturing flows. | G10: Book a 15-20 minute MODEX meeting with the exec anchor or a direct report, then lock a follow-up working session with the operator owner inside 7 days. | H10: JM_Smucker.png
A11: 7 | B11: The Home Depot | C11: LB - The Home Depot | D11: John Deaton | Executive Vice President – Supply Chain & Product Development | E11: Amit Kalra | Senior Vice President – Supply Chain | F11: Position YardFlow as site-level flow standardization for high-volume campuses where transport handoffs and trailer orchestration matter. | G11: Book a MODEX floor-side meeting with the named leader or chief of staff and leave with one owner for a post-show operational deep dive. | H11: The_Home_Depot.png
A12: 8 | B12: Georgia Pacific | C12: LB - Georgia Pacific | D12: Jeremy Finley | Vice President, Supply Chain | E12: Ryan Hutcherson | Senior Vice President, Supply Chain | F12: Lead with yard, gate, trailer visibility, and dock-flow standardization. | G12: Book a 15-20 minute MODEX meeting with the exec anchor or a direct report, then lock a follow-up working session with the operator owner inside 7 days. | H12: Georgia_Pacific.png
A13: 9 | B13: H-E-B | C13: LB - H-E-B | D13: Dakota Socha | Transportation & Reverse Logistics | E13: Craig Stucker | Director, Parkway Transport at H-E-B | F13: Use Primo to position YardFlow as the connective tissue between network growth and site-level execution. | G13: Book a 15-20 minute MODEX meeting with the exec anchor or a direct report, then lock a follow-up working session with the operator owner inside 7 days. | H13: H_E_B.png
A14: 10 | B14: Hyundai Motor America | C14: LB - Hyundai Motor America | D14: Carey Gammon | Director, Vehicle Operations (HMA) | E14: Yongchul Chung | Senior Manager, Global Logistics & Supply Chain | F14: Lead with finished-vehicle / campus-flow standardization and escalation visibility. | G14: Book a 15-20 minute MODEX meeting with the exec anchor or a direct report, then lock a follow-up working session with the operator owner inside 7 days. | H14: Hyundai_Motor_America.png

Sheet Jake Battlecards
A1: Jake Battlecards
A2: Top-20 account battlecards for Jake at MODEX. Built to bridge each custom infographic into a sharp meeting thesis, discovery path, objection response, and ask.
A4: Rank | B4: Account | C4: Vertical | D4: Public trigger / why now | E4: Exec anchor | F4: Operator anchor | G4: Best intro route | H4: 15-sec opener | I4: 30-sec hypothesis | J4: Discovery path (3 questions) | K4: Likely objection | L4: Counter | M4: Primary MODEX ask | N4: Fallback ask | O4: Proof stack | P4: Source URL 1 | Q4: Source URL 2 | R4: Infographic
A5: 1 | B5: Danone | C5: Food & Beverage | D5: Danone North America put Heiko Gerling into the COO role in 2025 and is transforming its logistics network, including a Jacksonville RDC milestone and a $65M Jacksonville production-line expansion. | E5: Heiko Gerling | Chief Operations Officer, North America | F5: Whitney Klemm | Supply Chain Leader | G5: Mark -> Heiko / CSCO office | H5: You have public signs of change right now: Danone North America put Heiko Gerling into the COO role in 2025 and is transforming its logistics network, including a Jacksonville RDC milestone and a $65M Jacksonville production-line expansion. If MODEX is on the calendar, our thesis is simple: YardFlow helps large networks reduce execution variance at the gate and dock so sites ship more with less drama. | I5: Show how Primo used yard/process standardization to lift throughput without adding yard labor. | J5: 1. How standardized is the driver journey from gate check-in through dock assignment across sites today? 2. Where do trailer queues, dock-office workarounds, or detention pain show up most often in your network? 3. How much of the current pressure is concentrated in Jacksonville or other constrained high-volume sites? | K5: We already have processes and probably have scheduling tech in place. | L5: Perfect. YardFlow is not a rip-and-replace pitch. The wedge is standardizing the driver journey and dock handoffs across sites so the process actually behaves the same way under pressure. | M5: Use the Mark Shaughnessy route to secure a 20-minute meeting with Heiko Gerling or his delegate, and tee up a follow-on review with the Jacksonville / network ops team plus a Primo reference. | N5: If they will not commit live, ask for the right operator owner, permission to send the account infographic, and a scheduled post-show working session. | O5: Danone-specific infographic + Primo proof + offer for Primo customer reference join-in. | P5: https://www.danonenorthamerica.com/about-us/our-leaders.html | Q5: https://www.danonenorthamerica.com/newsroom/details/danone-announces-opening-of-new-65-million-production-line-in-jacksonville-florida.html.html.html.html | R5: View graphic
A6: 2 | B6: General Mills | C6: Food & Beverage | D6: Jonathan Ness was named Chief Supply Chain Officer in March 2026. | E6: Jonathan Ness | Chief Supply Chain Officer | F6: Nisar Ahsanullah | General Mills supply chain leader | G6: Direct outreach to CSCO office | H6: You have public signs of change right now: Jonathan Ness was named Chief Supply Chain Officer in March 2026. If MODEX is on the calendar, our thesis is simple: YardFlow helps large networks reduce execution variance at the gate and dock so sites ship more with less drama. | I6: Anchor on multi-site consistency and how standardized yard execution supports sourcing, planning, manufacturing, logistics, and customer operations. | J6: 1. How standardized is the driver journey from gate check-in through dock assignment across sites today? 2. Where do trailer queues, dock-office workarounds, or detention pain show up most often in your network? 3. With a new CSCO in seat, where is the team most focused: service, cost, standardization, or resilience? | K6: We just changed CSCOs; now is not the time. | L6: Fresh leadership is exactly when teams revisit where standardization can unlock service and productivity. This is a low-drama operational wedge, not a transformation moonshot. | M6: Book a 15-20 minute MODEX meeting with the exec anchor or a direct report, then lock a follow-up working session with the operator owner inside 7 days. | N6: If they will not commit live, ask for the right operator owner, permission to send the account infographic, and a scheduled post-show working session. | O6: Primo proof + short ROI angle around reduced variance and higher throughput. | P6: https://www.generalmills.com/news/press-releases/general-mills-names-jonathan-ness-chief-supply-chain-officer | Q6: https://www.generalmills.com/about-us/leadership | R6: View graphic
A7: 3 | B7: Frito-Lay | C7: Food & Beverage | D7: PepsiCo is pushing a One North America agenda and has been testing combined snack-and-beverage warehousing. | E7: Beth Mars | Transportation Director | F7: Brian Watson | Vice President of Supply Chain | G7: LinkedIn / Sales Nav | H7: You have public signs of change right now: PepsiCo is pushing a One North America agenda and has been testing combined snack-and-beverage warehousing. If MODEX is on the calendar, our thesis is simple: YardFlow helps large networks reduce execution variance at the gate and dock so sites ship more with less drama. | I7: Position YardFlow as the layer that reduces execution variance when network design is shifting under the business. | J7: 1. How standardized is the driver journey from gate check-in through dock assignment across sites today? 2. Where do trailer queues, dock-office workarounds, or detention pain show up most often in your network? 3. As snack-and-beverage warehousing gets tested, what breaks first at the facility edge? | K7: Our network is too big and too integrated for a niche yard tool. | L7: That’s precisely why variance at the site level matters. The point is not a niche tool; it is a standardized execution layer when network design is changing. | M7: Book a 15-20 minute MODEX meeting with the exec anchor or a direct report, then lock a follow-up working session with the operator owner inside 7 days. | N7: If they will not commit live, ask for the right operator owner, permission to send the account infographic, and a scheduled post-show working session. | O7: Primo proof + variance-tax framing. | P7: https://www.pepsico.com/newsroom/stories/2025/pepsico-announces-organizational-changes-to-accelerate-growth | Q7: https://investors.pepsico.com/docs/pepsico-5v9wci20/media/Files/investors/q3-2025-prepared-management-remarks.pdf | R7: View graphic
A8: 4 | B8: Diageo | C8: Food & Beverage | D8: Diageo North America announced a new manufacturing and warehousing facility in Alabama to enhance North America supply chain operations. | E8: Raymond Reddrick | SVP North America Supply - Manufacturing and Distillation | F8: Marsha McIntosh-Hamilton | President of North America Supply | G8: LinkedIn / Sales Nav | H8: You have public signs of change right now: Diageo North America announced a new manufacturing and warehousing facility in Alabama to enhance North America supply chain operations. If MODEX is on the calendar, our thesis is simple: YardFlow helps large networks reduce execution variance at the gate and dock so sites ship more with less drama. | I8: Use Primo to prove YardFlow is not theory; it is a way to make new network capacity behave better, faster. | J8: 1. How standardized is the driver journey from gate check-in through dock assignment across sites today? 2. Where do trailer queues, dock-office workarounds, or detention pain show up most often in your network? 3. As Alabama comes online, how are you thinking about operating protocol consistency across the North America network? | K8: We’re already investing in facilities and automation. | L8: Great. Capital projects raise the stakes on site execution. The closer the business gets to new capacity, the more expensive non-standard yard flow becomes. | M8: Book a 15-20 minute MODEX meeting with the exec anchor or a direct report, then lock a follow-up working session with the operator owner inside 7 days. | N8: If they will not commit live, ask for the right operator owner, permission to send the account infographic, and a scheduled post-show working session. | O8: Primo proof + manufacturing / warehousing site-flow angle. | P8: https://www.diageo.com/en/news-and-media/press-releases/2025/diageo-north-america-announces-new-manufacturing-and-warehousing-facility-in-alabama | Q8: https://www.diageo.com/~/media/Files/D/Diageo-V2/Diageo-Corp/investors/results-reports-and-events/investor-events/2025/cagny-2025-presentation-with-script.pdf | R8: View graphic
A9: 5 | B9: Hormel Foods | C9: Food & Beverage | D9: Will Bonifant was appointed group vice president and chief supply chain officer in February 2026. | E9: Will Bonifant | Group Vice President and Chief Supply Chain Officer | F9: Nicholas Schwartz | Supply Chain Planning COE & Strategy Lead | G9: Direct outreach to CSCO office | H9: You have public signs of change right now: Will Bonifant was appointed group vice president and chief supply chain officer in February 2026. If MODEX is on the calendar, our thesis is simple: YardFlow helps large networks reduce execution variance at the gate and dock so sites ship more with less drama. | I9: Use Primo to show that standard work in the yard can compound with broader supply-chain transformation. | J9: 1. How standardized is the driver journey from gate check-in through dock assignment across sites today? 2. Where do trailer queues, dock-office workarounds, or detention pain show up most often in your network? 3. Where are planning, logistics, and manufacturing most likely to fall out of sync during peaks? | K9: We need to focus higher in the supply chain than the yard. | L9: The yard is where planning, production, transportation, and customer service collide in real life. Fixing the handoff is how strategy shows up on the dock. | M9: Book a 15-20 minute MODEX meeting with the exec anchor or a direct report, then lock a follow-up working session with the operator owner inside 7 days. | N9: If they will not commit live, ask for the right operator owner, permission to send the account infographic, and a scheduled post-show working session. | O9: Primo proof + transformation angle. | P9: https://www.hormelfoods.com/newsroom/press-releases/hormel-foods-names-will-bonifant-group-vice-president-and-chief-supply-chain-officer/ | Q9: https://www.hormelfoods.com/about/leadership/ | R9: View graphic
A10: 6 | B10: JM Smucker | C10: Food & Beverage | D10: Smucker created a new Chief Product Supply Officer role and promoted Rob Ferguson into it in February 2026. | E10: Rob Ferguson | Chief Product Supply Officer | Executive Vice President, Coffee, Pet, and Away From Home | F10: Anbu Kuppusamy | Transportation Function Leader | G10: Direct outreach to product supply office | H10: You have public signs of change right now: Smucker created a new Chief Product Supply Officer role and promoted Rob Ferguson into it in February 2026. If MODEX is on the calendar, our thesis is simple: YardFlow helps large networks reduce execution variance at the gate and dock so sites ship more with less drama. | I10: Frame YardFlow as a way to reduce site-by-site operational variance across distribution and manufacturing flows. | J10: 1. How standardized is the driver journey from gate check-in through dock assignment across sites today? 2. Where do trailer queues, dock-office workarounds, or detention pain show up most often in your network? 3. What would Rob Ferguson most want fixed first: service misses, labor inefficiency, or site-to-site inconsistency? | K10: We have bigger priorities than check-in and trailer staging. | L10: Exactly why this works: it is a contained operational lever that can improve throughput and service without asking the org to swallow a giant program. | M10: Book a 15-20 minute MODEX meeting with the exec anchor or a direct report, then lock a follow-up working session with the operator owner inside 7 days. | N10: If they will not commit live, ask for the right operator owner, permission to send the account infographic, and a scheduled post-show working session. | O10: Primo proof + variance-tax framing. | P10: https://investors.jmsmucker.com/news/news-details/2026/The-J-M--Smucker-Co--Announces-Senior-Leadership-Updates-to-Drive-Continued-Growth-and-Execution/default.aspx | Q10: https://investors.jmsmucker.com/governance/company-officers/default.aspx | R10: View graphic
A11: 7 | B11: The Home Depot | C11: Retail | D11: Richard McPhail is a MODEX 2026 keynote. Home Depot also has a visible public supply-chain bench including Amit Kalra and John Drake. | E11: John Deaton | Executive Vice President – Supply Chain & Product Development | F11: Amit Kalra | Senior Vice President – Supply Chain | G11: Executive outreach | H11: You have public signs of change right now: Richard McPhail is a MODEX 2026 keynote. Home Depot also has a visible public supply-chain bench including Amit Kalra and John Drake. If MODEX is on the calendar, our thesis is simple: YardFlow helps large networks reduce execution variance at the gate and dock so sites ship more with less drama. | I11: Position YardFlow as site-level flow standardization for high-volume campuses where transport handoffs and trailer orchestration matter. | J11: 1. How standardized is the driver journey from gate check-in through dock assignment across sites today? 2. Where do trailer queues, dock-office workarounds, or detention pain show up most often in your network? 3. Across transportation and direct-to-customer delivery, where does local site variance create the most downstream noise? | K11: We already run a sophisticated supply chain. | L11: No argument. The pitch is not sophistication, it is site consistency. Even elite networks leak performance when every yard and dock team improvises under pressure. | M11: Book a MODEX floor-side meeting with the named leader or chief of staff and leave with one owner for a post-show operational deep dive. | N11: If they will not commit live, ask for the right operator owner, permission to send the account infographic, and a scheduled post-show working session. | O11: Primo proof + one-pager focused on standardization, traffic flow, and execution consistency. | P11: https://corporate.homedepot.com/page/home-depot-leadership-0?page=1 | Q11: https://www.modexshow.com/education | R11: View graphic
A12: 8 | B12: Georgia Pacific | C12: Industrial | D12: Georgia-Pacific is expanding Palatka with an $83M project including a 36-acre trailer yard, 574-trailer capacity, an inspection station, and warehouse expansion. | E12: Jeremy Finley | Vice President, Supply Chain | F12: Ryan Hutcherson | Senior Vice President, Supply Chain | G12: LinkedIn / Sales Nav | H12: You have public signs of change right now: Georgia-Pacific is expanding Palatka with an $83M project including a 36-acre trailer yard, 574-trailer capacity, an inspection station, and warehouse expansion. If MODEX is on the calendar, our thesis is simple: YardFlow helps large networks reduce execution variance at the gate and dock so sites ship more with less drama. | I12: Lead with yard, gate, trailer visibility, and dock-flow standardization. | J12: 1. How standardized is the driver journey from gate check-in through dock assignment across sites today? 2. Where do trailer queues, dock-office workarounds, or detention pain show up most often in your network? 3. With more trailer capacity at Palatka, how will the team keep the yard from becoming a larger, faster bottleneck? | K12: A trailer yard expansion already solves our problem. | L12: It solves capacity. It does not guarantee disciplined flow, dock direction, or timestamped accountability once more trailers arrive. | M12: Book a 15-20 minute MODEX meeting with the exec anchor or a direct report, then lock a follow-up working session with the operator owner inside 7 days. | N12: If they will not commit live, ask for the right operator owner, permission to send the account infographic, and a scheduled post-show working session. | O12: Primo proof + operator-first demo angle. | P12: https://www.prnewswire.com/news-releases/georgia-pacific-announces-83-million-expansion-project-at-palatka-florida-facility-302150221.html | Q12: https://news.gp.com/ | R12: View graphic
A13: 9 | B13: H-E-B | C13: Retail | D13: H-E-B bought 600+ acres in North Texas for a master-planned supply-chain campus and is expanding logistics capacity for continued DFW growth. | E13: Dakota Socha | Transportation & Reverse Logistics | F13: Craig Stucker | Director, Parkway Transport at H-E-B | G13: LinkedIn / Sales Nav | H13: You have public signs of change right now: H-E-B bought 600+ acres in North Texas for a master-planned supply-chain campus and is expanding logistics capacity for continued DFW growth. If MODEX is on the calendar, our thesis is simple: YardFlow helps large networks reduce execution variance at the gate and dock so sites ship more with less drama. | I13: Use Primo to position YardFlow as the connective tissue between network growth and site-level execution. | J13: 1. How standardized is the driver journey from gate check-in through dock assignment across sites today? 2. Where do trailer queues, dock-office workarounds, or detention pain show up most often in your network? 3. Before the North Texas campus muscle memory hardens, what operating standards do you most want baked in? | K13: We’re building future capacity; this is a later conversation. | L13: That’s why now matters. The cheapest moment to standardize operating protocol is before the new campus muscle memory hardens. | M13: Book a 15-20 minute MODEX meeting with the exec anchor or a direct report, then lock a follow-up working session with the operator owner inside 7 days. | N13: If they will not commit live, ask for the right operator owner, permission to send the account infographic, and a scheduled post-show working session. | O13: Primo proof + retail distribution growth angle. | P13: https://newsroom.heb.com/h-e-b-buys-land-to-develop-a-master-planned-supply-chain-campus-in-north-texas/ | Q13: https://newsroom.heb.com/articles/ | R13: View graphic
A14: 10 | B14: Hyundai Motor America | C14: Manufacturing | D14: Automotive distribution and finished-vehicle logistics complexity plus official past-attendee signal. | E14: Carey Gammon | Director, Vehicle Operations (HMA) | F14: Yongchul Chung | Senior Manager, Global Logistics & Supply Chain | G14: Public LinkedIn / vehicle ops route | H14: You have public signs of change right now: Automotive distribution and finished-vehicle logistics complexity plus official past-attendee signal. If MODEX is on the calendar, our thesis is simple: YardFlow helps large networks reduce execution variance at the gate and dock so sites ship more with less drama. | I14: Lead with finished-vehicle / campus-flow standardization and escalation visibility. | J14: 1. How standardized is the driver journey from gate check-in through dock assignment across sites today? 2. Where do trailer queues, dock-office workarounds, or detention pain show up most often in your network? 3. Which logistics motions are most sensitive to staging and release discipline on campus today? | K14: Finished vehicle and parts logistics are too specialized. | L14: Agreed, but the pattern is the same: standardized routing, staging, and release discipline reduce avoidable friction on complex campuses. | M14: Book a 15-20 minute MODEX meeting with the exec anchor or a direct report, then lock a follow-up working session with the operator owner inside 7 days. | N14: If they will not commit live, ask for the right operator owner, permission to send the account infographic, and a scheduled post-show working session. | O14: Primo proof + automotive analog frame | P14: https://www.hyundainews.com/releases/761 | Q14: https://www.hyundainews.com/releases/4537 | R14: View graphic
A15: 11 | B15: Honda | C15: Manufacturing | D15: Large manufacturing campuses and logistics complexity make yard execution a lever. | E15: Jim Small | Executive Vice President, Manufacturing | F15: Nicole Miller | Logistics leader | G15: Manufacturing / logistics route | H15: You have public signs of change right now: Large manufacturing campuses and logistics complexity make yard execution a lever. If MODEX is on the calendar, our thesis is simple: YardFlow helps large networks reduce execution variance at the gate and dock so sites ship more with less drama. | I15: Talk standard-driver-journey, trailer orchestration, and site-to-site discipline. | J15: 1. How standardized is the driver journey from gate check-in through dock assignment across sites today? 2. Where do trailer queues, dock-office workarounds, or detention pain show up most often in your network? 3. Which plants or distribution campuses feel the most friction between production, staging, and outbound release? | K15: We’re manufacturing-first; the yard is downstream. | L15: Downstream is where revenue leaves the site. If outbound flow stumbles, manufacturing wins do not fully turn into shipped volume. | M15: Book a 15-20 minute MODEX meeting with the exec anchor or a direct report, then lock a follow-up working session with the operator owner inside 7 days. | N15: If they will not commit live, ask for the right operator owner, permission to send the account infographic, and a scheduled post-show working session. | O15: Primo proof + plant throughput frame | P15: https://hondanews.com/pages/executives | Q15: https://hondanews.com/en-US/honda-corporate/releases/release-f09141ba9e0061c24e5e5b0bb316ba72-honda-honors-52-suppliers-in-north-america-for-outstanding-performance-2 | R15: View graphic
A16: 12 | B16: John Deere | C16: Manufacturing | D16: Industrial campus complexity and dealer/service expectations make execution discipline relevant. | E16: Cory Reed | President, Worldwide Agriculture & Turf, Production & Precision Ag, Customer Success | F16: Steve Wilhelmi | Vice President, Logistics | G16: Corporate logistics route | H16: You have public signs of change right now: Industrial campus complexity and dealer/service expectations make execution discipline relevant. If MODEX is on the calendar, our thesis is simple: YardFlow helps large networks reduce execution variance at the gate and dock so sites ship more with less drama. | I16: Frame around industrial-campus standardization and throughput visibility. | J16: 1. How standardized is the driver journey from gate check-in through dock assignment across sites today? 2. Where do trailer queues, dock-office workarounds, or detention pain show up most often in your network? 3. Where do dealer expectations and site execution collide hardest in your logistics network? | K16: We already have strong logistics leadership. | L16: Great. Strong leadership tends to like measurable, repeatable operational control. YardFlow gives them a tighter execution standard at the site edge. | M16: Book a 15-20 minute MODEX meeting with the exec anchor or a direct report, then lock a follow-up working session with the operator owner inside 7 days. | N16: If they will not commit live, ask for the right operator owner, permission to send the account infographic, and a scheduled post-show working session. | O16: Primo proof + industrial campus frame | P16: https://about.deere.com/en-us/explore-john-deere/leadership/cory-reed | Q16: https://about.deere.com/en-us/explore-john-deere/fellows | R16: View graphic
... A24: 20 | B24: IKEA | C24: Retail | D24: IKEA U.S. continues expanding smaller-format locations and has publicly highlighted logistics units and growing zero-emission delivery operations, while Henrik Elm oversees supply and operations across the total IKEA value chain. | E24: Rob Olson | Chief Operating Officer, IKEA U.S. | F24: Pam Andrews | Vice President of Logistics | G24: U.S. ops + logistics route | H24: You have public signs of change right now: IKEA U.S. continues expanding smaller-format locations and has publicly highlighted logistics units and growing zero-emission delivery operations, while Henrik Elm oversees supply and operations across the total IKEA value chain. If MODEX is on the calendar, our thesis is simple: YardFlow helps large networks reduce execution variance at the gate and dock so sites ship more with less drama. | I24: Position YardFlow as a way to eliminate local execution variance at physical fulfillment sites rather than as a traditional yard-management replacement. | J24: 1. How standardized is the driver journey from gate check-in through dock assignment across sites today? 2. Where do trailer queues, dock-office workarounds, or detention pain show up most often in your network? 3. Inside logistics units, where does gate-to-dock inconsistency undermine delivery reliability or sustainability goals? | K24: Our logistics agenda is heavily focused on sustainability and delivery, not yard flow. | L24: Those goals still depend on execution discipline in logistics units. Cleaner gate-to-dock flow supports both service and sustainability. | M24: Book a 15-20 minute MODEX meeting with the exec anchor or a direct report, then lock a follow-up working session with the operator owner inside 7 days. | N24: If they will not commit live, ask for the right operator owner, permission to send the account infographic, and a scheduled post-show working session. | O24: Primo proof + fulfillment-node execution frame | P24: https://www.ikea.com/global/en/our-business/reports/ikea-supply-chain-operations-decarb-catalogue/ | Q24: https://www.ikea.com/global/en/our-business/sustainability/zero-emissions-for-home-deliveries/ | R24: View graphic

Sheet Jake Talk Tracks
A1: Jake Talk Tracks
A2: Use these scripts when a meeting opens, stalls, or needs to convert from polite booth chat into a real discovery call. Tight enough for MODEX. Specific enough to not sound like conference oatmeal.
A4: Account | B4: 20-sec opener | C4: 60-sec narrative | D4: Bridge to Primo proof | E4: What to listen for | F4: If they say "we already have a system" | G4: If they say "not a priority" | H4: If they say "send me something" | I4: Strong close | J4: Meeting owner | K4: Next asset to send | L4: Source URL
A5: Danone | B5: Danone is interesting for us because Danone North America put Heiko Gerling into the COO role in 2025 and is transforming its logistics network, including a Jacksonville RDC milestone and a $65M Jacksonville production-line expansion. We help operators standardize the driver journey from gate check-in to dock release so high-volume sites can move more without adding execution chaos. | C5: The headline for Danone is plant throughput, dock turns, outbound velocity, and headcount-neutral execution. When demand is there, the constraint is usually not production alone. It is the sloppy handoff from gate to dock to release. We are not pitching generic visibility. We are pitching a standardized operating protocol that removes local improvisation at the facility edge. That is where detention, dock-office friction, and lost throughput hide. | D5: Our cleanest proof point is Primo Brands: 24 facilities live, average drop-and-hook time cut from 48 to 24 minutes, and the customer described the result as being able to take on additional volume while remaining headcount neutral in the dock office. Use the Danone infographic to make the analogy concrete. | E5: Signals to chase: mentions of campus congestion, inconsistent site playbooks, too much radio / phone dispatching, detention pain, handoff confusion, peak-season instability, or a desire for more standardization across facilities. | F5: Perfect. YardFlow is not a rip-and-replace pitch. The wedge is standardizing the driver journey and dock handoffs across sites so the process actually behaves the same way under pressure. | G5: That usually means the pain is being absorbed somewhere else. The question I’d ask is whether Heiko Gerling would care if one constrained site could ship more volume without adding people or forcing a larger system replacement. | H5: Happy to. I’ll send the Danone infographic plus a short Primo proof summary. Before I do, who besides Heiko Gerling should be in the next conversation so we aim it at the real operator owner? | I5: Use the Mark Shaughnessy route to secure a 20-minute meeting with Heiko Gerling or his delegate, and tee up a follow-on review with the Jacksonville / network ops team plus a Primo reference. | J5: Primary: Heiko Gerling. Secondary operator: Whitney Klemm. | K5: Danone-specific infographic + Primo proof + offer for Primo customer reference join-in. | L5: https://www.danonenorthamerica.com/about-us/our-leaders.html
A6: General Mills | B6: General Mills is interesting for us because Jonathan Ness was named Chief Supply Chain Officer in March 2026. We help operators standardize the driver journey from gate check-in to dock release so high-volume sites can move more without adding execution chaos. | C6: The headline for General Mills is plant throughput, dock turns, outbound velocity, and headcount-neutral execution. When demand is there, the constraint is usually not production alone. It is the sloppy handoff from gate to dock to release. We are not pitching generic visibility. We are pitching a standardized operating protocol that removes local improvisation at the facility edge. That is where detention, dock-office friction, and lost throughput hide. | D6: Our cleanest proof point is Primo Brands: 24 facilities live, average drop-and-hook time cut from 48 to 24 minutes, and the customer described the result as being able to take on additional volume while remaining headcount neutral in the dock office. Use the General Mills infographic to make the analogy concrete. | E6: Signals to chase: mentions of campus congestion, inconsistent site playbooks, too much radio / phone dispatching, detention pain, handoff confusion, peak-season instability, or a desire for more standardization across facilities. | F6: Fresh leadership is exactly when teams revisit where standardization can unlock service and productivity. This is a low-drama operational wedge, not a transformation moonshot. | G6: That usually means the pain is being absorbed somewhere else. The question I’d ask is whether Jonathan Ness would care if one constrained site could ship more volume without adding people or forcing a larger system replacement. | H6: Happy to. I’ll send the General Mills infographic plus a short Primo proof summary. Before I do, who besides Jonathan Ness should be in the next conversation so we aim it at the real operator owner? | I6: Book a 15-20 minute MODEX meeting with the exec anchor or a direct report, then lock a follow-up working session with the operator owner inside 7 days. | J6: Primary: Jonathan Ness. Secondary operator: Nisar Ahsanullah. | K6: Primo proof + short ROI angle around reduced variance and higher throughput. | L6: https://www.generalmills.com/news/press-releases/general-mills-names-jonathan-ness-chief-supply-chain-officer
A7: Frito-Lay | B7: Frito-Lay is interesting for us because PepsiCo is pushing a One North America agenda and has been testing combined snack-and-beverage warehousing. We help operators standardize the driver journey from gate check-in to dock release so high-volume sites can move more without adding execution chaos. | C7: The headline for Frito-Lay is plant throughput, dock turns, outbound velocity, and headcount-neutral execution. When demand is there, the constraint is usually not production alone. It is the sloppy handoff from gate to dock to release. We are not pitching generic visibility. We are pitching a standardized operating protocol that removes local improvisation at the facility edge. That is where detention, dock-office friction, and lost throughput hide. | D7: Our cleanest proof point is Primo Brands: 24 facilities live, average drop-and-hook time cut from 48 to 24 minutes, and the customer described the result as being able to take on additional volume while remaining headcount neutral in the dock office. Use the Frito-Lay infographic to make the analogy concrete. | E7: Signals to chase: mentions of campus congestion, inconsistent site playbooks, too much radio / phone dispatching, detention pain, handoff confusion, peak-season instability, or a desire for more standardization across facilities. | F7: That’s precisely why variance at the site level matters. The point is not a niche tool; it is a standardized execution layer when network design is changing. | G7: That usually means the pain is being absorbed somewhere else. The question I’d ask is whether Beth Mars would care if one constrained site could ship more volume without adding people or forcing a larger system replacement. | H7: Happy to. I’ll send the Frito-Lay infographic plus a short Primo proof summary. Before I do, who besides Beth Mars should be in the next conversation so we aim it at the real operator owner? | I7: Book a 15-20 minute MODEX meeting with the exec anchor or a direct report, then lock a follow-up working session with the operator owner inside 7 days. | J7: Primary: Beth Mars. Secondary operator: Brian Watson. | K7: Primo proof + variance-tax framing. | L7: https://www.pepsico.com/newsroom/stories/2025/pepsico-announces-organizational-changes-to-accelerate-growth
A8: Diageo | B8: Diageo is interesting for us because Diageo North America announced a new manufacturing and warehousing facility in Alabama to enhance North America supply chain operations. We help operators standardize the driver journey from gate check-in to dock release so high-volume sites can move more without adding execution chaos. | C8: The headline for Diageo is plant throughput, dock turns, outbound velocity, and headcount-neutral execution. When demand is there, the constraint is usually not production alone. It is the sloppy handoff from gate to dock to release. We are not pitching generic visibility. We are pitching a standardized operating protocol that removes local improvisation at the facility edge. That is where detention, dock-office friction, and lost throughput hide. | D8: Our cleanest proof point is Primo Brands: 24 facilities live, average drop-and-hook time cut from 48 to 24 minutes, and the customer described the result as being able to take on additional volume while remaining headcount neutral in the dock office. Use the Diageo infographic to make the analogy concrete. | E8: Signals to chase: mentions of campus congestion, inconsistent site playbooks, too much radio / phone dispatching, detention pain, handoff confusion, peak-season instability, or a desire for more standardization across facilities. | F8: Great. Capital projects raise the stakes on site execution. The closer the business gets to new capacity, the more expensive non-standard yard flow becomes. | G8: That usually means the pain is being absorbed somewhere else. The question I’d ask is whether Raymond Reddrick would care if one constrained site could ship more volume without adding people or forcing a larger system replacement. | H8: Happy to. I’ll send the Diageo infographic plus a short Primo proof summary. Before I do, who besides Raymond Reddrick should be in the next conversation so we aim it at the real operator owner? | I8: Book a 15-20 minute MODEX meeting with the exec anchor or a direct report, then lock a follow-up working session with the operator owner inside 7 days. | J8: Primary: Raymond Reddrick. Secondary operator: Marsha McIntosh-Hamilton. | K8: Primo proof + manufacturing / warehousing site-flow angle. | L8: https://www.diageo.com/en/news-and-media/press-releases/2025/diageo-north-america-announces-new-manufacturing-and-warehousing-facility-in-alabama
A9: Hormel Foods | B9: Hormel Foods is interesting for us because Will Bonifant was appointed group vice president and chief supply chain officer in February 2026. We help operators standardize the driver journey from gate check-in to dock release so high-volume sites can move more without adding execution chaos. | C9: The headline for Hormel Foods is plant throughput, dock turns, outbound velocity, and headcount-neutral execution. When demand is there, the constraint is usually not production alone. It is the sloppy handoff from gate to dock to release. We are not pitching generic visibility. We are pitching a standardized operating protocol that removes local improvisation at the facility edge. That is where detention, dock-office friction, and lost throughput hide. | D9: Our cleanest proof point is Primo Brands: 24 facilities live, average drop-and-hook time cut from 48 to 24 minutes, and the customer described the result as being able to take on additional volume while remaining headcount neutral in the dock office. Use the Hormel Foods infographic to make the analogy concrete. | E9: Signals to chase: mentions of campus congestion, inconsistent site playbooks, too much radio / phone dispatching, detention pain, handoff confusion, peak-season instability, or a desire for more standardization across facilities. | F9: The yard is where planning, production, transportation, and customer service collide in real life. Fixing the handoff is how strategy shows up on the dock. | G9: That usually means the pain is being absorbed somewhere else. The question I’d ask is whether Will Bonifant would care if one constrained site could ship more volume without adding people or forcing a larger system replacement. | H9: Happy to. I’ll send the Hormel Foods infographic plus a short Primo proof summary. Before I do, who besides Will Bonifant should be in the next conversation so we aim it at the real operator owner? | I9: Book a 15-20 minute MODEX meeting with the exec anchor or a direct report, then lock a follow-up working session with the operator owner inside 7 days. | J9: Primary: Will Bonifant. Secondary operator: Nicholas Schwartz. | K9: Primo proof + transformation angle. | L9: https://www.hormelfoods.com/newsroom/press-releases/hormel-foods-names-will-bonifant-group-vice-president-and-chief-supply-chain-officer/
A10: JM Smucker | B10: JM Smucker is interesting for us because Smucker created a new Chief Product Supply Officer role and promoted Rob Ferguson into it in February 2026. We help operators standardize the driver journey from gate check-in to dock release so high-volume sites can move more without adding execution chaos. | C10: The headline for JM Smucker is plant throughput, dock turns, outbound velocity, and headcount-neutral execution. When demand is there, the constraint is usually not production alone. It is the sloppy handoff from gate to dock to release. We are not pitching generic visibility. We are pitching a standardized operating protocol that removes local improvisation at the facility edge. That is where detention, dock-office friction, and lost throughput hide. | D10: Our cleanest proof point is Primo Brands: 24 facilities live, average drop-and-hook time cut from 48 to 24 minutes, and the customer described the result as being able to take on additional volume while remaining headcount neutral in the dock office. Use the JM Smucker infographic to make the analogy concrete. | E10: Signals to chase: mentions of campus congestion, inconsistent site playbooks, too much radio / phone dispatching, detention pain, handoff confusion, peak-season instability, or a desire for more standardization across facilities. | F10: Exactly why this works: it is a contained operational lever that can improve throughput and service without asking the org to swallow a giant program. | G10: That usually means the pain is being absorbed somewhere else. The question I’d ask is whether Rob Ferguson would care if one constrained site could ship more volume without adding people or forcing a larger system replacement. | H10: Happy to. I’ll send the JM Smucker infographic plus a short Primo proof summary. Before I do, who besides Rob Ferguson should be in the next conversation so we aim it at the real operator owner? | I10: Book a 15-20 minute MODEX meeting with the exec anchor or a direct report, then lock a follow-up working session with the operator owner inside 7 days. | J10: Primary: Rob Ferguson. Secondary operator: Anbu Kuppusamy. | K10: Primo proof + variance-tax framing. | L10: https://investors.jmsmucker.com/news/news-details/2026/The-J-M--Smucker-Co--Announces-Senior-Leadership-Updates-to-Drive-Continued-Growth-and-Execution/default.aspx
A11: The Home Depot | B11: The Home Depot is interesting for us because Richard McPhail is a MODEX 2026 keynote. Home Depot also has a visible public supply-chain bench including Amit Kalra and John Drake. We help operators standardize the driver journey from gate check-in to dock release so high-volume sites can move more without adding execution chaos. | C11: The headline for The Home Depot is campus flow, appointment discipline, trailer visibility, and consistent dock prioritization. Retail networks pay a variance tax when stores and DCs move on different operating rhythms. We are not pitching generic visibility. We are pitching a standardized operating protocol that removes local improvisation at the facility edge. That is where detention, dock-office friction, and lost throughput hide. | D11: Our cleanest proof point is Primo Brands: 24 facilities live, average drop-and-hook time cut from 48 to 24 minutes, and the customer described the result as being able to take on additional volume while remaining headcount neutral in the dock office. Use the The Home Depot infographic to make the analogy concrete. | E11: Signals to chase: mentions of campus congestion, inconsistent site playbooks, too much radio / phone dispatching, detention pain, handoff confusion, peak-season instability, or a desire for more standardization across facilities. | F11: No argument. The pitch is not sophistication, it is site consistency. Even elite networks leak performance when every yard and dock team improvises under pressure. | G11: That usually means the pain is being absorbed somewhere else. The question I’d ask is whether John Deaton would care if one constrained site could ship more volume without adding people or forcing a larger system replacement. | H11: Happy to. I’ll send the The Home Depot infographic plus a short Primo proof summary. Before I do, who besides John Deaton should be in the next conversation so we aim it at the real operator owner? | I11: Book a MODEX floor-side meeting with the named leader or chief of staff and leave with one owner for a post-show operational deep dive. | J11: Primary: John Deaton. Secondary operator: Amit Kalra. | K11: Primo proof + one-pager focused on standardization, traffic flow, and execution consistency. | L11: https://corporate.homedepot.com/page/home-depot-leadership-0?page=1
A12: Georgia Pacific | B12: Georgia Pacific is interesting for us because Georgia-Pacific is expanding Palatka with an $83M project including a 36-acre trailer yard, 574-trailer capacity, an inspection station, and warehouse expansion. We help operators standardize the driver journey from gate check-in to dock release so high-volume sites can move more without adding execution chaos. | C12: The headline for Georgia Pacific is trailer-yard utilization, dock coordination, and standardized site execution. Industrial networks can have world-class production and still leak margin through non-standard site flow. We are not pitching generic visibility. We are pitching a standardized operating protocol that removes local improvisation at the facility edge. That is where detention, dock-office friction, and lost throughput hide. | D12: Our cleanest proof point is Primo Brands: 24 facilities live, average drop-and-hook time cut from 48 to 24 minutes, and the customer described the result as being able to take on additional volume while remaining headcount neutral in the dock office. Use the Georgia Pacific infographic to make the analogy concrete. | E12: Signals to chase: mentions of campus congestion, inconsistent site playbooks, too much radio / phone dispatching, detention pain, handoff confusion, peak-season instability, or a desire for more standardization across facilities. | F12: It solves capacity. It does not guarantee disciplined flow, dock direction, or timestamped accountability once more trailers arrive. | G12: That usually means the pain is being absorbed somewhere else. The question I’d ask is whether Jeremy Finley would care if one constrained site could ship more volume without adding people or forcing a larger system replacement. | H12: Happy to. I’ll send the Georgia Pacific infographic plus a short Primo proof summary. Before I do, who besides Jeremy Finley should be in the next conversation so we aim it at the real operator owner? | I12: Book a 15-20 minute MODEX meeting with the exec anchor or a direct report, then lock a follow-up working session with the operator owner inside 7 days. | J12: Primary: Jeremy Finley. Secondary operator: Ryan Hutcherson. | K12: Primo proof + operator-first demo angle. | L12: https://www.prnewswire.com/news-releases/georgia-pacific-announces-83-million-expansion-project-at-palatka-florida-facility-302150221.html
A13: H-E-B | B13: H-E-B is interesting for us because H-E-B bought 600+ acres in North Texas for a master-planned supply-chain campus and is expanding logistics capacity for continued DFW growth. We help operators standardize the driver journey from gate check-in to dock release so high-volume sites can move more without adding execution chaos. | C13: The headline for H-E-B is campus flow, appointment discipline, trailer visibility, and consistent dock prioritization. Retail networks pay a variance tax when stores and DCs move on different operating rhythms. We are not pitching generic visibility. We are pitching a standardized operating protocol that removes local improvisation at the facility edge. That is where detention, dock-office friction, and lost throughput hide. | D13: Our cleanest proof point is Primo Brands: 24 facilities live, average drop-and-hook time cut from 48 to 24 minutes, and the customer described the result as being able to take on additional volume while remaining headcount neutral in the dock office. Use the H-E-B infographic to make the analogy concrete. | E13: Signals to chase: mentions of campus congestion, inconsistent site playbooks, too much radio / phone dispatching, detention pain, handoff confusion, peak-season instability, or a desire for more standardization across facilities. | F13: That’s why now matters. The cheapest moment to standardize operating protocol is before the new campus muscle memory hardens. | G13: That usually means the pain is being absorbed somewhere else. The question I’d ask is whether Dakota Socha would care if one constrained site could ship more volume without adding people or forcing a larger system replacement. | H13: Happy to. I’ll send the H-E-B infographic plus a short Primo proof summary. Before I do, who besides Dakota Socha should be in the next conversation so we aim it at the real operator owner? | I13: Book a 15-20 minute MODEX meeting with the exec anchor or a direct report, then lock a follow-up working session with the operator owner inside 7 days. | J13: Primary: Dakota Socha. Secondary operator: Craig Stucker. | K13: Primo proof + retail distribution growth angle. | L13: https://newsroom.heb.com/h-e-b-buys-land-to-develop-a-master-planned-supply-chain-campus-in-north-texas/
A14: Hyundai Motor America | B14: Hyundai Motor America is interesting for us because Automotive distribution and finished-vehicle logistics complexity plus official past-attendee signal. We help operators standardize the driver journey from gate check-in to dock release so high-volume sites can move more without adding execution chaos. | C14: The headline for Hyundai Motor America is campus orchestration, trailer staging discipline, and tighter handoffs between manufacturing and shipping. Large industrial campuses lose time in the yards long before anyone calls it a yard problem. We are not pitching generic visibility. We are pitching a standardized operating protocol that removes local improvisation at the facility edge. That is where detention, dock-office friction, and lost throughput hide. | D14: Our cleanest proof point is Primo Brands: 24 facilities live, average drop-and-hook time cut from 48 to 24 minutes, and the customer described the result as being able to take on additional volume while remaining headcount neutral in the dock office. Use the Hyundai Motor America infographic to make the analogy concrete. | E14: Signals to chase: mentions of campus congestion, inconsistent site playbooks, too much radio / phone dispatching, detention pain, handoff confusion, peak-season instability, or a desire for more standardization across facilities. | F14: Agreed, but the pattern is the same: standardized routing, staging, and release discipline reduce avoidable friction on complex campuses. | G14: That usually means the pain is being absorbed somewhere else. The question I’d ask is whether Carey Gammon would care if one constrained site could ship more volume without adding people or forcing a larger system replacement. | H14: Happy to. I’ll send the Hyundai Motor America infographic plus a short Primo proof summary. Before I do, who besides Carey Gammon should be in the next conversation so we aim it at the real operator owner? | I14: Book a 15-20 minute MODEX meeting with the exec anchor or a direct report, then lock a follow-up working session with the operator owner inside 7 days. | J14: Primary: Carey Gammon. Secondary operator: Yongchul Chung. | K14: Primo proof + automotive analog frame | L14: https://www.hyundainews.com/releases/761
A15: Honda | B15: Honda is interesting for us because Large manufacturing campuses and logistics complexity make yard execution a lever. We help operators standardize the driver journey from gate check-in to dock release so high-volume sites can move more without adding execution chaos. | C15: The headline for Honda is campus orchestration, trailer staging discipline, and tighter handoffs between manufacturing and shipping. Large industrial campuses lose time in the yards long before anyone calls it a yard problem. We are not pitching generic visibility. We are pitching a standardized operating protocol that removes local improvisation at the facility edge. That is where detention, dock-office friction, and lost throughput hide. | D15: Our cleanest proof point is Primo Brands: 24 facilities live, average drop-and-hook time cut from 48 to 24 minutes, and the customer described the result as being able to take on additional volume while remaining headcount neutral in the dock office. Use the Honda infographic to make the analogy concrete. | E15: Signals to chase: mentions of campus congestion, inconsistent site playbooks, too much radio / phone dispatching, detention pain, handoff confusion, peak-season instability, or a desire for more standardization across facilities. | F15: Downstream is where revenue leaves the site. If outbound flow stumbles, manufacturing wins do not fully turn into shipped volume. | G15: That usually means the pain is being absorbed somewhere else. The question I’d ask is whether Jim Small would care if one constrained site could ship more volume without adding people or forcing a larger system replacement. | H15: Happy to. I’ll send the Honda infographic plus a short Primo proof summary. Before I do, who besides Jim Small should be in the next conversation so we aim it at the real operator owner? | I15: Book a 15-20 minute MODEX meeting with the exec anchor or a direct report, then lock a follow-up working session with the operator owner inside 7 days. | J15: Primary: Jim Small. Secondary operator: Nicole Miller. | K15: Primo proof + plant throughput frame | L15: https://hondanews.com/pages/executives
... A24: IKEA | B24: IKEA is interesting for us because IKEA U.S. continues expanding smaller-format locations and has publicly highlighted logistics units and growing zero-emission delivery operations, while Henrik Elm oversees supply and operations across the total IKEA value chain. We help operators standardize the driver journey from gate check-in to dock release so high-volume sites can move more without adding execution chaos. | C24: The headline for IKEA is campus flow, appointment discipline, trailer visibility, and consistent dock prioritization. Retail networks pay a variance tax when stores and DCs move on different operating rhythms. We are not pitching generic visibility. We are pitching a standardized operating protocol that removes local improvisation at the facility edge. That is where detention, dock-office friction, and lost throughput hide. | D24: Our cleanest proof point is Primo Brands: 24 facilities live, average drop-and-hook time cut from 48 to 24 minutes, and the customer described the result as being able to take on additional volume while remaining headcount neutral in the dock office. Use the IKEA infographic to make the analogy concrete. | E24: Signals to chase: mentions of campus congestion, inconsistent site playbooks, too much radio / phone dispatching, detention pain, handoff confusion, peak-season instability, or a desire for more standardization across facilities. | F24: Those goals still depend on execution discipline in logistics units. Cleaner gate-to-dock flow supports both service and sustainability. | G24: That usually means the pain is being absorbed somewhere else. The question I’d ask is whether Rob Olson would care if one constrained site could ship more volume without adding people or forcing a larger system replacement. | H24: Happy to. I’ll send the IKEA infographic plus a short Primo proof summary. Before I do, who besides Rob Olson should be in the next conversation so we aim it at the real operator owner? | I24: Book a 15-20 minute MODEX meeting with the exec anchor or a direct report, then lock a follow-up working session with the operator owner inside 7 days. | J24: Primary: Rob Olson. Secondary operator: Pam Andrews. | K24: Primo proof + fulfillment-node execution frame | L24: https://www.ikea.com/global/en/our-business/reports/ikea-supply-chain-operations-decarb-catalogue/

Sheet Objection Map
A1: Objection Map
A2: Fast counters by objection type. Use when a booth chat gets slippery or someone tries to kill the convo with a lazy one-liner.
A4: Objection type | B4: What they are really saying | C4: Counter move | D4: Proof point to use | E4: Best follow-up question | F4: Best asset | G4: Use on accounts | H4: Notes
A5: We already have a YMS / TMS / scheduling system | B5: They think you are pitching a rip-and-replace tool or a commodity layer. | C5: Clarify that YardFlow’s wedge is standardizing the execution protocol and driver journey, not just adding more software screens. | D5: Primo drop-and-hook improvement and headcount-neutral execution. | E5: How consistent is the process across sites when volume spikes? | F5: Account infographic + Primo proof sheet | G5: Most accounts, especially Danone, Home Depot, H-E-B, Dollar Tree | H5: Do not argue systems architecture first. Reframe to variance and execution.
A6: Not a priority right now | B6: They do not yet feel the cost of the problem or have not attached it to a current trigger. | C6: Tie back to the trigger event: new leader, new facility, network redesign, or campus expansion. | D6: Account-specific why-now from the dossier. | E6: What has to happen operationally before this becomes urgent? | F6: Account dossier + talk track | G6: General Mills, Hormel, Smucker, H-E-B, Diageo | H6: Use their own public change event against inertia.
A7: Send me something | B7: They want an exit, or they are willing to continue if the next step is light. | C7: Agree, but trade the asset for routing intel and a scheduled follow-up. | D7: Primo + account-specific infographic. | E7: Who should own the next conversation internally? | F7: Infographic + 1-page proof summary | G7: All accounts | H7: Never send blind with no next step.
A8: This feels too tactical | B8: They think yard flow is beneath enterprise strategy. | C8: Reframe as the execution layer where planning, transportation, customer service, and manufacturing actually converge. | D8: Variance tax framing and headcount-neutral throughput story. | E8: Where do those functions currently break down at the site edge? | F8: Battlecard + infographic | G8: Food & beverage, retail, manufacturing | H8: Make the facility edge sound boardroom-relevant.
A9: We are too complex / too big | B9: They assume complexity makes standardization unrealistic. | C9: Argue the opposite: bigger networks pay a bigger variance tax when local improvisation is tolerated. | D9: Primo multi-site proof. | E9: Which sites operate differently today and what does that inconsistency cost you? | F9: Primo proof + account infographic | G9: Frito-Lay, Home Depot, FedEx, Dollar General, IKEA | H9: Scale is the reason to care, not an excuse to ignore it.

Sheet MODEX Close Plan
A1: MODEX Close Plan
A2: What Jake should try to leave every meeting with. Because "great chatting at the booth" is not a pipeline stage.
A4: Account | B4: Best first win | C4: Ask for this in the meeting | D4: Fallback if they resist | E4: Who to pull in next | F4: Asset to send same day | G4: Target timing | H4: Owner | I4: Status
A5: Danone | B5: Named operator-level follow-up within 7 days | C5: Use the Mark Shaughnessy route to secure a 20-minute meeting with Heiko Gerling or his delegate, and tee up a follow-on review with the Jacksonville / network ops team plus a Primo reference. | D5: Get explicit routing: name, title, and email of the operator owner. Then secure permission to send the infographic and Primo proof the same day. | E5: Whitney Klemm | F5: Danone-specific infographic + Primo proof + offer for Primo customer reference join-in. | G5: During MODEX or within 7 days after show | H5: Jake | I5: Open
A6: General Mills | B6: Named operator-level follow-up within 7 days | C6: Book a 15-20 minute MODEX meeting with the exec anchor or a direct report, then lock a follow-up working session with the operator owner inside 7 days. | D6: Get explicit routing: name, title, and email of the operator owner. Then secure permission to send the infographic and Primo proof the same day. | E6: Nisar Ahsanullah | F6: Primo proof + short ROI angle around reduced variance and higher throughput. | G6: During MODEX or within 7 days after show | H6: Jake | I6: Open
A7: Frito-Lay | B7: Named operator-level follow-up within 7 days | C7: Book a 15-20 minute MODEX meeting with the exec anchor or a direct report, then lock a follow-up working session with the operator owner inside 7 days. | D7: Get explicit routing: name, title, and email of the operator owner. Then secure permission to send the infographic and Primo proof the same day. | E7: Brian Watson | F7: Primo proof + variance-tax framing. | G7: During MODEX or within 7 days after show | H7: Jake | I7: Open
A8: Diageo | B8: Named operator-level follow-up within 7 days | C8: Book a 15-20 minute MODEX meeting with the exec anchor or a direct report, then lock a follow-up working session with the operator owner inside 7 days. | D8: Get explicit routing: name, title, and email of the operator owner. Then secure permission to send the infographic and Primo proof the same day. | E8: Marsha McIntosh-Hamilton | F8: Primo proof + manufacturing / warehousing site-flow angle. | G8: During MODEX or within 7 days after show | H8: Jake | I8: Open
A9: Hormel Foods | B9: Named operator-level follow-up within 7 days | C9: Book a 15-20 minute MODEX meeting with the exec anchor or a direct report, then lock a follow-up working session with the operator owner inside 7 days. | D9: Get explicit routing: name, title, and email of the operator owner. Then secure permission to send the infographic and Primo proof the same day. | E9: Nicholas Schwartz | F9: Primo proof + transformation angle. | G9: During MODEX or within 7 days after show | H9: Jake | I9: Open
A10: JM Smucker | B10: Named operator-level follow-up within 7 days | C10: Book a 15-20 minute MODEX meeting with the exec anchor or a direct report, then lock a follow-up working session with the operator owner inside 7 days. | D10: Get explicit routing: name, title, and email of the operator owner. Then secure permission to send the infographic and Primo proof the same day. | E10: Anbu Kuppusamy | F10: Primo proof + variance-tax framing. | G10: During MODEX or within 7 days after show | H10: Jake | I10: Open
A11: The Home Depot | B11: Named operator-level follow-up within 7 days | C11: Book a MODEX floor-side meeting with the named leader or chief of staff and leave with one owner for a post-show operational deep dive. | D11: Get explicit routing: name, title, and email of the operator owner. Then secure permission to send the infographic and Primo proof the same day. | E11: Amit Kalra | F11: Primo proof + one-pager focused on standardization, traffic flow, and execution consistency. | G11: During MODEX or within 7 days after show | H11: Jake | I11: Open
A12: Georgia Pacific | B12: Named operator-level follow-up within 7 days | C12: Book a 15-20 minute MODEX meeting with the exec anchor or a direct report, then lock a follow-up working session with the operator owner inside 7 days. | D12: Get explicit routing: name, title, and email of the operator owner. Then secure permission to send the infographic and Primo proof the same day. | E12: Ryan Hutcherson | F12: Primo proof + operator-first demo angle. | G12: During MODEX or within 7 days after show | H12: Jake | I12: Open
A13: H-E-B | B13: Named operator-level follow-up within 7 days | C13: Book a 15-20 minute MODEX meeting with the exec anchor or a direct report, then lock a follow-up working session with the operator owner inside 7 days. | D13: Get explicit routing: name, title, and email of the operator owner. Then secure permission to send the infographic and Primo proof the same day. | E13: Craig Stucker | F13: Primo proof + retail distribution growth angle. | G13: During MODEX or within 7 days after show | H13: Jake | I13: Open
A14: Hyundai Motor America | B14: Named operator-level follow-up within 7 days | C14: Book a 15-20 minute MODEX meeting with the exec anchor or a direct report, then lock a follow-up working session with the operator owner inside 7 days. | D14: Get explicit routing: name, title, and email of the operator owner. Then secure permission to send the infographic and Primo proof the same day. | E14: Yongchul Chung | F14: Primo proof + automotive analog frame | G14: During MODEX or within 7 days after show | H14: Jake | I14: Open
A15: Honda | B15: Named operator-level follow-up within 7 days | C15: Book a 15-20 minute MODEX meeting with the exec anchor or a direct report, then lock a follow-up working session with the operator owner inside 7 days. | D15: Get explicit routing: name, title, and email of the operator owner. Then secure permission to send the infographic and Primo proof the same day. | E15: Nicole Miller | F15: Primo proof + plant throughput frame | G15: During MODEX or within 7 days after show | H15: Jake | I15: Open
... A24: IKEA | B24: Named operator-level follow-up within 7 days | C24: Book a 15-20 minute MODEX meeting with the exec anchor or a direct report, then lock a follow-up working session with the operator owner inside 7 days. | D24: Get explicit routing: name, title, and email of the operator owner. Then secure permission to send the infographic and Primo proof the same day. | E24: Pam Andrews | F24: Primo proof + fulfillment-node execution frame | G24: During MODEX or within 7 days after show | H24: Jake | I24: Open

Sheet Graphic Assets
A1: Top 20 custom YardFlow infographic assets
A2: Each image repurposes the Danone-style proof asset into an account-specific hypothesis for MODEX. Use this tab as the asset register and use the Gallery tab to browse the actual graphics.
A4: Rank | B4: Account | C4: Hypothesis headline | D4: Primary use-case hypothesis | E4: Best exec anchor | F4: Best operator anchor | G4: Image file | H4: Public source context
A5: 1 | B5: Danone | C5: WHEN DEMAND SPIKES, OUTBOUND FLOW BECOMES THE CONSTRAINT | D5: Danone's North American network is expanding. YardFlow standardizes gate-to-dock execution so plants and DCs move more product without adding dock-office chaos. | E5: Heiko Gerling | Chief Operations Officer, North America | F5: Whitney Klemm | Supply Chain Leader | G5: Danone.png | H5: Danone North America put Heiko Gerling into the COO role in 2025 and is transforming its logistics network, including a Jacksonville RDC milestone and a $65M Jacksonville production-line expansion.
A6: 2 | B6: General Mills | C6: NEW SUPPLY CHAIN LEADERSHIP CREATES A WINDOW TO CUT VARIANCE | D6: With a new CSCO in place, the opportunity is to reduce site-to-site execution drift. YardFlow makes yard and dock flow consistent across plants and DCs. | E6: Jonathan Ness | Chief Supply Chain Officer | F6: Nisar Ahsanullah | General Mills supply chain leader | G6: General_Mills.png | H6: Jonathan Ness was named Chief Supply Chain Officer in March 2026.
A7: 3 | B7: Frito-Lay | C7: IN A HIGH-VELOCITY SNACK NETWORK, SMALL DELAYS STACK FAST | D7: Frito-Lay wins on speed and consistency. YardFlow reduces gate friction, dispatch lag, and dock confusion so trailer flow stays tight under peak volume. | E7: Beth Mars | Transportation Director | F7: Brian Watson | Vice President of Supply Chain | G7: Frito_Lay.png | H7: PepsiCo is pushing a One North America agenda and has been testing combined snack-and-beverage warehousing.
A8: 4 | B8: Diageo | C8: NEW CAPACITY ONLY PAYS OFF IF THE YARD CAN FEED THE DOCK | D8: As Diageo scales new manufacturing and warehousing capacity, YardFlow standardizes campus execution so physical expansion translates into clean throughput. | E8: Raymond Reddrick | SVP North America Supply - Manufacturing and Distillation | F8: Marsha McIntosh-Hamilton | President of North America Supply | G8: Diageo.png | H8: Diageo North America announced a new manufacturing and warehousing facility in Alabama to enhance North America supply chain operations.
A9: 5 | B9: Hormel Foods | C9: FRESH SUPPLY CHAIN LEADERSHIP IS THE MOMENT TO STANDARDIZE EXECUTION | D9: Hormel's new CSCO inherits a broad network. YardFlow turns yard and dock operations into a standard operating layer instead of a site-by-site improvisation. | E9: Will Bonifant | Group Vice President and Chief Supply Chain Officer | F9: Nicholas Schwartz | Supply Chain Planning COE & Strategy Lead | G9: Hormel_Foods.png | H9: Will Bonifant was appointed group vice president and chief supply chain officer in February 2026.
A10: 6 | B10: JM Smucker | C10: MULTI-CATEGORY NETWORKS BREAK DOWN WHEN EACH SITE RUNS ITS OWN PLAYBOOK | D10: Smucker's new product-supply structure is a chance to standardize ground-level execution. YardFlow reduces network variance at the gate, in the yard, and at the dock. | E10: Rob Ferguson | Chief Product Supply Officer | Executive Vice President, Coffee, Pet, and Away From Home | F10: Anbu Kuppusamy | Transportation Function Leader | G10: JM_Smucker.png | H10: Smucker created a new Chief Product Supply Officer role and promoted Rob Ferguson into it in February 2026.
A11: 7 | B11: The Home Depot | C11: FAST DELIVERY NETWORKS STILL LIVE OR DIE AT THE YARD AND DOCK | D11: Home Depot has built the network. YardFlow helps individual nodes run a tighter arrival, staging, and docking protocol so asset speed is not lost on the ground. | E11: John Deaton | Executive Vice President – Supply Chain & Product Development | F11: Amit Kalra | Senior Vice President – Supply Chain | G11: The_Home_Depot.png | H11: Richard McPhail is a MODEX 2026 keynote. Home Depot also has a visible public supply-chain bench including Amit Kalra and John Drake.
A12: 8 | B12: Georgia Pacific | C12: MILL AND WAREHOUSE THROUGHPUT LEAKS WHEN TRAILER FLOW ISN'T ORCHESTRATED | D12: Georgia-Pacific's mixed-load and mill logistics environment rewards disciplined execution. YardFlow creates a standard gate-to-release operating protocol. | E12: Jeremy Finley | Vice President, Supply Chain | F12: Ryan Hutcherson | Senior Vice President, Supply Chain | G12: Georgia_Pacific.png | H12: Georgia-Pacific is expanding Palatka with an $83M project including a 36-acre trailer yard, 574-trailer capacity, an inspection station, and warehouse expansion.
A13: 9 | B13: H-E-B | C13: GROCERY NETWORKS NEED TIGHT TRAILER FLOW, NOT YARD DRAMA | D13: For a high-service grocery network, yard variance is a hidden freshness and availability tax. YardFlow standardizes check-in, routing, and dock handoffs across DC campuses. | E13: Dakota Socha | Transportation & Reverse Logistics | F13: Craig Stucker | Director, Parkway Transport at H-E-B | G13: H_E_B.png | H13: H-E-B bought 600+ acres in North Texas for a master-planned supply-chain campus and is expanding logistics capacity for continued DFW growth.
A14: 10 | B14: Hyundai Motor America | C14: SEQUENCED MANUFACTURING SUFFERS WHEN YARD EXECUTION IS LOOSE | D14: Automotive networks cannot afford trailer ambiguity. YardFlow brings timestamped control to check-in, routing, staging, and dock release around plant operations. | E14: Carey Gammon | Director, Vehicle Operations (HMA) | F14: Yongchul Chung | Senior Manager, Global Logistics & Supply Chain | G14: Hyundai_Motor_America.png | H14: Automotive distribution and finished-vehicle logistics complexity plus official past-attendee signal.
A15: 11 | B15: Honda | C15: PLANT FLOW BREAKS WHEN CHECK-IN, STAGING, AND DOCK MOVES AREN'T STANDARD | D15: Honda's manufacturing rhythm depends on disciplined logistics. YardFlow creates a repeatable arrival-to-release protocol that supports plant continuity. | E15: Jim Small | Executive Vice President, Manufacturing | F15: Nicole Miller | Logistics leader | G15: Honda.png | H15: Large manufacturing campuses and logistics complexity make yard execution a lever.
A16: 12 | B16: John Deere | C16: PARTS AND EQUIPMENT NETWORKS NEED CLEAN CAMPUS EXECUTION | D16: John Deere's network relies on dependable flow across plants and distribution points. YardFlow standardizes yard execution so service and throughput are not left to local habit. | E16: Cory Reed | President, Worldwide Agriculture & Turf, Production & Precision Ag, Customer Success | F16: Steve Wilhelmi | Vice President, Logistics | G16: John_Deere.png | H16: Industrial campus complexity and dealer/service expectations make execution discipline relevant.
... A24: 20 | B24: IKEA | C24: BULKY PRODUCT FLOWS BREAK DOWN WHEN CAMPUS MOVES AREN'T COORDINATED | D24: IKEA's large-format distribution model depends on disciplined physical flow. YardFlow standardizes yard and dock movements so high-cube freight moves cleanly through the node. | E24: Rob Olson | Chief Operating Officer, IKEA U.S. | F24: Pam Andrews | Vice President of Logistics | G24: IKEA.png | H24: IKEA U.S. continues expanding smaller-format locations and has publicly highlighted logistics units and growing zero-emission delivery operations, while Henrik Elm oversees supply and operations across the total IKEA value chain.

Sheet Jake Daily Brief
A1: Jake Daily Brief
A2: Use this at the hotel or before doors open. It is the smallest possible command view for today’s priorities, hot signals, and follow-up commitments.
A4: Target accounts | C4: Named personas | E4: Live captures logged | G4: HOT captures | I4: Due follow-ups | K4: Warm intro accounts
A5: =COUNTA(Accounts!$B$2:$B$21) -> 20 | C5: =COUNTA(Personas!$D$2:$D$226) -> 100 | E5: =COUNTIF('Live Capture'!$E$6:$E$125,"<>") -> 120 | G5: =COUNTIF('Live Capture'!$W$6:$W$125,"HOT") -> 1 | I5: =COUNTIF('Follow-Up Engine'!$L$6:$L$25,"Due today") -> 0 | K5: 1
A8: Today’s must-win actions
A9: Action | B9: Owner | C9: Trigger | D9: Account | E9: Asset / proof | F9: Done?
A10: Package Danone intro through Mark | B10: Casey | C10: Warm intro live | D10: Danone | E10: Danone infographic + concise ask | F10: No
A11: Work booked meetings first, then HOT walk-ups | B11: Jake | C11: Show-floor operating rule | D11: Top 20 | E11: Leave-behinds + battlecards | F11: No
A12: Send same-day recaps before dinner | B12: Casey | C12: Any real conversation | D12: All meeting accounts | E12: Follow-Up Templates | F12: No
A14: Mobile form live? Use the Google Form between meetings for fastest logging. Use Mobile Capture Lite only as backup.
A15: Fallback targets if meetings move
A16: Account | B16: Named persona | C16: Why now | D16: Use this asset | E16: Notes | F16: Status
A17: The Home Depot | B17: Amit Kalra / John Drake | C17: Official keynote + supply-chain leadership | D17: Home Depot leave-behind | E17: Strong public MODEX signal | F17: Queued
A18: General Mills | B18: Jonathan Ness | C18: Fresh CSCO appointment | D18: General Mills leave-behind | E18: Good why-now angle | F18: Queued
A19: Hormel Foods | B19: Will Bonifant | C19: Fresh CSCO appointment | D19: Hormel leave-behind | E19: Good proof transfer from Primo | F19: Queued

Sheet Infographic Gallery
A1: Infographic Gallery
A2: These are custom account-specific YardFlow infographics stored in the workbook for quick share, export, or screenshot. Each one is a meeting hypothesis, not a claim of live deployment at that account.
A22: 1. Danone — WHEN DEMAND SPIKES, OUTBOUND FLOW BECOMES THE CONSTRAINT | F22: 2. General Mills — NEW SUPPLY CHAIN LEADERSHIP CREATES A WINDOW TO CUT VARIANCE
A23: Danone's North American network is expanding. YardFlow standardizes gate-to-dock execution so plants and DCs move more product without adding dock-office chaos. | F23: With a new CSCO in place, the opportunity is to reduce site-to-site execution drift. YardFlow makes yard and dock flow consistent across plants and DCs.
A25: Exec anchor: Heiko Gerling | Chief Operations Officer, North America | Operator anchor: Whitney Klemm | Supply Chain Leader | F25: Exec anchor: Jonathan Ness | Chief Supply Chain Officer | Operator anchor: Nisar Ahsanullah | General Mills supply chain leader
A44: 3. Frito-Lay — IN A HIGH-VELOCITY SNACK NETWORK, SMALL DELAYS STACK FAST | F44: 4. Diageo — NEW CAPACITY ONLY PAYS OFF IF THE YARD CAN FEED THE DOCK
A45: Frito-Lay wins on speed and consistency. YardFlow reduces gate friction, dispatch lag, and dock confusion so trailer flow stays tight under peak volume. | F45: As Diageo scales new manufacturing and warehousing capacity, YardFlow standardizes campus execution so physical expansion translates into clean throughput.
A47: Exec anchor: Beth Mars | Transportation Director | Operator anchor: Brian Watson | Vice President of Supply Chain | F47: Exec anchor: Raymond Reddrick | SVP North America Supply - Manufacturing and Distillation | Operator anchor: Marsha McIntosh-Hamilton | President of North America Supply
A66: 5. Hormel Foods — FRESH SUPPLY CHAIN LEADERSHIP IS THE MOMENT TO STANDARDIZE EXECUTION | F66: 6. JM Smucker — MULTI-CATEGORY NETWORKS BREAK DOWN WHEN EACH SITE RUNS ITS OWN PLAYBOOK
A67: Hormel's new CSCO inherits a broad network. YardFlow turns yard and dock operations into a standard operating layer instead of a site-by-site improvisation. | F67: Smucker's new product-supply structure is a chance to standardize ground-level execution. YardFlow reduces network variance at the gate, in the yard, and at the dock.
A69: Exec anchor: Will Bonifant | Group Vice President and Chief Supply Chain Officer | Operator anchor: Nicholas Schwartz | Supply Chain Planning COE & Strategy Lead | F69: Exec anchor: Rob Ferguson | Chief Product Supply Officer | Executive Vice President, Coffee, Pet, and Away From Home | Operator anchor: Anbu Kuppusamy | Transportation Function Leader
A88: 7. The Home Depot — FAST DELIVERY NETWORKS STILL LIVE OR DIE AT THE YARD AND DOCK | F88: 8. Georgia Pacific — MILL AND WAREHOUSE THROUGHPUT LEAKS WHEN TRAILER FLOW ISN'T ORCHESTRATED
A89: Home Depot has built the network. YardFlow helps individual nodes run a tighter arrival, staging, and docking protocol so asset speed is not lost on the ground. | F89: Georgia-Pacific's mixed-load and mill logistics environment rewards disciplined execution. YardFlow creates a standard gate-to-release operating protocol.
A91: Exec anchor: John Deaton | Executive Vice President – Supply Chain & Product Development | Operator anchor: Amit Kalra | Senior Vice President – Supply Chain | F91: Exec anchor: Jeremy Finley | Vice President, Supply Chain | Operator anchor: Ryan Hutcherson | Senior Vice President, Supply Chain
... A223: Exec anchor: Roxanne Weng | Chief Supply Chain Officer | Operator anchor: Adam Janatsch | VP Distribution Operations | F223: Exec anchor: Rob Olson | Chief Operating Officer, IKEA U.S. | Operator anchor: Pam Andrews | Vice President of Logistics

Sheet Control Tower
A1: MODEX Campaign Control Tower
A2: Last rebuilt: 2026-03-25 | Purpose: no-scroll operating view for Jake’s MODEX hunt. Expanded to top 20 + outreach packs.
A4: Target Accounts | D4: Top 20 Board | G4: Named Personas | J4: Jake Queue | L4: Open here:
A5: =COUNTA(Accounts!$B$2:$B$21) -> 20 | D5: =COUNTA('Top 20 Board'!$B$2:$B$21) -> 20 | G5: =COUNTA(Personas!$D$2:$D$226) -> 100 | J5: Use Jake Queue | L5: MODEX Command Sheet
A6: P1 Personas | D6: Warm Intro Accounts | G6: Named Speaker / Keynote Accounts | J6: Apps Script | L6: Then:
A7: =COUNTIF(Personas!$C$2:$C$226,"P1") -> 43 | D7: 1 | G7: 3 | J7: See Apps Script Install | L7: Follow-Up Engine
J8: QR Journey | L8: QR Assets
A9: Rank | B9: Account | C9: Exec Anchor | D9: Operator Anchor | E9: Why now | F9: Primo wedge | G9: Best intro path | H9: Next action | I9: Priority band | J9: Use for live scan display | L9: Use for account-specific QR links
A10: {=IFERROR(INDEX(Accounts!$A:$A,MATCH(B10,Accounts!$B:$B,0)),"")} -> 1 | B10: Danone | C10: Heiko Gerling | Chief Operations Officer, North America | D10: Whitney Klemm | Supply Chain Leader | E10: {=IFERROR(INDEX('Meeting Briefs'!$E:$E,MATCH(B10,'Meeting Briefs'!$A:$A,0)),"")} -> Active Shaughnessy intro path and likely MODEX attendance signal. | F10: {=IFERROR(INDEX('Meeting Briefs'!$G:$G,MATCH(B10,'Meeting Briefs'!$A:$A,0)),"")} -> Primo proof should land hardest here because both are high-volume food / beverage-style networks with plant throughput pressure. | G10: Form Intake | H10: Prep Mark Shaughnessy intro path | J10: Mobile Capture
A11: {=IFERROR(INDEX(Accounts!$A:$A,MATCH(B11,Accounts!$B:$B,0)),"")} -> 2 | B11: General Mills | C11: Jonathan Ness | Chief Supply Chain Officer | D11: Nisar Ahsanullah | General Mills supply chain leader | E11: {=IFERROR(INDEX('Meeting Briefs'!$E:$E,MATCH(B11,'Meeting Briefs'!$A:$A,0)),"")} -> New CSCO in March 2026. | F11: {=IFERROR(INDEX('Meeting Briefs'!$G:$G,MATCH(B11,'Meeting Briefs'!$A:$A,0)),"")} -> Fresh supply chain leadership creates a window to discuss standardization and throughput across plants and DCs. | G11: Use Form Intake Control | H11: Identify target persona(s) | J11: Use Google Form or Mobile Capture Lite
A12: {=IFERROR(INDEX(Accounts!$A:$A,MATCH(B12,Accounts!$B:$B,0)),"")} -> 2 | B12: Frito-Lay | C12: Beth Mars | Transportation Director | D12: Brian Watson | Vice President of Supply Chain | E12: {=IFERROR(INDEX('Meeting Briefs'!$E:$E,MATCH(B12,'Meeting Briefs'!$A:$A,0)),"")} -> Public MODEX signal plus likely fit for multi-site execution standardization. | F12: {=IFERROR(INDEX('Meeting Briefs'!$G:$G,MATCH(B12,'Meeting Briefs'!$A:$A,0)),"")} -> High-velocity snack network should respond to reduced gate friction, dock congestion, and more consistent trailer flow. | G12: {=IFERROR(INDEX('Hunt Plan'!$I:$I,MATCH(B12,'Hunt Plan'!$B:$B,0)),"")} -> PepsiCo network / LinkedIn path | H12: Identify target persona(s)
A13: {=IFERROR(INDEX(Accounts!$A:$A,MATCH(B13,Accounts!$B:$B,0)),"")} -> 2 | B13: Diageo | C13: Raymond Reddrick | SVP North America Supply - Manufacturing and Distillation | D13: Marsha McIntosh-Hamilton | President of North America Supply | E13: {=IFERROR(INDEX('Meeting Briefs'!$E:$E,MATCH(B13,'Meeting Briefs'!$A:$A,0)),"")} -> Public MODEX signal plus likely fit for multi-site execution standardization. | F13: {=IFERROR(INDEX('Meeting Briefs'!$G:$G,MATCH(B13,'Meeting Briefs'!$A:$A,0)),"")} -> Beverage flow is time-sensitive and network-heavy; YardFlow story should translate well from Primo. | G13: {=IFERROR(INDEX('Hunt Plan'!$I:$I,MATCH(B13,'Hunt Plan'!$B:$B,0)),"")} -> Board / advisor network research | H13: Identify target persona(s)
A14: {=IFERROR(INDEX(Accounts!$A:$A,MATCH(B14,Accounts!$B:$B,0)),"")} -> 5 | B14: Hormel Foods | C14: Will Bonifant | Group Vice President and Chief Supply Chain Officer | D14: Nicholas Schwartz | Supply Chain Planning COE & Strategy Lead | E14: {=IFERROR(INDEX('Meeting Briefs'!$E:$E,MATCH(B14,'Meeting Briefs'!$A:$A,0)),"")} -> New CSCO in March 2026. | F14: {=IFERROR(INDEX('Meeting Briefs'!$G:$G,MATCH(B14,'Meeting Briefs'!$A:$A,0)),"")} -> Food manufacturing plus leadership change makes this a strong “why now” account. | G14: {=IFERROR(INDEX('Hunt Plan'!$I:$I,MATCH(B14,'Hunt Plan'!$B:$B,0)),"")} -> Board / network research | H14: Identify target persona(s)
A15: {=IFERROR(INDEX(Accounts!$A:$A,MATCH(B15,Accounts!$B:$B,0)),"")} -> 5 | B15: JM Smucker | C15: Rob Ferguson | Chief Product Supply Officer | Executive Vice President, Coffee, Pet, and Away From Home | D15: Anbu Kuppusamy | Transportation Function Leader | E15: {=IFERROR(INDEX('Meeting Briefs'!$E:$E,MATCH(B15,'Meeting Briefs'!$A:$A,0)),"")} -> New Chief Product Supply Officer role in February 2026. | F15: {=IFERROR(INDEX('Meeting Briefs'!$G:$G,MATCH(B15,'Meeting Briefs'!$A:$A,0)),"")} -> New product supply leadership is a clean trigger for a network standardization conversation. | G15: {=IFERROR(INDEX('Hunt Plan'!$I:$I,MATCH(B15,'Hunt Plan'!$B:$B,0)),"")} -> Board / network research | H15: Identify target persona(s)
A16: {=IFERROR(INDEX(Accounts!$A:$A,MATCH(B16,Accounts!$B:$B,0)),"")} -> 9 | B16: The Home Depot | C16: John Deaton | Executive Vice President – Supply Chain & Product Development | D16: Amit Kalra | Senior Vice President – Supply Chain | E16: {=IFERROR(INDEX('Meeting Briefs'!$E:$E,MATCH(B16,'Meeting Briefs'!$A:$A,0)),"")} -> Official keynote tie gives unusually strong event signal. | F16: {=IFERROR(INDEX('Meeting Briefs'!$G:$G,MATCH(B16,'Meeting Briefs'!$A:$A,0)),"")} -> Strongest public MODEX signal. Massive retail network makes execution variance expensive. | G16: {=IFERROR(INDEX('Hunt Plan'!$I:$I,MATCH(B16,'Hunt Plan'!$B:$B,0)),"")} -> MODEX keynote proximity + ecosystem intros | H16: Identify target persona(s)
A17: {=IFERROR(INDEX(Accounts!$A:$A,MATCH(B17,Accounts!$B:$B,0)),"")} -> 10 | B17: Georgia Pacific | C17: Jeremy Finley | Vice President, Supply Chain | D17: Ryan Hutcherson | Senior Vice President, Supply Chain | E17: {=IFERROR(INDEX('Meeting Briefs'!$E:$E,MATCH(B17,'Meeting Briefs'!$A:$A,0)),"")} -> Public MODEX signal plus likely fit for multi-site execution standardization. | F17: {=IFERROR(INDEX('Meeting Briefs'!$G:$G,MATCH(B17,'Meeting Briefs'!$A:$A,0)),"")} -> Industrial plant flow and trailer variability create real throughput drag across sites. | G17: {=IFERROR(INDEX('Hunt Plan'!$I:$I,MATCH(B17,'Hunt Plan'!$B:$B,0)),"")} -> LinkedIn + website research | H17: Identify target persona(s)
A18: {=IFERROR(INDEX(Accounts!$A:$A,MATCH(B18,Accounts!$B:$B,0)),"")} -> 11 | B18: H-E-B | C18: Dakota Socha | Transportation & Reverse Logistics | D18: Craig Stucker | Director, Parkway Transport at H-E-B | E18: {=IFERROR(INDEX('Meeting Briefs'!$E:$E,MATCH(B18,'Meeting Briefs'!$A:$A,0)),"")} -> Public MODEX signal plus likely fit for multi-site execution standardization. | F18: {=IFERROR(INDEX('Meeting Briefs'!$G:$G,MATCH(B18,'Meeting Briefs'!$A:$A,0)),"")} -> Grocery distribution is brutally unforgiving; standardized site flow has obvious value. | G18: {=IFERROR(INDEX('Hunt Plan'!$I:$I,MATCH(B18,'Hunt Plan'!$B:$B,0)),"")} -> LinkedIn + grocery ops network | H18: Identify target persona(s)
A19: {=IFERROR(INDEX(Accounts!$A:$A,MATCH(B19,Accounts!$B:$B,0)),"")} -> 13 | B19: Hyundai Motor America | C19: Carey Gammon | Director, Vehicle Operations (HMA) | D19: Yongchul Chung | Senior Manager, Global Logistics & Supply Chain | E19: {=IFERROR(INDEX('Meeting Briefs'!$E:$E,MATCH(B19,'Meeting Briefs'!$A:$A,0)),"")} -> Public MODEX signal plus likely fit for multi-site execution standardization. | F19: {=IFERROR(INDEX('Meeting Briefs'!$G:$G,MATCH(B19,'Meeting Briefs'!$A:$A,0)),"")} -> Automotive has different physics than CPG, but flow variability still kills utilization and visibility. | G19: {=IFERROR(INDEX('Hunt Plan'!$I:$I,MATCH(B19,'Hunt Plan'!$B:$B,0)),"")} -> Automotive logistics network research | H19: Identify target persona(s)

Sheet Jake Queue
A1: Jake Queue
A2: Single pane of glass for what Jake should do next. Pulls together hot captures, due follow-ups, warm intros, and same-day recap work.
A4: Priority Bucket | B4: Due | C4: Account | D4: Persona | E4: Title / Task | F4: Source | G4: Owner | H4: Recommended Action | I4: Status | J4: Notes
A5: =IF('Live Capture'!A6="","",IF('Live Capture'!W6="HOT","HOT capture","Due follow-up")) -> HOT capture | B5: =IF(A5="","",IF(A5="HOT capture","Today",IF('Follow-Up Engine'!G6<>"",'Follow-Up Engine'!G6,"Today"))) -> Today | C5: =IF(A5="","",IF(A5="HOT capture",'Live Capture'!E6,'Follow-Up Engine'!B6)) -> Danone | D5: =IF(A5="","",IF(A5="HOT capture",'Live Capture'!F6,'Follow-Up Engine'!C6)) -> Test Contact | E5: =IF(A5="","",IF(A5="HOT capture",'Live Capture'!Q6,'Follow-Up Engine'!H6)) -> Send Danone Infographic | F5: =IF(A5="","",IF(A5="HOT capture","Live Capture","Follow-Up Engine")) -> Live Capture | G5: =IF(A5="","",IF(A5="HOT capture",'Live Capture'!R6,'Follow-Up Engine'!J6)) -> Jake | H5: =IF(A5="","",IF(A5="HOT capture","Send same-day recap and lock next step","Send asset / next-step follow-up")) -> Send same-day recap and lock next step | I5: =IF(A5="","",IF(A5="HOT capture",'Live Capture'!X6,'Follow-Up Engine'!K6)) -> Open | J5: =IF(A5="","",IF(A5="HOT capture",'Live Capture'!Y6,'Follow-Up Engine'!M6)) -> Test submission from setup validation
A6: =IF('Live Capture'!A7="","",IF('Live Capture'!W7="HOT","HOT capture","Due follow-up")) | B6: =IF(A6="","",IF(A6="HOT capture","Today",IF('Follow-Up Engine'!G7<>"",'Follow-Up Engine'!G7,"Today"))) | C6: =IF(A6="","",IF(A6="HOT capture",'Live Capture'!E7,'Follow-Up Engine'!B7)) | D6: =IF(A6="","",IF(A6="HOT capture",'Live Capture'!F7,'Follow-Up Engine'!C7)) | E6: =IF(A6="","",IF(A6="HOT capture",'Live Capture'!Q7,'Follow-Up Engine'!H7)) | F6: =IF(A6="","",IF(A6="HOT capture","Live Capture","Follow-Up Engine")) | G6: =IF(A6="","",IF(A6="HOT capture",'Live Capture'!R7,'Follow-Up Engine'!J7)) | H6: =IF(A6="","",IF(A6="HOT capture","Send same-day recap and lock next step","Send asset / next-step follow-up")) | I6: =IF(A6="","",IF(A6="HOT capture",'Live Capture'!X7,'Follow-Up Engine'!K7)) | J6: =IF(A6="","",IF(A6="HOT capture",'Live Capture'!Y7,'Follow-Up Engine'!M7))
A7: =IF('Live Capture'!A8="","",IF('Live Capture'!W8="HOT","HOT capture","Due follow-up")) | B7: =IF(A7="","",IF(A7="HOT capture","Today",IF('Follow-Up Engine'!G8<>"",'Follow-Up Engine'!G8,"Today"))) | C7: =IF(A7="","",IF(A7="HOT capture",'Live Capture'!E8,'Follow-Up Engine'!B8)) | D7: =IF(A7="","",IF(A7="HOT capture",'Live Capture'!F8,'Follow-Up Engine'!C8)) | E7: =IF(A7="","",IF(A7="HOT capture",'Live Capture'!Q8,'Follow-Up Engine'!H8)) | F7: =IF(A7="","",IF(A7="HOT capture","Live Capture","Follow-Up Engine")) | G7: =IF(A7="","",IF(A7="HOT capture",'Live Capture'!R8,'Follow-Up Engine'!J8)) | H7: =IF(A7="","",IF(A7="HOT capture","Send same-day recap and lock next step","Send asset / next-step follow-up")) | I7: =IF(A7="","",IF(A7="HOT capture",'Live Capture'!X8,'Follow-Up Engine'!K8)) | J7: =IF(A7="","",IF(A7="HOT capture",'Live Capture'!Y8,'Follow-Up Engine'!M8))
A8: =IF('Live Capture'!A9="","",IF('Live Capture'!W9="HOT","HOT capture","Due follow-up")) | B8: =IF(A8="","",IF(A8="HOT capture","Today",IF('Follow-Up Engine'!G9<>"",'Follow-Up Engine'!G9,"Today"))) | C8: =IF(A8="","",IF(A8="HOT capture",'Live Capture'!E9,'Follow-Up Engine'!B9)) | D8: =IF(A8="","",IF(A8="HOT capture",'Live Capture'!F9,'Follow-Up Engine'!C9)) | E8: =IF(A8="","",IF(A8="HOT capture",'Live Capture'!Q9,'Follow-Up Engine'!H9)) | F8: =IF(A8="","",IF(A8="HOT capture","Live Capture","Follow-Up Engine")) | G8: =IF(A8="","",IF(A8="HOT capture",'Live Capture'!R9,'Follow-Up Engine'!J9)) | H8: =IF(A8="","",IF(A8="HOT capture","Send same-day recap and lock next step","Send asset / next-step follow-up")) | I8: =IF(A8="","",IF(A8="HOT capture",'Live Capture'!X9,'Follow-Up Engine'!K9)) | J8: =IF(A8="","",IF(A8="HOT capture",'Live Capture'!Y9,'Follow-Up Engine'!M9))
A9: =IF('Live Capture'!A10="","",IF('Live Capture'!W10="HOT","HOT capture","Due follow-up")) | B9: =IF(A9="","",IF(A9="HOT capture","Today",IF('Follow-Up Engine'!G10<>"",'Follow-Up Engine'!G10,"Today"))) | C9: =IF(A9="","",IF(A9="HOT capture",'Live Capture'!E10,'Follow-Up Engine'!B10)) | D9: =IF(A9="","",IF(A9="HOT capture",'Live Capture'!F10,'Follow-Up Engine'!C10)) | E9: =IF(A9="","",IF(A9="HOT capture",'Live Capture'!Q10,'Follow-Up Engine'!H10)) | F9: =IF(A9="","",IF(A9="HOT capture","Live Capture","Follow-Up Engine")) | G9: =IF(A9="","",IF(A9="HOT capture",'Live Capture'!R10,'Follow-Up Engine'!J10)) | H9: =IF(A9="","",IF(A9="HOT capture","Send same-day recap and lock next step","Send asset / next-step follow-up")) | I9: =IF(A9="","",IF(A9="HOT capture",'Live Capture'!X10,'Follow-Up Engine'!K10)) | J9: =IF(A9="","",IF(A9="HOT capture",'Live Capture'!Y10,'Follow-Up Engine'!M10))
A10: =IF('Live Capture'!A11="","",IF('Live Capture'!W11="HOT","HOT capture","Due follow-up")) | B10: =IF(A10="","",IF(A10="HOT capture","Today",IF('Follow-Up Engine'!G11<>"",'Follow-Up Engine'!G11,"Today"))) | C10: =IF(A10="","",IF(A10="HOT capture",'Live Capture'!E11,'Follow-Up Engine'!B11)) | D10: =IF(A10="","",IF(A10="HOT capture",'Live Capture'!F11,'Follow-Up Engine'!C11)) | E10: =IF(A10="","",IF(A10="HOT capture",'Live Capture'!Q11,'Follow-Up Engine'!H11)) | F10: =IF(A10="","",IF(A10="HOT capture","Live Capture","Follow-Up Engine")) | G10: =IF(A10="","",IF(A10="HOT capture",'Live Capture'!R11,'Follow-Up Engine'!J11)) | H10: =IF(A10="","",IF(A10="HOT capture","Send same-day recap and lock next step","Send asset / next-step follow-up")) | I10: =IF(A10="","",IF(A10="HOT capture",'Live Capture'!X11,'Follow-Up Engine'!K11)) | J10: =IF(A10="","",IF(A10="HOT capture",'Live Capture'!Y11,'Follow-Up Engine'!M11))
A11: =IF('Live Capture'!A12="","",IF('Live Capture'!W12="HOT","HOT capture","Due follow-up")) | B11: =IF(A11="","",IF(A11="HOT capture","Today",IF('Follow-Up Engine'!G12<>"",'Follow-Up Engine'!G12,"Today"))) | C11: =IF(A11="","",IF(A11="HOT capture",'Live Capture'!E12,'Follow-Up Engine'!B12)) | D11: =IF(A11="","",IF(A11="HOT capture",'Live Capture'!F12,'Follow-Up Engine'!C12)) | E11: =IF(A11="","",IF(A11="HOT capture",'Live Capture'!Q12,'Follow-Up Engine'!H12)) | F11: =IF(A11="","",IF(A11="HOT capture","Live Capture","Follow-Up Engine")) | G11: =IF(A11="","",IF(A11="HOT capture",'Live Capture'!R12,'Follow-Up Engine'!J12)) | H11: =IF(A11="","",IF(A11="HOT capture","Send same-day recap and lock next step","Send asset / next-step follow-up")) | I11: =IF(A11="","",IF(A11="HOT capture",'Live Capture'!X12,'Follow-Up Engine'!K12)) | J11: =IF(A11="","",IF(A11="HOT capture",'Live Capture'!Y12,'Follow-Up Engine'!M12))
A12: =IF('Live Capture'!A13="","",IF('Live Capture'!W13="HOT","HOT capture","Due follow-up")) | B12: =IF(A12="","",IF(A12="HOT capture","Today",IF('Follow-Up Engine'!G13<>"",'Follow-Up Engine'!G13,"Today"))) | C12: =IF(A12="","",IF(A12="HOT capture",'Live Capture'!E13,'Follow-Up Engine'!B13)) | D12: =IF(A12="","",IF(A12="HOT capture",'Live Capture'!F13,'Follow-Up Engine'!C13)) | E12: =IF(A12="","",IF(A12="HOT capture",'Live Capture'!Q13,'Follow-Up Engine'!H13)) | F12: =IF(A12="","",IF(A12="HOT capture","Live Capture","Follow-Up Engine")) | G12: =IF(A12="","",IF(A12="HOT capture",'Live Capture'!R13,'Follow-Up Engine'!J13)) | H12: =IF(A12="","",IF(A12="HOT capture","Send same-day recap and lock next step","Send asset / next-step follow-up")) | I12: =IF(A12="","",IF(A12="HOT capture",'Live Capture'!X13,'Follow-Up Engine'!K13)) | J12: =IF(A12="","",IF(A12="HOT capture",'Live Capture'!Y13,'Follow-Up Engine'!M13))
A13: =IF('Live Capture'!A14="","",IF('Live Capture'!W14="HOT","HOT capture","Due follow-up")) | B13: =IF(A13="","",IF(A13="HOT capture","Today",IF('Follow-Up Engine'!G14<>"",'Follow-Up Engine'!G14,"Today"))) | C13: =IF(A13="","",IF(A13="HOT capture",'Live Capture'!E14,'Follow-Up Engine'!B14)) | D13: =IF(A13="","",IF(A13="HOT capture",'Live Capture'!F14,'Follow-Up Engine'!C14)) | E13: =IF(A13="","",IF(A13="HOT capture",'Live Capture'!Q14,'Follow-Up Engine'!H14)) | F13: =IF(A13="","",IF(A13="HOT capture","Live Capture","Follow-Up Engine")) | G13: =IF(A13="","",IF(A13="HOT capture",'Live Capture'!R14,'Follow-Up Engine'!J14)) | H13: =IF(A13="","",IF(A13="HOT capture","Send same-day recap and lock next step","Send asset / next-step follow-up")) | I13: =IF(A13="","",IF(A13="HOT capture",'Live Capture'!X14,'Follow-Up Engine'!K14)) | J13: =IF(A13="","",IF(A13="HOT capture",'Live Capture'!Y14,'Follow-Up Engine'!M14))
A14: =IF('Live Capture'!A15="","",IF('Live Capture'!W15="HOT","HOT capture","Due follow-up")) | B14: =IF(A14="","",IF(A14="HOT capture","Today",IF('Follow-Up Engine'!G15<>"",'Follow-Up Engine'!G15,"Today"))) | C14: =IF(A14="","",IF(A14="HOT capture",'Live Capture'!E15,'Follow-Up Engine'!B15)) | D14: =IF(A14="","",IF(A14="HOT capture",'Live Capture'!F15,'Follow-Up Engine'!C15)) | E14: =IF(A14="","",IF(A14="HOT capture",'Live Capture'!Q15,'Follow-Up Engine'!H15)) | F14: =IF(A14="","",IF(A14="HOT capture","Live Capture","Follow-Up Engine")) | G14: =IF(A14="","",IF(A14="HOT capture",'Live Capture'!R15,'Follow-Up Engine'!J15)) | H14: =IF(A14="","",IF(A14="HOT capture","Send same-day recap and lock next step","Send asset / next-step follow-up")) | I14: =IF(A14="","",IF(A14="HOT capture",'Live Capture'!X15,'Follow-Up Engine'!K15)) | J14: =IF(A14="","",IF(A14="HOT capture",'Live Capture'!Y15,'Follow-Up Engine'!M15))
A15: =IF('Live Capture'!A16="","",IF('Live Capture'!W16="HOT","HOT capture","Due follow-up")) | B15: =IF(A15="","",IF(A15="HOT capture","Today",IF('Follow-Up Engine'!G16<>"",'Follow-Up Engine'!G16,"Today"))) | C15: =IF(A15="","",IF(A15="HOT capture",'Live Capture'!E16,'Follow-Up Engine'!B16)) | D15: =IF(A15="","",IF(A15="HOT capture",'Live Capture'!F16,'Follow-Up Engine'!C16)) | E15: =IF(A15="","",IF(A15="HOT capture",'Live Capture'!Q16,'Follow-Up Engine'!H16)) | F15: =IF(A15="","",IF(A15="HOT capture","Live Capture","Follow-Up Engine")) | G15: =IF(A15="","",IF(A15="HOT capture",'Live Capture'!R16,'Follow-Up Engine'!J16)) | H15: =IF(A15="","",IF(A15="HOT capture","Send same-day recap and lock next step","Send asset / next-step follow-up")) | I15: =IF(A15="","",IF(A15="HOT capture",'Live Capture'!X16,'Follow-Up Engine'!K16)) | J15: =IF(A15="","",IF(A15="HOT capture",'Live Capture'!Y16,'Follow-Up Engine'!M16))
A16: =IF('Live Capture'!A17="","",IF('Live Capture'!W17="HOT","HOT capture","Due follow-up")) | B16: =IF(A16="","",IF(A16="HOT capture","Today",IF('Follow-Up Engine'!G17<>"",'Follow-Up Engine'!G17,"Today"))) | C16: =IF(A16="","",IF(A16="HOT capture",'Live Capture'!E17,'Follow-Up Engine'!B17)) | D16: =IF(A16="","",IF(A16="HOT capture",'Live Capture'!F17,'Follow-Up Engine'!C17)) | E16: =IF(A16="","",IF(A16="HOT capture",'Live Capture'!Q17,'Follow-Up Engine'!H17)) | F16: =IF(A16="","",IF(A16="HOT capture","Live Capture","Follow-Up Engine")) | G16: =IF(A16="","",IF(A16="HOT capture",'Live Capture'!R17,'Follow-Up Engine'!J17)) | H16: =IF(A16="","",IF(A16="HOT capture","Send same-day recap and lock next step","Send asset / next-step follow-up")) | I16: =IF(A16="","",IF(A16="HOT capture",'Live Capture'!X17,'Follow-Up Engine'!K17)) | J16: =IF(A16="","",IF(A16="HOT capture",'Live Capture'!Y17,'Follow-Up Engine'!M17))
... A24: =IF('Live Capture'!A25="","",IF('Live Capture'!W25="HOT","HOT capture","Due follow-up")) | B24: =IF(A24="","",IF(A24="HOT capture","Today",IF('Follow-Up Engine'!G25<>"",'Follow-Up Engine'!G25,"Today"))) | C24: =IF(A24="","",IF(A24="HOT capture",'Live Capture'!E25,'Follow-Up Engine'!B25)) | D24: =IF(A24="","",IF(A24="HOT capture",'Live Capture'!F25,'Follow-Up Engine'!C25)) | E24: =IF(A24="","",IF(A24="HOT capture",'Live Capture'!Q25,'Follow-Up Engine'!H25)) | F24: =IF(A24="","",IF(A24="HOT capture","Live Capture","Follow-Up Engine")) | G24: =IF(A24="","",IF(A24="HOT capture",'Live Capture'!R25,'Follow-Up Engine'!J25)) | H24: =IF(A24="","",IF(A24="HOT capture","Send same-day recap and lock next step","Send asset / next-step follow-up")) | I24: =IF(A24="","",IF(A24="HOT capture",'Live Capture'!X25,'Follow-Up Engine'!K25)) | J24: =IF(A24="","",IF(A24="HOT capture",'Live Capture'!Y25,'Follow-Up Engine'!M25))

Sheet Form Intake Control
A1: Field | B1: Value | C1: Notes
A2: Form Name | B2: FreightRoll MODEX Mobile Intake | C2: Google Form created by script
A3: Form Edit URL | B3: https://docs.google.com/forms/d/1VEaHPZWUIdtGdDg-vqClCCzBpQq8zf1kTzzg2OTMWls/edit | C3: Owner/admin link
A4: Form Published URL | B4: https://docs.google.com/forms/d/e/1FAIpQLSeTjD6PG1DaJkBSHl-Zrx5eLqr5HZ4pZd9wWFORaQGzfaEJzg/viewform | C4: Share this for intake
A5: Spreadsheet URL | B5: https://docs.google.com/spreadsheets/d/1kaszaXK2LNXQ4BOzUQ-lYgX21P-rmI0JN7ux4fdQIZE/edit | C5: Bound spreadsheet
A6: Last Setup Run | B6: 46106.438 | C6: Timestamp
A7: Next Step | B7: Validate Live Capture + QR workflow | C7: If QR has not already been built
A8: Test | B8: Submit 1 fake response | C8: Confirm Live Capture populates
A9: Status | B9: Operational

Sheet QR Journey
A1: Label | B1: Value
A2: Journey Concept | B2: Scan -> Prefilled intake -> Live Capture -> Follow-up engine
A3: Master Intake URL | B3: https://docs.google.com/forms/d/e/1FAIpQLSeTjD6PG1DaJkBSHl-Zrx5eLqr5HZ4pZd9wWFORaQGzfaEJzg/viewform
A4: Master QR | B4: =image("https://quickchart.io/qr?text="&encodeurl(B3)&"&size=240")
A5: Recommended Use | B5: Use this on-screen or printed at booth / meeting table
A6: Account-Specific QR | B6: See QR Assets tab
A7: Why it matters | B7: Digital driver journey homage: cleaner handoff, faster capture, less note chaos

Sheet QR Assets
A1: Account | B1: Prefilled Form URL | C1: QR Formula | D1: Default Asset | E1: Primo Default | F1: Source Sheet | G1: Notes
A2: Danone | B2: https://docs.google.com/forms/d/e/1FAIpQLSeTjD6PG1DaJkBSHl-Zrx5eLqr5HZ4pZd9wWFORaQGzfaEJzg/viewform?usp=pp_url&entry.1824994547=Danone&entry.1519321262=Infographic&entry.717907390=Yes | C2: =image("https://quickchart.io/qr?text="&encodeurl(B2)&"&size=180") | D2: Infographic | E2: Yes | G2: Account-specific prefilled QR
A3: General Mills | B3: https://docs.google.com/forms/d/e/1FAIpQLSeTjD6PG1DaJkBSHl-Zrx5eLqr5HZ4pZd9wWFORaQGzfaEJzg/viewform?usp=pp_url&entry.1824994547=General+Mills&entry.1519321262=Infographic&entry.717907390=Yes | C3: =image("https://quickchart.io/qr?text="&encodeurl(B3)&"&size=180") | D3: Infographic | E3: Yes | G3: Account-specific prefilled QR
A4: Frito-Lay | B4: https://docs.google.com/forms/d/e/1FAIpQLSeTjD6PG1DaJkBSHl-Zrx5eLqr5HZ4pZd9wWFORaQGzfaEJzg/viewform?usp=pp_url&entry.1824994547=Frito-Lay&entry.1519321262=Infographic&entry.717907390=Yes | C4: =image("https://quickchart.io/qr?text="&encodeurl(B4)&"&size=180") | D4: Infographic | E4: Yes | G4: Account-specific prefilled QR
A5: Diageo | B5: https://docs.google.com/forms/d/e/1FAIpQLSeTjD6PG1DaJkBSHl-Zrx5eLqr5HZ4pZd9wWFORaQGzfaEJzg/viewform?usp=pp_url&entry.1824994547=Diageo&entry.1519321262=Infographic&entry.717907390=Yes | C5: =image("https://quickchart.io/qr?text="&encodeurl(B5)&"&size=180") | D5: Infographic | E5: Yes | G5: Account-specific prefilled QR
A6: Hormel Foods | B6: https://docs.google.com/forms/d/e/1FAIpQLSeTjD6PG1DaJkBSHl-Zrx5eLqr5HZ4pZd9wWFORaQGzfaEJzg/viewform?usp=pp_url&entry.1824994547=Hormel+Foods&entry.1519321262=Infographic&entry.717907390=Yes | C6: =image("https://quickchart.io/qr?text="&encodeurl(B6)&"&size=180") | D6: Infographic | E6: Yes | G6: Account-specific prefilled QR
A7: JM Smucker | B7: https://docs.google.com/forms/d/e/1FAIpQLSeTjD6PG1DaJkBSHl-Zrx5eLqr5HZ4pZd9wWFORaQGzfaEJzg/viewform?usp=pp_url&entry.1824994547=JM+Smucker&entry.1519321262=Infographic&entry.717907390=Yes | C7: =image("https://quickchart.io/qr?text="&encodeurl(B7)&"&size=180") | D7: Infographic | E7: Yes | G7: Account-specific prefilled QR
A8: The Home Depot | B8: https://docs.google.com/forms/d/e/1FAIpQLSeTjD6PG1DaJkBSHl-Zrx5eLqr5HZ4pZd9wWFORaQGzfaEJzg/viewform?usp=pp_url&entry.1824994547=The+Home+Depot&entry.1519321262=Infographic&entry.717907390=Yes | C8: =image("https://quickchart.io/qr?text="&encodeurl(B8)&"&size=180") | D8: Infographic | E8: Yes | G8: Account-specific prefilled QR
A9: Georgia Pacific | B9: https://docs.google.com/forms/d/e/1FAIpQLSeTjD6PG1DaJkBSHl-Zrx5eLqr5HZ4pZd9wWFORaQGzfaEJzg/viewform?usp=pp_url&entry.1824994547=Georgia+Pacific&entry.1519321262=Infographic&entry.717907390=Yes | C9: =image("https://quickchart.io/qr?text="&encodeurl(B9)&"&size=180") | D9: Infographic | E9: Yes | G9: Account-specific prefilled QR
A10: H-E-B | B10: https://docs.google.com/forms/d/e/1FAIpQLSeTjD6PG1DaJkBSHl-Zrx5eLqr5HZ4pZd9wWFORaQGzfaEJzg/viewform?usp=pp_url&entry.1824994547=H-E-B&entry.1519321262=Infographic&entry.717907390=Yes | C10: =image("https://quickchart.io/qr?text="&encodeurl(B10)&"&size=180") | D10: Infographic | E10: Yes | G10: Account-specific prefilled QR
A11: Hyundai Motor America | B11: https://docs.google.com/forms/d/e/1FAIpQLSeTjD6PG1DaJkBSHl-Zrx5eLqr5HZ4pZd9wWFORaQGzfaEJzg/viewform?usp=pp_url&entry.1824994547=Hyundai+Motor+America&entry.1519321262=Infographic&entry.717907390=Yes | C11: =image("https://quickchart.io/qr?text="&encodeurl(B11)&"&size=180") | D11: Infographic | E11: Yes | G11: Account-specific prefilled QR
A12: Honda | B12: https://docs.google.com/forms/d/e/1FAIpQLSeTjD6PG1DaJkBSHl-Zrx5eLqr5HZ4pZd9wWFORaQGzfaEJzg/viewform?usp=pp_url&entry.1824994547=Honda&entry.1519321262=Infographic&entry.717907390=Yes | C12: =image("https://quickchart.io/qr?text="&encodeurl(B12)&"&size=180") | D12: Infographic | E12: Yes | G12: Account-specific prefilled QR
A13: John Deere | B13: https://docs.google.com/forms/d/e/1FAIpQLSeTjD6PG1DaJkBSHl-Zrx5eLqr5HZ4pZd9wWFORaQGzfaEJzg/viewform?usp=pp_url&entry.1824994547=John+Deere&entry.1519321262=Infographic&entry.717907390=Yes | C13: =image("https://quickchart.io/qr?text="&encodeurl(B13)&"&size=180") | D13: Infographic | E13: Yes | G13: Account-specific prefilled QR
... A21: IKEA | B21: https://docs.google.com/forms/d/e/1FAIpQLSeTjD6PG1DaJkBSHl-Zrx5eLqr5HZ4pZd9wWFORaQGzfaEJzg/viewform?usp=pp_url&entry.1824994547=IKEA&entry.1519321262=Infographic&entry.717907390=Yes | C21: =image("https://quickchart.io/qr?text="&encodeurl(B21)&"&size=180") | D21: Infographic | E21: Yes | G21: Account-specific prefilled QR

Sheet Form Schema
A1: Form Schema
A2: This is the canonical mobile intake schema. The companion Apps Script can build a Google Form from these fields or you can recreate them manually.
A4: Order | B4: Question Title | C4: Type | D4: Required? | E4: Suggested Choices | F4: Maps to Live Capture | G4: Notes
A5: 1 | B5: Show Day | C5: MULTIPLE_CHOICE | D5: Yes | E5: Day 1|Day 2|Day 3|Day 4 | F5: Show Day | G5: Keep event day consistent.
A6: 2 | B6: Time Block | C6: MULTIPLE_CHOICE | D6: Yes | E6: 8:00-10:00|10:00-12:00|12:00-2:00|2:00-4:00|4:00-6:00 | F6: Time Block | G6: Use simple windows.
A7: 3 | B7: Account | C7: TEXT | D7: Yes | F7: Account | G7: Short answer allows unknown net-new accounts.
A8: 4 | B8: Persona Name | C8: TEXT | D8: No | F8: Persona Name | G8: Named buyer or operator.
A9: 5 | B9: Title | C9: TEXT | D9: No | F9: Title | G9: Useful for influence scoring.
A10: 6 | B10: Channel | C10: MULTIPLE_CHOICE | D10: Yes | E10: Booth|Floor walk-up|Warm intro|Scheduled meeting|Session|Afterparty | F10: Channel | G10: Quick attribution.
A11: 7 | B11: Meeting Type | C11: MULTIPLE_CHOICE | D11: Yes | E11: Intro|Discovery|Proof validation|Follow-up|Partner | F11: Meeting Type | G11: Maps to meeting style.
A12: 8 | B12: Location | C12: TEXT | D12: No | F12: Location | G12: Hall / booth / coffee / offsite.
A13: 9 | B13: Interest (1-5) | C13: MULTIPLE_CHOICE | D13: Yes | E13: 1|2|3|4|5 | F13: Interest (1-5) | G13: Core heat signal.
A14: 10 | B14: Urgency (1-5) | C14: MULTIPLE_CHOICE | D14: Yes | E14: 1|2|3|4|5 | F14: Urgency (1-5) | G14: Core heat signal.
A15: 11 | B15: Influence (1-5) | C15: MULTIPLE_CHOICE | D15: Yes | E15: 1|2|3|4|5 | F15: Influence (1-5) | G15: Core heat signal.
A16: 12 | B16: Use-Case Fit (1-5) | C16: MULTIPLE_CHOICE | D16: Yes | E16: 1|2|3|4|5 | F16: Use-Case Fit (1-5) | G16: Core heat signal.
A17: 13 | B17: Requested Asset | C17: MULTIPLE_CHOICE | D17: No | E17: Infographic|Leave-behind|ROI model|Primo proof|Case study|Deck | F17: Requested Asset | G17: Useful for routing.
A18: 14 | B18: Need Primo? | C18: MULTIPLE_CHOICE | D18: Yes | E18: Yes|No | F18: Need Primo? | G18: Triggers customer proof workflow.
A19: 15 | B19: Next Step | C19: TEXT | D19: No | F19: Next Step | G19: What should happen next.
A20: 16 | B20: Owner | C20: MULTIPLE_CHOICE | D20: Yes | E20: Jake|Casey|Jake / Casey | F20: Owner | G20: Routing owner.
A21: 17 | B21: Due Date | C21: DATE | D21: No | F21: Due Date | G21: Optional follow-up target.
A22: 18 | B22: Follow-Up Template | C22: MULTIPLE_CHOICE | D22: No | E22: Post-meeting strong interest|Post-meeting standard|Warm intro ask|Primo proof ask|Missed connect | F22: Follow-Up Template | G22: Automation hint.
A23: 19 | B23: Outcome | C23: MULTIPLE_CHOICE | D23: No | E23: Met|Qualified|Needs intro|Send asset|Not a fit|Follow later | F23: Outcome | G23: Simple post-convo classification.
A24: 20 | B24: Notes | C24: PARAGRAPH_TEXT | D24: No | F24: Notes | G24: Freeform context.

Sheet Form Ops
A1: Check | B1: Status | C1: Value | D1: Notes
A2: Form exists | B2: OK | C2: 1VEaHPZWUIdtGdDg-vqClCCzBpQq8zf1kTzzg2OTMWls
A3: Published URL | B3: OK | C3: https://docs.google.com/forms/d/e/1FAIpQLSeTjD6PG1DaJkBSHl-Zrx5eLqr5HZ4pZd9wWFORaQGzfaEJzg/viewform
A4: Edit URL | B4: OK | C4: https://docs.google.com/forms/d/1VEaHPZWUIdtGdDg-vqClCCzBpQq8zf1kTzzg2OTMWls/edit
A5: Destination spreadsheet | B5: OK | C5: 1kaszaXK2LNXQ4BOzUQ-lYgX21P-rmI0JN7ux4fdQIZE
A6: Trigger installed | B6: OK | C6: onFormSubmit

Sheet Form-to-LiveCapture Map
A1: Form-to-Live Capture Map
A2: This is the routing logic the Apps Script follows when a form response arrives. Raw Google Form answers are normalized into the operating columns on Live Capture.
A4: Live Capture Column | B4: Live Capture Header | C4: Source Question / Value | D4: Transform | E4: Required? | F4: Notes
A5: A | B5: Capture ID | C5: Generated by script | D5: LC-FORM-### sequence | E5: Yes | F5: Do not come from the form.
A6: B | B6: Logged At | C6: Form submit timestamp | D6: Use submit timestamp | E6: Yes | F6: Keeps chronological audit trail.
A7: C | B7: Show Day | C7: Show Day | D7: Direct map | E7: Yes
A8: D | B8: Time Block | C8: Time Block | D8: Direct map | E8: Yes
A9: E | B9: Account | C9: Account | D9: Direct map | E9: Yes
A10: F | B10: Persona Name | C10: Persona Name | D10: Direct map | E10: No
A11: G | B11: Title | C11: Title | D11: Direct map | E11: No
A12: H | B12: Channel | C12: Channel | D12: Direct map | E12: Yes
A13: I | B13: Meeting Type | C13: Meeting Type | D13: Direct map | E13: Yes
A14: J | B14: Location | C14: Location | D14: Direct map | E14: No
A15: K | B15: Interest (1-5) | C15: Interest (1-5) | D15: Numeric parse | E15: Yes
A16: L | B16: Urgency (1-5) | C16: Urgency (1-5) | D16: Numeric parse | E16: Yes
A17: M | B17: Influence (1-5) | C17: Influence (1-5) | D17: Numeric parse | E17: Yes
A18: N | B18: Use-Case Fit (1-5) | C18: Use-Case Fit (1-5) | D18: Numeric parse | E18: Yes
... A25: U | B25: Outcome | C25: Outcome | D25: Direct map | E25: No
A26: V | B26: Heat Score | C26: Calculated in-sheet | D26: Interest+Urgency+Influence+Fit+(2 if Primo=Yes) | E26: Yes | F26: Formula remains in sheet.
A27: W | B27: Band | C27: Calculated in-sheet | D27: HOT/WARM/WORK/NURTURE based on score | E27: Yes | F27: Formula remains in sheet.
A28: X | B28: Status | C28: Default | D28: Open | E28: Yes | F28: Script default.
A29: Y | B29: Notes | C29: Notes | D29: Direct map | E29: No

Sheet Apps Script Install
A1: Apps Script Install
A2: Google Sheets supports custom menus and lets you assign Apps Script functions to images or drawings in a bound spreadsheet. Use this tab to wire the workbook into a clickable operating system after upload.
A4: Step | B4: What to do | C4: Why it matters | D4: Reference URL
A5: 1 | B5: Upload the workbook to Google Drive and open it with Google Sheets. | C5: The script must be bound to the Google Sheet, not left as a local Excel file. | D5: https://developers.google.com/apps-script/guides/sheets
A6: 2 | B6: Open Extensions > Apps Script and replace the default project with the companion files in the ZIP bundle. | C6: This creates the custom FreightRoll Control Tower menu and quick actions. | D6: https://developers.google.com/apps-script/guides/menus
A7: 3 | B7: Save the project, run onOpen once, and authorize the script. | C7: Authorization is required before menus and row actions work. | D7: https://developers.google.com/apps-script/guides/menus
A8: 4 | B8: Insert drawings on Control Tower or Field View for the actions you use most. Assign each drawing the matching function name. | C8: Sheets lets images and drawings run bound Apps Script functions when clicked. | D8: https://developers.google.com/apps-script/guides/menus
A9: 5 | B9: Use the sidebar or custom menu during MODEX to jump between tabs, stamp status, log rows to Meetings, and queue follow-up. | C9: This removes friction and keeps the floor workflow tight. | D9: https://developers.google.com/apps-script/guides/sheets
A12: Suggested button labels
A13: Button label | B13: Assign this script function | C13: Put it on | D13: What it does
A14: Live Capture | B14: openLiveCapture | C14: Control Tower | D14: Jump straight into the fast-entry tab.
A15: Jake Queue | B15: openJakeQueue | C15: Control Tower | D15: Open the triage board.
A16: Log Meeting | B16: logSelectedLiveCaptureToMeetings | C16: Field View / Live Capture | D16: Push selected capture row into Meetings and Activities.
A17: Queue Follow-Up | B17: queueSelectedLiveCaptureFollowUp | C17: Field View / Live Capture | D17: Create an activity from the selected capture row.
A18: Mark HOT | B18: markSelectedCaptureHot | C18: Field View / Live Capture | D18: Set band/status for the selected row.
A19: Reset Filters | B19: resetAllFilters | C19: Control Tower / Field View | D19: Clear filters and hidden rows across key tabs.
A21: Form automation add-on
A22: 1 | B22: Run setupMobileForm() from Apps Script after uploading to Google Sheets. | C22: Creates a Google Form, sets this spreadsheet as the response destination, and installs the submit trigger. | D22: https://developers.google.com/apps-script/reference/forms
A23: 2 | B23: Submit one test response from your phone. | C23: Confirms the raw response sheet and the Live Capture routing are both working. | D23: https://support.google.com/docs/answer/2917686?hl=en
A24: 3 | B24: Use backfillLatestFormResponses() only if you need to replay raw rows into Live Capture. | C24: Helpful after script updates or if the trigger was not installed initially. | D24: https://developers.google.com/apps-script/guides/sheets

Sheet Automation Map
A1: Automation Map
A2: What the script project is designed to automate once this workbook is uploaded to Google Sheets.
A4: Function | B4: Tab(s) | C4: Trigger type | D4: Input | E4: Output | F4: Notes
A5: onOpen | B5: All | C5: Open spreadsheet | D5: None | E5: FreightRoll Control Tower custom menu | F5: Creates navigation + quick actions menu.
A6: openControlTower | B6: Control Tower | C6: Menu / button | D6: None | E6: Moves user to Control Tower | F6: Fast home-base action.
A7: openLiveCapture | B7: Live Capture | C7: Menu / button | D7: None | E7: Moves user to Live Capture | F7: Use this constantly on the floor.
A8: openJakeQueue | B8: Jake Queue | C8: Menu / button | D8: None | E8: Moves user to Jake Queue | F8: Daily triage view.
A9: logSelectedLiveCaptureToMeetings | B9: Live Capture, Meetings, Activities | C9: Menu / button | D9: Active row on Live Capture | E9: Creates/updates meeting + activity log entries | F9: Use after a real conversation.
A10: queueSelectedLiveCaptureFollowUp | B10: Live Capture, Activities | C10: Menu / button | D10: Active row on Live Capture | E10: Creates a follow-up task in Activities | F10: For anything that did not become a formal meeting.
A11: markSelectedCaptureHot | B11: Live Capture | C11: Menu / button | D11: Active row on Live Capture | E11: Sets band/status to HOT/Open | F11: Great for floor triage.
A12: markSelectedCaptureWarm | B12: Live Capture | C12: Menu / button | D12: Active row on Live Capture | E12: Sets band/status to WARM/Open
A13: resetAllFilters | B13: Field tabs | C13: Menu / button | D13: None | E13: Clears filters across operating tabs | F13: Handy after sorting chaos sets in.
A14: buildJakeDailyBrief | B14: Jake Queue, Dashboard | C14: Menu | D14: None | E14: Refreshes daily brief timestamp + jumps to queue | F14: Lightweight daily reset.
A15: setupMobileForm | B15: Form Intake Control / Google Form | C15: Manual run | D15: None | E15: Creates linked mobile intake form + writes URLs | F15: Primary setup action.
A16: installFormTrigger | B16: Apps Script project | C16: Manual run | D16: None | E16: Installable onFormSubmit trigger | F16: Needed for automated routing.
A17: onFormSubmit | B17: Raw form response sheet / Live Capture | C17: Form submit trigger | D17: Form event object | E17: New normalized Live Capture row | F17: Routes phone submissions into operating sheet.
A18: backfillLatestFormResponses | B18: Raw form response sheet / Live Capture | C18: Manual run | D18: Existing raw rows | E18: Rebuild / replay Live Capture rows | F18: Use after trigger problems or mapping changes.
A19: openFormIntakeControl | B19: Form Intake Control | C19: Menu / sidebar | D19: None | E19: Moves user to Form Intake Control tab | F19: Fast setup navigation.

Sheet Field View
A1: Field View
A2: One-line operating view for the top 20. Designed for quick scanning on a laptop at the show or over coffee before the next lap.
A4: Rank | B4: Account | C4: Tier | D4: Exec Anchor | E4: Operator Anchor | F4: Intro Path | G4: Best Asset | H4: Next Move | I4: Meeting Status | J4: Live Captures | K4: HOT Captures | L4: Open Due | M4: Last Activity
A5: ='Top 20 Board'!A2 -> 1 | B5: ='Top 20 Board'!B2 -> Danone | C5: ='Top 20 Board'!D2 -> Tier 1 | D5: ='Top 20 Board'!E2 -> Heiko Gerling | Chief Operations Officer, North America | E5: ='Top 20 Board'!F2 -> Whitney Klemm | Supply Chain Leader | F5: ='Top 20 Board'!H2 -> Mark Shaughnessy -> Danone CSCO intro | G5: {=IFERROR(INDEX('Graphic Assets'!$G:$G,MATCH(B5,'Graphic Assets'!$A:$A,0)),"Infographic")} -> Infographic | H5: {=IFERROR(INDEX('Account Dossiers'!$N:$N,MATCH(B5,'Account Dossiers'!$B:$B,0)),"")} -> Work Shaughnessy intro first, then flank with operator-level outreach in Jacksonville and logistics transformation lanes. | I5: =IF(COUNTIFS(Meetings!$B:$B,B5,Meetings!$D:$D,"Booked")>0,"Booked",IF(COUNTIFS(Meetings!$B:$B,B5,Meetings!$D:$D,"Completed")>0,"Completed",IF(COUNTIFS(Meetings!$B:$B,B5,Meetings!$D:$D,"Requested")>0,"Requested","Targeted"))) -> Targeted | J5: =COUNTIF('Live Capture'!$E:$E,B5) -> 1 | K5: =COUNTIFS('Live Capture'!$E:$E,B5,'Live Capture'!$W:$W,"HOT") -> 1 | L5: =COUNTIFS('Live Capture'!$E:$E,B5,'Live Capture'!$S:$S,"<="&TODAY(),'Live Capture'!$X:$X,"<>Closed") -> 0 | M5: =IFERROR(maxifs(Activities!$A:$A,Activities!$B:$B,B5),"") -> 46106.495
A6: ='Top 20 Board'!A3 -> 2 | B6: ='Top 20 Board'!B3 -> General Mills | C6: ='Top 20 Board'!D3 -> Tier 1 | D6: ='Top 20 Board'!E3 -> Jonathan Ness | Chief Supply Chain Officer | E6: ='Top 20 Board'!F3 -> Nisar Ahsanullah | General Mills supply chain leader | F6: ='Top 20 Board'!H3 -> No warm intro yet | G6: {=IFERROR(INDEX('Graphic Assets'!$G:$G,MATCH(B6,'Graphic Assets'!$A:$A,0)),"Infographic")} -> Infographic | H6: {=IFERROR(INDEX('Account Dossiers'!$N:$N,MATCH(B6,'Account Dossiers'!$B:$B,0)),"")} -> Lead with the new-CSCO why-now and hunt two levels down into logistics and customer operations. | I6: =IF(COUNTIFS(Meetings!$B:$B,B6,Meetings!$D:$D,"Booked")>0,"Booked",IF(COUNTIFS(Meetings!$B:$B,B6,Meetings!$D:$D,"Completed")>0,"Completed",IF(COUNTIFS(Meetings!$B:$B,B6,Meetings!$D:$D,"Requested")>0,"Requested","Targeted"))) -> Targeted | J6: =COUNTIF('Live Capture'!$E:$E,B6) -> 0 | K6: =COUNTIFS('Live Capture'!$E:$E,B6,'Live Capture'!$W:$W,"HOT") -> 0 | L6: =COUNTIFS('Live Capture'!$E:$E,B6,'Live Capture'!$S:$S,"<="&TODAY(),'Live Capture'!$X:$X,"<>Closed") -> 0 | M6: =IFERROR(maxifs(Activities!$A:$A,Activities!$B:$B,B6),"") -> 0
A7: ='Top 20 Board'!A4 -> 2 | B7: ='Top 20 Board'!B4 -> Frito-Lay | C7: ='Top 20 Board'!D4 -> Tier 1 | D7: ='Top 20 Board'!E4 -> Beth Mars | Transportation Director | E7: ='Top 20 Board'!F4 -> Brian Watson | Vice President of Supply Chain | F7: ='Top 20 Board'!H4 -> PepsiCo network / LinkedIn path | G7: {=IFERROR(INDEX('Graphic Assets'!$G:$G,MATCH(B7,'Graphic Assets'!$A:$A,0)),"Infographic")} -> Infographic | H7: {=IFERROR(INDEX('Account Dossiers'!$N:$N,MATCH(B7,'Account Dossiers'!$B:$B,0)),"")} -> Hunt PepsiCo North America and Frito-Lay logistics leaders tied to food/beverage integration and warehousing transformation. | I7: =IF(COUNTIFS(Meetings!$B:$B,B7,Meetings!$D:$D,"Booked")>0,"Booked",IF(COUNTIFS(Meetings!$B:$B,B7,Meetings!$D:$D,"Completed")>0,"Completed",IF(COUNTIFS(Meetings!$B:$B,B7,Meetings!$D:$D,"Requested")>0,"Requested","Targeted"))) -> Targeted | J7: =COUNTIF('Live Capture'!$E:$E,B7) -> 0 | K7: =COUNTIFS('Live Capture'!$E:$E,B7,'Live Capture'!$W:$W,"HOT") -> 0 | L7: =COUNTIFS('Live Capture'!$E:$E,B7,'Live Capture'!$S:$S,"<="&TODAY(),'Live Capture'!$X:$X,"<>Closed") -> 0 | M7: =IFERROR(maxifs(Activities!$A:$A,Activities!$B:$B,B7),"") -> 0
A8: ='Top 20 Board'!A5 -> 2 | B8: ='Top 20 Board'!B5 -> Diageo | C8: ='Top 20 Board'!D5 -> Tier 1 | D8: ='Top 20 Board'!E5 -> Raymond Reddrick | SVP North America Supply - Manufacturing and Distillation | E8: ='Top 20 Board'!F5 -> Marsha McIntosh-Hamilton | President of North America Supply | F8: ='Top 20 Board'!H5 -> Board / advisor network research | G8: {=IFERROR(INDEX('Graphic Assets'!$G:$G,MATCH(B8,'Graphic Assets'!$A:$A,0)),"Infographic")} -> Infographic | H8: {=IFERROR(INDEX('Account Dossiers'!$N:$N,MATCH(B8,'Account Dossiers'!$B:$B,0)),"")} -> Target North America supply chain + Alabama project leaders; ask for a short meeting on standardizing site execution before scale introduces entropy. | I8: =IF(COUNTIFS(Meetings!$B:$B,B8,Meetings!$D:$D,"Booked")>0,"Booked",IF(COUNTIFS(Meetings!$B:$B,B8,Meetings!$D:$D,"Completed")>0,"Completed",IF(COUNTIFS(Meetings!$B:$B,B8,Meetings!$D:$D,"Requested")>0,"Requested","Targeted"))) -> Targeted | J8: =COUNTIF('Live Capture'!$E:$E,B8) -> 0 | K8: =COUNTIFS('Live Capture'!$E:$E,B8,'Live Capture'!$W:$W,"HOT") -> 0 | L8: =COUNTIFS('Live Capture'!$E:$E,B8,'Live Capture'!$S:$S,"<="&TODAY(),'Live Capture'!$X:$X,"<>Closed") -> 0 | M8: =IFERROR(maxifs(Activities!$A:$A,Activities!$B:$B,B8),"") -> 0
A9: ='Top 20 Board'!A6 -> 5 | B9: ='Top 20 Board'!B6 -> Hormel Foods | C9: ='Top 20 Board'!D6 -> Tier 2 | D9: ='Top 20 Board'!E6 -> Will Bonifant | Group Vice President and Chief Supply Chain Officer | E9: ='Top 20 Board'!F6 -> Nicholas Schwartz | Supply Chain Planning COE & Strategy Lead | F9: ='Top 20 Board'!H6 -> Board / network research | G9: {=IFERROR(INDEX('Graphic Assets'!$G:$G,MATCH(B9,'Graphic Assets'!$A:$A,0)),"Infographic")} -> Infographic | H9: {=IFERROR(INDEX('Account Dossiers'!$N:$N,MATCH(B9,'Account Dossiers'!$B:$B,0)),"")} -> Lead with transformation timing and hunt operator-level logistics / plant-network leaders under the new CSCO. | I9: =IF(COUNTIFS(Meetings!$B:$B,B9,Meetings!$D:$D,"Booked")>0,"Booked",IF(COUNTIFS(Meetings!$B:$B,B9,Meetings!$D:$D,"Completed")>0,"Completed",IF(COUNTIFS(Meetings!$B:$B,B9,Meetings!$D:$D,"Requested")>0,"Requested","Targeted"))) -> Targeted | J9: =COUNTIF('Live Capture'!$E:$E,B9) -> 0 | K9: =COUNTIFS('Live Capture'!$E:$E,B9,'Live Capture'!$W:$W,"HOT") -> 0 | L9: =COUNTIFS('Live Capture'!$E:$E,B9,'Live Capture'!$S:$S,"<="&TODAY(),'Live Capture'!$X:$X,"<>Closed") -> 0 | M9: =IFERROR(maxifs(Activities!$A:$A,Activities!$B:$B,B9),"") -> 0
A10: ='Top 20 Board'!A7 -> 5 | B10: ='Top 20 Board'!B7 -> JM Smucker | C10: ='Top 20 Board'!D7 -> Tier 2 | D10: ='Top 20 Board'!E7 -> Rob Ferguson | Chief Product Supply Officer | Executive Vice President, Coffee, Pet, and Away From Home | E10: ='Top 20 Board'!F7 -> Anbu Kuppusamy | Transportation Function Leader | F10: ='Top 20 Board'!H7 -> Board / network research | G10: {=IFERROR(INDEX('Graphic Assets'!$G:$G,MATCH(B10,'Graphic Assets'!$A:$A,0)),"Infographic")} -> Infographic | H10: {=IFERROR(INDEX('Account Dossiers'!$N:$N,MATCH(B10,'Account Dossiers'!$B:$B,0)),"")} -> Target Rob Ferguson plus operator lieutenants; pitch network consistency, throughput, and execution control. | I10: =IF(COUNTIFS(Meetings!$B:$B,B10,Meetings!$D:$D,"Booked")>0,"Booked",IF(COUNTIFS(Meetings!$B:$B,B10,Meetings!$D:$D,"Completed")>0,"Completed",IF(COUNTIFS(Meetings!$B:$B,B10,Meetings!$D:$D,"Requested")>0,"Requested","Targeted"))) -> Targeted | J10: =COUNTIF('Live Capture'!$E:$E,B10) -> 0 | K10: =COUNTIFS('Live Capture'!$E:$E,B10,'Live Capture'!$W:$W,"HOT") -> 0 | L10: =COUNTIFS('Live Capture'!$E:$E,B10,'Live Capture'!$S:$S,"<="&TODAY(),'Live Capture'!$X:$X,"<>Closed") -> 0 | M10: =IFERROR(maxifs(Activities!$A:$A,Activities!$B:$B,B10),"") -> 0
A11: ='Top 20 Board'!A8 -> 9 | B11: ='Top 20 Board'!B8 -> The Home Depot | C11: ='Top 20 Board'!D8 -> Tier 2 | D11: ='Top 20 Board'!E8 -> John Deaton | Executive Vice President – Supply Chain & Product Development | E11: ='Top 20 Board'!F8 -> Amit Kalra | Senior Vice President – Supply Chain | F11: ='Top 20 Board'!H8 -> MODEX keynote proximity + ecosystem intros | G11: {=IFERROR(INDEX('Graphic Assets'!$G:$G,MATCH(B11,'Graphic Assets'!$A:$A,0)),"Infographic")} -> Infographic | H11: {=IFERROR(INDEX('Account Dossiers'!$N:$N,MATCH(B11,'Account Dossiers'!$B:$B,0)),"")} -> Prioritize attendee-hunt around keynote orbit; target McPhail-adjacent supply-chain leaders and transportation operators. | I11: =IF(COUNTIFS(Meetings!$B:$B,B11,Meetings!$D:$D,"Booked")>0,"Booked",IF(COUNTIFS(Meetings!$B:$B,B11,Meetings!$D:$D,"Completed")>0,"Completed",IF(COUNTIFS(Meetings!$B:$B,B11,Meetings!$D:$D,"Requested")>0,"Requested","Targeted"))) -> Targeted | J11: =COUNTIF('Live Capture'!$E:$E,B11) -> 0 | K11: =COUNTIFS('Live Capture'!$E:$E,B11,'Live Capture'!$W:$W,"HOT") -> 0 | L11: =COUNTIFS('Live Capture'!$E:$E,B11,'Live Capture'!$S:$S,"<="&TODAY(),'Live Capture'!$X:$X,"<>Closed") -> 0 | M11: =IFERROR(maxifs(Activities!$A:$A,Activities!$B:$B,B11),"") -> 0
A12: ='Top 20 Board'!A9 -> 10 | B12: ='Top 20 Board'!B9 -> Georgia Pacific | C12: ='Top 20 Board'!D9 -> Tier 2 | D12: ='Top 20 Board'!E9 -> Jeremy Finley | Vice President, Supply Chain | E12: ='Top 20 Board'!F9 -> Ryan Hutcherson | Senior Vice President, Supply Chain | F12: ='Top 20 Board'!H9 -> LinkedIn + website research | G12: {=IFERROR(INDEX('Graphic Assets'!$G:$G,MATCH(B12,'Graphic Assets'!$A:$A,0)),"Infographic")} -> Infographic | H12: {=IFERROR(INDEX('Account Dossiers'!$N:$N,MATCH(B12,'Account Dossiers'!$B:$B,0)),"")} -> Run a plant-ops / logistics hunt around Palatka specifically, not just corporate GP. | I12: =IF(COUNTIFS(Meetings!$B:$B,B12,Meetings!$D:$D,"Booked")>0,"Booked",IF(COUNTIFS(Meetings!$B:$B,B12,Meetings!$D:$D,"Completed")>0,"Completed",IF(COUNTIFS(Meetings!$B:$B,B12,Meetings!$D:$D,"Requested")>0,"Requested","Targeted"))) -> Targeted | J12: =COUNTIF('Live Capture'!$E:$E,B12) -> 0 | K12: =COUNTIFS('Live Capture'!$E:$E,B12,'Live Capture'!$W:$W,"HOT") -> 0 | L12: =COUNTIFS('Live Capture'!$E:$E,B12,'Live Capture'!$S:$S,"<="&TODAY(),'Live Capture'!$X:$X,"<>Closed") -> 0 | M12: =IFERROR(maxifs(Activities!$A:$A,Activities!$B:$B,B12),"") -> 0
A13: ='Top 20 Board'!A10 -> 11 | B13: ='Top 20 Board'!B10 -> H-E-B | C13: ='Top 20 Board'!D10 -> Tier 2 | D13: ='Top 20 Board'!E10 -> Dakota Socha | Transportation & Reverse Logistics | E13: ='Top 20 Board'!F10 -> Craig Stucker | Director, Parkway Transport at H-E-B | F13: ='Top 20 Board'!H10 -> LinkedIn + grocery ops network | G13: {=IFERROR(INDEX('Graphic Assets'!$G:$G,MATCH(B13,'Graphic Assets'!$A:$A,0)),"Infographic")} -> Infographic | H13: {=IFERROR(INDEX('Account Dossiers'!$N:$N,MATCH(B13,'Account Dossiers'!$B:$B,0)),"")} -> Prioritize North Texas supply-chain and transportation leaders; hunt for eFC and campus-development operators. | I13: =IF(COUNTIFS(Meetings!$B:$B,B13,Meetings!$D:$D,"Booked")>0,"Booked",IF(COUNTIFS(Meetings!$B:$B,B13,Meetings!$D:$D,"Completed")>0,"Completed",IF(COUNTIFS(Meetings!$B:$B,B13,Meetings!$D:$D,"Requested")>0,"Requested","Targeted"))) -> Targeted | J13: =COUNTIF('Live Capture'!$E:$E,B13) -> 0 | K13: =COUNTIFS('Live Capture'!$E:$E,B13,'Live Capture'!$W:$W,"HOT") -> 0 | L13: =COUNTIFS('Live Capture'!$E:$E,B13,'Live Capture'!$S:$S,"<="&TODAY(),'Live Capture'!$X:$X,"<>Closed") -> 0 | M13: =IFERROR(maxifs(Activities!$A:$A,Activities!$B:$B,B13),"") -> 0
A14: ='Top 20 Board'!A11 -> 13 | B14: ='Top 20 Board'!B11 -> Hyundai Motor America | C14: ='Top 20 Board'!D11 -> Tier 3 | D14: ='Top 20 Board'!E11 -> Carey Gammon | Director, Vehicle Operations (HMA) | E14: ='Top 20 Board'!F11 -> Yongchul Chung | Senior Manager, Global Logistics & Supply Chain | F14: ='Top 20 Board'!H11 -> Automotive logistics network research | G14: {=IFERROR(INDEX('Graphic Assets'!$G:$G,MATCH(B14,'Graphic Assets'!$A:$A,0)),"Infographic")} -> Infographic | H14: {=IFERROR(INDEX('Account Dossiers'!$N:$N,MATCH(B14,'Account Dossiers'!$B:$B,0)),"")} -> Hunt logistics and supply-chain managers tied to U.S. localization, parts flow, and distribution execution. | I14: =IF(COUNTIFS(Meetings!$B:$B,B14,Meetings!$D:$D,"Booked")>0,"Booked",IF(COUNTIFS(Meetings!$B:$B,B14,Meetings!$D:$D,"Completed")>0,"Completed",IF(COUNTIFS(Meetings!$B:$B,B14,Meetings!$D:$D,"Requested")>0,"Requested","Targeted"))) -> Targeted | J14: =COUNTIF('Live Capture'!$E:$E,B14) -> 0 | K14: =COUNTIFS('Live Capture'!$E:$E,B14,'Live Capture'!$W:$W,"HOT") -> 0 | L14: =COUNTIFS('Live Capture'!$E:$E,B14,'Live Capture'!$S:$S,"<="&TODAY(),'Live Capture'!$X:$X,"<>Closed") -> 0 | M14: =IFERROR(maxifs(Activities!$A:$A,Activities!$B:$B,B14),"") -> 0
